Workbook
Name _1_DtG: #REF!
Name _1_DtG: #REF!
Name _1_DtG: #REF!
Name actSheetName: "Manual Contract extract"
Name divgrp: #REF!
Name divgrp: #REF!
Name divgrp: #REF!
Name divgrp1: #REF!
Name divgrp1: #REF!
Name divlst: #REF!
Name HlookupDTG: #REF!
Name majgrp: #REF!
Name majgrp: #REF!
Name majgrp: #REF!
Name majgrpp: #REF!
Name majgrpp: #REF!
Name majlst: #REF!
Name tm1\\_0_C: 'FIRM Load Pull'!$E$9:$R$12
Name tm1\\_0_H: "{ ""server"" : ""https://paprd-wdc1-apexpaw-01.limited-use.ibm.com"", ""cube"" : ""{ \""server\"" : \""loadtgts\"", \""cube\"" : \""loadtgts\""}""}"
Name tm1\\_0_H_1: "{ ""server"" : ""https://b01acidbc002.ahe.pok.ibm.com:9514"", ""cube"" : ""{ \""server\"" : \""loadtgts\"", \""cube\"" : \""streamload\""}"", ""CubeCaption"" : ""streamload""}"
Name tm1\\_0_H_2: "{ ""server"" : ""https://prdpaw01.sl.bluecloud.ibm.com"", ""cube"" : ""{ \""server\"" : \""loadtgts\"", \""cube\"" : \""streamload\""}"", ""CubeCaption"" : ""streamload""}"
Name tm1\\_0_R: 'FIRM Load Pull'!$C$13:$D$146
Name tm1\\_0_S: 'FIRM Load Pull'!$C$4:$C$8
Name tm1\\_1_C: graph!$D$11:$AD$14
Name tm1\\_1_H: "{ ""server"" : ""https://paprd-wdc1-apexpaw-01.limited-use.ibm.com"", ""cube"" : ""{ \""server\"" : \""loadtgts\"", \""cube\"" : \""loadtgts\""}""}"
Name tm1\\_1_H_1: "{ ""server"" : ""https://b01acidbc002.ahe.pok.ibm.com:9514"", ""cube"" : ""{ \""server\"" : \""loadtgts\"", \""cube\"" : \""streamload\""}"", ""CubeCaption"" : ""streamload""}"
Name tm1\\_1_H_2: "{ ""server"" : ""https://prdpaw01.sl.bluecloud.ibm.com"", ""cube"" : ""{ \""server\"" : \""loadtgts\"", \""cube\"" : \""streamload\""}"", ""CubeCaption"" : ""streamload""}"
Name tm1\\_1_R: graph!$B$15:$C$15
Name tm1\\_1_S: graph!$B$6:$B$10
Name tm1\\_10_C: 'Tracks Pull'!$X$9:$BZ$12
Name tm1\\_10_H: "{ ""server"" : ""https://paprd-wdc1-apexpaw-01.limited-use.ibm.com"", ""cube"" : ""{ \""server\"" : \""loadtgts\"", \""cube\"" : \""tks_tgts\""}""}"
Name tm1\\_10_H_1: "{ ""server"" : ""https://b01acidbc002.ahe.pok.ibm.com:9514"", ""cube"" : ""{ \""server\"" : \""loadtgts\"", \""cube\"" : \""loadtgts\""}"", ""CubeCaption"" : ""loadtgts""}"
Name tm1\\_10_H_2: "{ ""server"" : ""https://prdpaw01.sl.bluecloud.ibm.com"", ""cube"" : ""{ \""server\"" : \""loadtgts\"", \""cube\"" : \""loadtgts\""}"", ""CubeCaption"" : ""loadtgts""}"
Name tm1\\_10_R: 'Tracks Pull'!$U$13:$W$135
Name tm1\\_10_S: 'Tracks Pull'!$V$4:$V$7
Name tm1\\_100_C: #REF!
Name tm1\\_100_R: #REF!
Name tm1\\_101_C: #REF!
Name tm1\\_101_R: #REF!
Name tm1\\_102_H: "{ ""server"" : ""https://prdpaw01.sl.bluecloud.ibm.com"", ""cube"" : ""{ \""server\"" : \""loadtgts\"", \""cube\"" : \""loadtgts\""}""}"
Name tm1\\_103_C: #REF!
Name tm1\\_103_H: "{ ""server"" : ""https://prdpaw03.sl.bluecloud.ibm.com"", ""cube"" : ""{ \""server\"" : \""wwconsol\"", \""cube\"" : \""wwconsol\""}""}"
Name tm1\\_103_R: #REF!
Name tm1\\_104_C: #REF!
Name tm1\\_104_R: #REF!
Name tm1\\_105_C: #REF!
Name tm1\\_105_R: #REF!
Name tm1\\_106_C: #REF!
Name tm1\\_106_R: #REF!
Name tm1\\_107_C: #REF!
Name tm1\\_107_R: #REF!
Name tm1\\_108_C: #REF!
Name tm1\\_108_H: "{ ""server"" : ""https://b01acidbc005.ahe.pok.ibm.com:9514"", ""cube"" : ""{ \""server\"" : \""wwconsol\"", \""cube\"" : \""wwconsol\""}"", ""CubeCaption"" : ""wwconsol""}"
Name tm1\\_108_R: #REF!
Name tm1\\_109_C: #REF!
Name tm1\\_109_R: #REF!
Name tm1\\_11_H_1: "{ ""server"" : ""https://b01acidbc002.ahe.pok.ibm.com:9514"", ""cube"" : ""{ \""server\"" : \""loadtgts\"", \""cube\"" : \""loadtgts\""}"", ""CubeCaption"" : ""loadtgts""}"
Name tm1\\_11_H_2: "{ ""server"" : ""https://prdpaw01.sl.bluecloud.ibm.com"", ""cube"" : ""{ \""server\"" : \""loadtgts\"", \""cube\"" : \""loadtgts\""}"", ""CubeCaption"" : ""loadtgts""}"
Name tm1\\_110_C: #REF!
Name tm1\\_110_H: "{ ""server"" : ""https://b01acidbc002.ahe.pok.ibm.com:9514"", ""cube"" : ""{ \""server\"" : \""loadtgts\"", \""cube\"" : \""loadtgts\""}"", ""CubeCaption"" : ""loadtgts""}"

Sheet Cognos_Office_Connection_Cache

Sheet Summary page
B3: =CONCATENATE(INPUT!B2,INPUT!B1," Firm Load") -> 4Q25 Firm Load | E3: =CONCATENATE(INPUT!B2,INPUT!B1," Retail Load") -> 4Q25 Retail Load | L3: =CONCATENATE(INPUT!B2,INPUT!B1,"QTD Firm Load") -> 4Q25QTD Firm Load | O3: =CONCATENATE(INPUT!B2,INPUT!B1,"QTD Retail Load") -> 4Q25QTD Retail Load
B5: =WW!H9 -> 448.58962 | E5: =WW!#REF! -> #REF! | H5: =E5-743-18 -> #REF! | L5: =WW!H49 -> 326.86944 | O5: =WW!#REF! -> #REF! | R5: =O5-743 -> #REF!
B6: Rev $m | E6: Rev $m | L6: Rev $m | O6: Rev $m
B7: =WW!K9 -> 0.15984053 | C7: YtY | E7: =WW!#REF! -> #REF! | F7: YtY | L7: =WW!K49 -> 0.54610409 | M7: YtY | O7: =WW!#REF! -> #REF! | P7: YtY
B8: =WW!S9 -> -217.51703 | C8: B/(W) Tracks | E8: =WW!#REF! -> #REF! | F8: B/(W) Tracks | L8: =WW!S49 -> -339.21199 | M8: B/(W) Tracks | O8: =WW!#REF! -> #REF! | P8: B/(W) Tracks
B12: =CONCATENATE(INPUT!B2,INPUT!B1," Non HW") -> 4Q25 Non HW | E12: =CONCATENATE(INPUT!B2,INPUT!B1," Total Load") -> 4Q25 Total Load | L12: =CONCATENATE(INPUT!B2,INPUT!B1,"QTD Non HW") -> 4Q25QTD Non HW | O12: =CONCATENATE(INPUT!B2,INPUT!B1,"QTD Total Load") -> 4Q25QTD Total Load
B14: =WW!Z9 -> 581.21483 | E14: =WW!AD9 -> 1029.8044 | L14: =WW!Z49 -> 432.76636 | O14: =WW!AD49 -> 759.6358
B15: Rev $m | E15: Rev $m | L15: Rev $m | O15: Rev $m
E16: =WW!AE9 -> -0.63715343 | F16: YtY | O16: =WW!AE49 -> 0.1944096 | P16: YtY
B17: =WW!AF9 -> -2256.5531 | C17: B/(W) Budget | E17: =WW!AF9 -> -2256.5531 | F17: B/(W) Budget | L17: =WW!AB49 -> 145.98805 | M17: B/(W) Budget | O17: =WW!AF49 -> 143.47589 | P17: B/(W) Budget

Sheet graph
A6: 1 | B6: [Base]
B7: TotLoad
B8: Unit of Measure
B9: Industry | G9: MTH1 | K9: MTH2 | P9: 1Q
B10: data | D10: WK1 | E10: WK2 | F10: WK3 | G10: WK4 | H10: WK5 | I10: WK6 | J10: WK7 | K10: WK8 | L10: WK9 | M10: WK10 | N10: WK11 | O10: WK12 | P10: WK13 | R10: WK1 | S10: WK2 | T10: WK3 | U10: WK4 | V10: WK5 | W10: WK6 | X10: WK7 | Y10: WK8 | Z10: WK9 | AA10: WK10 | AB10: WK11 | AC10: WK12 | AD10: WK13
D11: Channel Total | E11: Channel Total | F11: Channel Total | G11: Channel Total | H11: Channel Total | I11: Channel Total | J11: Channel Total | K11: Channel Total | L11: Channel Total | M11: Channel Total | N11: Channel Total | O11: Channel Total | P11: Channel Total | R11: Channel Total | S11: Channel Total | T11: Channel Total | U11: Channel Total | V11: Channel Total | W11: Channel Total | X11: Channel Total | Y11: Channel Total | Z11: Channel Total | AA11: Channel Total | AB11: Channel Total | AC11: Channel Total | AD11: Channel Total
D12: 4Q | E12: 4Q | F12: 4Q | G12: 4Q | H12: 4Q | I12: 4Q | J12: 4Q | K12: 4Q | L12: 4Q | M12: 4Q | N12: 4Q | O12: 4Q | P12: 4Q | R12: 4Q | S12: 4Q | T12: 4Q | U12: 4Q | V12: 4Q | W12: 4Q | X12: 4Q | Y12: 4Q | Z12: 4Q | AA12: 4Q | AB12: 4Q | AC12: 4Q | AD12: 4Q
D13: Daily Firm | E13: =D13 -> Daily Firm | F13: =D13 -> Daily Firm | G13: =D13 -> Daily Firm | H13: =G13 -> Daily Firm | I13: =H13 -> Daily Firm | J13: Daily Firm | K13: =J13 -> Daily Firm | L13: =J13 -> Daily Firm | M13: =J13 -> Daily Firm | N13: =M13 -> Daily Firm | O13: =N13 -> Daily Firm | P13: =O13 -> Daily Firm | R13: Daily Load | S13: =R13 -> Daily Load | T13: =R13 -> Daily Load | U13: =R13 -> Daily Load | V13: =U13 -> Daily Load | W13: =V13 -> Daily Load | X13: Daily Firm | Y13: =X13 -> Daily Firm | Z13: =X13 -> Daily Firm | AA13: =X13 -> Daily Firm | AB13: =AA13 -> Daily Firm | AC13: =AA13 -> Daily Firm | AD13: =AB13 -> Daily Firm
D14: Ld100424 | E14: Ld101124 | F14: Ld101824 | G14: Ld102524 | H14: Ld110124 | I14: Ld110824 | J14: Ld111524 | K14: Ld112224 | L14: Ld112924 | M14: Ld120624 | N14: Ld121324 | O14: Ld122024 | P14: Ld4Q24Final | R14: Ld100424 | S14: Ld101124 | T14: Ld101824 | U14: Ld102524 | V14: Ld110124 | W14: Ld110824 | X14: Ld111524 | Y14: Ld112224 | Z14: Ld112924 | AA14: Ld120624 | AB14: Ld121324 | AC14: Ld122024 | AD14: Ld4Q24Final
B15: EG | C15: WW-Worldwide | D15: 0 | E15: 96.998332 | F15: 155.97591 | G15: 203.79163 | H15: 305.16829 | I15: 347.00735 | J15: 397.70233 | K15: 508.92735 | L15: 743.93306 | M15: 797.41309 | N15: 997.54391 | O15: 1512.7427 | P15: 2268.954 | R15: 0 | S15: 612.21655 | T15: 661.00777 | U15: 791.23819 | V15: 1115.4992 | W15: 1441.6635 | X15: 397.70233 | Y15: 508.92735 | Z15: 743.93306 | AA15: 797.41309 | AB15: 997.54391 | AC15: 1512.7427 | AD15: 2268.954
C17: Rev $m | D17: WK1 | E17: WK2 | F17: WK3 | G17: WK4 | H17: WK5 | I17: WK6 | J17: WK7 | K17: WK8 | L17: WK9 | M17: WK10 | N17: WK11 | O17: WK12 | P17: WK13 | Q17: Rev $m | R17: WK1 | S17: WK2 | T17: WK3 | U17: WK4 | V17: WK5 | W17: WK6 | X17: WK7 | Y17: WK8 | Z17: WK9 | AA17: WK10 | AB17: WK11 | AC17: WK12 | AD17: WK13
C18: Firm Load | D18: =D15 -> 0 | E18: =E15 -> 96.998332 | F18: =F15 -> 155.97591 | G18: =G15 -> 203.79163 | H18: =H15 -> 305.16829 | I18: =I15 -> 347.00735 | J18: =J15 -> 397.70233 | K18: =K15 -> 508.92735 | ... P18: =P15 -> 2268.954 | Q18: Retail Load | R18: =R15 -> 0 | S18: =S15 -> 612.21655 | T18: =T15 -> 661.00777 | U18: =U15 -> 791.23819 | V18: =V15 -> 1115.4992 | W18: =W15 -> 1441.6635 | X18: =X15 -> 397.70233 | Y18: =Y15 -> 508.92735 | ... AD18: =AD15 -> 2268.954
C19: Firm Tracks | D19: ='Tracks Pull'!X107 -> 146.22327 | E19: ='Tracks Pull'!Y107 -> 210.57539 | F19: ='Tracks Pull'!Z107 -> 281.1178 | G19: ='Tracks Pull'!AA107 -> 346.47533 | H19: ='Tracks Pull'!AB107 -> 448.17493 | I19: ='Tracks Pull'!AC107 -> 532.44686 | J19: ='Tracks Pull'!AD107 -> 660.58244 | K19: ='Tracks Pull'!AE107 -> 870.20815 | ... P19: ='Tracks Pull'!AJ107 -> 2701.9326 | Q19: Retail Tracks | R19: ='Tracks Pull'!AZ107 -> 146.22327 | S19: ='Tracks Pull'!BA107 -> 210.57539 | T19: ='Tracks Pull'!BB107 -> 281.1178 | U19: ='Tracks Pull'!BC107 -> 346.47533 | V19: ='Tracks Pull'!BD107 -> 448.17493 | W19: ='Tracks Pull'!BE107 -> 532.44686 | X19: ='Tracks Pull'!BF107 -> 660.58244 | Y19: ='Tracks Pull'!BG107 -> 870.20815 | ... AD19: ='Tracks Pull'!BL107 -> 2701.9326
A22: 2 | C22: Firm Load by brand | F22: Retail Load by brand
C23: =WW!C10 -> Traditional z | D23: =WW!H10 -> 129.49898 | F23: =WW!C10 -> Traditional z | G23: =WW!#REF! -> #REF!
C24: =WW!C11 -> Power HW | D24: =WW!H11 -> 79.56673 | F24: =WW!C11 -> Power HW | G24: =WW!#REF! -> #REF!
C25: =WW!C12 -> Storage HW | D25: =WW!H12 -> 233.99971 | F25: =WW!C12 -> Storage HW | G25: =WW!#REF! -> #REF!
C26: GARS | D26: =WW!H14 -> 5.5241986 | F26: GARS | G26: =WW!#REF! -> #REF!
A29: 3 | C29: Firm Load by Geo | F29: Retail Load by Geo
C30: =WW!C18 -> Americas | D30: =WW!H18 -> 166.08077 | F30: =WW!C18 -> Americas | G30: =WW!#REF! -> #REF!
C31: =WW!C19 -> EMEA | D31: =WW!H19 -> 173.31338 | F31: =WW!C19 -> EMEA | G31: =WW!#REF! -> #REF!
C32: =WW!C20 -> Japan | D32: =WW!H20 -> 60.107739 | F32: =WW!C20 -> Japan | G32: =WW!#REF! -> #REF!
C33: =WW!C21 -> APAC | D33: =WW!H21 -> 43.563528 | F33: =WW!C21 -> APAC | G33: =WW!#REF! -> #REF!
C34: WW Top+GARS | D34: =WW!H22 -> 5.5241986 | F34: WW Top+GARS | G34: =WW!#REF! -> #REF!

Sheet Ref
C1: HWLoad Daily Reporting
C3: Reference Table Market Report | I3: IBM Confidential
A5: LOADCASES YTY/QTQ | L5: LOADCASES DTG/PROJECTION
F6: LOADCASES | L6: 1 | M6: =+L6+1 -> 2 | N6: =+M6+1 -> 3 | O6: =+N6+1 -> 4 | P6: =+O6+1 -> 5 | Q6: =+P6+1 -> 6 | R6: =+Q6+1 -> 7 | S6: =+R6+1 -> 8 | T6: =+S6+1 -> 9
A7: CURR_DATE | B7: CURR_QTR | C7: CURR_MTH | D7: CURR_WK | E7: CURR_DAY | F7: CURR | G7: PY | H7: PPY | I7: PQ | J7: MF_PP1 | K7: MF_PP2 | L7: CurMth&DTG | M7: CURR_DATE | N7: DTG | O7: PY | P7: PPY | Q7: CD | R7: PD | S7: PW | T7: PY
A8: 2025-10-07 | B8: 4 | C8: 10 | D8: 2 | E8: 1 | F8: LD100625 | G8: LD070824 | H8: LD101022 | I8: LD070824 | J8: LD100923 | K8: LD101022 | L8: =C8&N8 -> 1018 | M8: =A8 -> 2025-10-07 | N8: 18 | O8: LD100424 | P8: LD100423 | Q8: =F8 -> LD100625 | W8: 2025-10-07 | X8: =W8-A8 -> 0 | Y8: LD100424 | Z8: LD100423
A9: 2025-10-08 | B9: 4 | C9: 10 | D9: 2 | E9: 2 | F9: LD100725 | G9: LD070924 | H9: LD101122 | I9: LD070924 | J9: LD101023 | K9: LD101122 | L9: =C9&N9 -> 1017 | M9: =A9 -> 2025-10-08 | N9: 17 | O9: LD100724 | P9: LD100523 | Q9: =F9 -> LD100725 | R9: =Q8 -> LD100625 | W9: 2025-10-08 | X9: =W9-A9 -> 0 | Y9: LD100724 | Z9: LD100523
A10: 2025-10-09 | B10: 4 | C10: 10 | D10: 2 | E10: 3 | F10: LD100825 | G10: LD071024 | H10: LD101222 | I10: LD071024 | J10: LD101123 | K10: LD101222 | L10: =C10&N10 -> 1016 | M10: =A10 -> 2025-10-09 | N10: 16 | O10: LD100824 | P10: LD100623 | Q10: =F10 -> LD100825 | R10: =Q9 -> LD100725 | W10: 2025-10-09 | X10: =W10-A10 -> 0 | Y10: LD100824 | Z10: LD100623
A11: 2025-10-10 | B11: 4 | C11: 10 | D11: 2 | E11: 4 | F11: LD100925 | G11: LD071124 | H11: LD101322 | I11: LD071124 | J11: LD101223 | K11: LD101322 | L11: =C11&N11 -> 1015 | M11: =A11 -> 2025-10-10 | N11: 15 | O11: LD100924 | P11: LD100923 | Q11: =F11 -> LD100925 | R11: =Q10 -> LD100825 | W11: 2025-10-10 | X11: =W11-A11 -> 0 | Y11: LD100924 | Z11: LD100923
A12: 2025-10-13 | B12: 4 | C12: 10 | D12: 2 | E12: 5 | F12: LD101025 | G12: LD071224 | H12: LD011023 | I12: LD071224 | J12: LD101323 | K12: LD101422 | L12: =C12&N12 -> 1014 | M12: =A12 -> 2025-10-13 | N12: 14 | O12: LD101024 | P12: LD101023 | Q12: =F12 -> LD101025 | R12: =Q11 -> LD100925 | S12: LD070425 | T12: =+O12 -> LD101024 | W12: 2025-10-13 | X12: =W12-A12 -> 0 | Y12: LD101024 | Z12: LD101023
A13: 2025-10-14 | B13: 4 | C13: 10 | D13: 3 | E13: 1 | F13: LD101325 | G13: LD071524 | H13: LD101722 | I13: LD071524 | J13: LD101623 | K13: LD101722 | L13: =C13&N13 -> 1013 | M13: =A13 -> 2025-10-14 | N13: 13 | O13: LD101124 | P13: LD101123 | Q13: =F13 -> LD101325 | R13: =Q12 -> LD101025 | S13: =Q12 -> LD101025 | T13: =+O13 -> LD101124 | W13: 2025-10-14 | X13: =W13-A13 -> 0 | Y13: LD101124 | Z13: LD101123
A14: 2025-10-15 | B14: 4 | C14: 10 | D14: 3 | E14: 2 | F14: LD101425 | G14: LD071624 | H14: LD101822 | I14: LD071624 | J14: LD101723 | K14: LD101822 | L14: =C14&N14 -> 1012 | M14: =A14 -> 2025-10-15 | N14: 12 | O14: LD101424 | P14: LD101223 | Q14: =F14 -> LD101425 | R14: =Q13 -> LD101325 | S14: =S13 -> LD101025 | T14: =+O14 -> LD101424 | W14: 2025-10-15 | X14: =W14-A14 -> 0 | Y14: LD101424 | Z14: LD101223
A15: 2025-10-16 | B15: 4 | C15: 10 | D15: 3 | E15: 3 | F15: LD101525 | G15: LD071724 | H15: LD101922 | I15: LD071724 | J15: LD101823 | K15: LD101922 | L15: =C15&N15 -> 1011 | M15: =A15 -> 2025-10-16 | N15: 11 | O15: LD101524 | P15: LD101323 | Q15: =F15 -> LD101525 | R15: =Q14 -> LD101425 | S15: =S14 -> LD101025 | T15: =+O15 -> LD101524 | W15: 2025-10-16 | X15: =W15-A15 -> 0 | Y15: LD101524 | Z15: LD101323
A16: 2025-10-17 | B16: 4 | C16: 10 | D16: 3 | E16: 4 | F16: LD101625 | G16: LD071824 | H16: LD102022 | I16: LD071824 | J16: LD101923 | K16: LD102022 | L16: =C16&N16 -> 1010 | M16: =A16 -> 2025-10-17 | N16: 10 | O16: LD101624 | P16: LD101623 | Q16: =F16 -> LD101625 | R16: =Q15 -> LD101525 | S16: =S15 -> LD101025 | T16: =+O16 -> LD101624 | W16: 2025-10-17 | X16: =W16-A16 -> 0 | Y16: LD101624 | Z16: LD101623
A17: 2025-10-20 | B17: 4 | C17: 10 | D17: 3 | E17: 5 | F17: LD101725 | G17: LD071924 | H17: LD011723 | I17: LD071924 | J17: LD102023 | K17: LD102122 | L17: =C17&N17 -> 109 | M17: =A17 -> 2025-10-20 | N17: 9 | O17: LD101724 | P17: LD101723 | Q17: =F17 -> LD101725 | R17: =Q16 -> LD101625 | S17: =S16 -> LD101025 | T17: =+O17 -> LD101724 | W17: 2025-10-20 | X17: =W17-A17 -> 0 | Y17: LD101724 | Z17: LD101723
A18: 2025-10-21 | B18: 4 | C18: 10 | D18: 4 | E18: 1 | F18: LD102025 | G18: LD072224 | H18: LD102422 | I18: LD072224 | J18: LD102323 | K18: LD102422 | L18: =C18&N18 -> 108 | M18: =A18 -> 2025-10-21 | N18: 8 | O18: LD101824 | P18: LD101823 | Q18: =F18 -> LD102025 | R18: =Q17 -> LD101725 | S18: =Q17 -> LD101725 | T18: =+O18 -> LD101824 | W18: 2025-10-21 | X18: =W18-A18 -> 0 | Y18: LD101824 | Z18: LD101823
A19: 2025-10-22 | B19: 4 | C19: 10 | D19: 4 | E19: 2 | F19: LD102125 | G19: LD072324 | H19: LD102522 | I19: LD072324 | J19: LD102423 | K19: LD102522 | L19: =C19&N19 -> 107 | M19: =A19 -> 2025-10-22 | N19: 7 | O19: LD102124 | P19: LD101923 | Q19: =F19 -> LD102125 | R19: =Q18 -> LD102025 | S19: =S18 -> LD101725 | T19: =+O19 -> LD102124 | W19: 2025-10-22 | X19: =W19-A19 -> 0 | Y19: LD102124 | Z19: LD101923
A20: 2025-10-23 | B20: 4 | C20: 10 | D20: 4 | E20: 3 | F20: LD102225 | G20: LD072424 | H20: LD102622 | I20: LD072424 | J20: LD102523 | K20: LD102622 | L20: =C20&N20 -> 106 | M20: =A20 -> 2025-10-23 | N20: 6 | O20: LD102224 | P20: LD102023 | Q20: =F20 -> LD102225 | R20: =Q19 -> LD102125 | S20: =S19 -> LD101725 | T20: =+O20 -> LD102224 | W20: 2025-10-23 | X20: =W20-A20 -> 0 | Y20: LD102224 | Z20: LD102023
A21: 2025-10-24 | B21: 4 | C21: 10 | D21: 4 | E21: 4 | F21: LD102325 | G21: LD072524 | H21: LD102722 | I21: LD072524 | J21: LD102623 | K21: LD102722 | L21: =C21&N21 -> 105 | M21: =A21 -> 2025-10-24 | N21: 5 | O21: LD102324 | P21: LD102323 | Q21: =F21 -> LD102325 | R21: =Q20 -> LD102225 | S21: =S20 -> LD101725 | T21: =+O21 -> LD102324 | W21: 2025-10-24 | X21: =W21-A21 -> 0 | Y21: LD102324 | Z21: LD102323
A22: 2025-10-27 | B22: 4 | C22: 10 | D22: 4 | E22: 5 | F22: LD102425 | G22: LD072624 | H22: LD012423 | I22: LD072624 | J22: LD102723 | K22: LD102822 | L22: =C22&N22 -> 104 | M22: =A22 -> 2025-10-27 | N22: 4 | O22: LD102424 | P22: LD102423 | Q22: =F22 -> LD102425 | R22: =Q21 -> LD102325 | S22: =S21 -> LD101725 | T22: =+O22 -> LD102424 | W22: 2025-10-27 | X22: =W22-A22 -> 0 | Y22: LD102424 | Z22: LD102423
A23: 2025-10-28 | B23: 4 | C23: 10 | D23: 5 | E23: 1 | F23: LD102725 | G23: LD072924 | H23: LD102822 | I23: LD072624 | J23: LD102723 | K23: LD102822 | L23: =C23&N23 -> 103 | M23: =A23 -> 2025-10-28 | N23: 3 | O23: LD102524 | P23: LD102523 | Q23: =F23 -> LD102725 | R23: =Q22 -> LD102425 | S23: =Q22 -> LD102425 | T23: =+O23 -> LD102524 | W23: 2025-10-28 | X23: =W23-A23 -> 0 | Y23: LD102524 | Z23: LD102523
A24: 2025-10-29 | B24: 4 | C24: 10 | D24: 5 | E24: 2 | F24: LD102825 | G24: LD073024 | H24: LD103122 | I24: LD072924 | J24: LD103023 | K24: LD103122 | L24: =C24&N24 -> 102 | M24: =A24 -> 2025-10-29 | N24: 2 | O24: LD102824 | P24: LD102623 | Q24: =F24 -> LD102825 | R24: =Q23 -> LD102725 | S24: =Q22 -> LD102425 | T24: =+O24 -> LD102824 | W24: 2025-10-29 | X24: =W24-A24 -> 0 | Y24: LD102824 | Z24: LD102623
A25: 2025-10-30 | B25: 4 | C25: 10 | D25: 5 | E25: 3 | F25: LD102925 | G25: LD073124 | H25: LD110122 | I25: LD073024 | J25: LD103123 | K25: LD110122 | L25: =C25&N25 -> 101 | M25: =A25 -> 2025-10-30 | N25: 1 | O25: LD102924 | P25: LD102723 | Q25: =F25 -> LD102925 | R25: =Q24 -> LD102825 | S25: =S24 -> LD102425 | T25: =+O25 -> LD102924 | W25: 2025-10-30 | X25: =W25-A25 -> 0 | Y25: LD102924 | Z25: LD102723
A26: 2025-10-31 | B26: 4 | C26: 10 | D26: 5 | E26: 4 | F26: LD103025 | G26: LD080124 | H26: LD110222 | I26: LD073124 | J26: LD110123 | K26: LD110222 | L26: =C26&N26 -> 100 | M26: =A26 -> 2025-10-31 | N26: 0 | O26: LD103024 | P26: LD103023 | Q26: =F26 -> LD103025 | R26: =Q25 -> LD102925 | S26: =S25 -> LD102425 | T26: =+O26 -> LD103024 | W26: 2025-10-31 | X26: =W26-A26 -> 0 | Y26: LD103024 | Z26: LD103023
A27: 2025-11-03 | B27: 4 | C27: 10 | D27: 5 | E27: 5 | F27: LD103125 | G27: LD080224 | H27: LD110322 | I27: LD080124 | J27: LD110223 | K27: LD110322 | L27: =C27&N27 -> 1020 | M27: =A27 -> 2025-11-03 | N27: 20 | O27: LD103124 | P27: LD103123 | Q27: =F27 -> LD103125 | R27: =Q26 -> LD103025 | S27: =S26 -> LD102425 | T27: =+O27 -> LD103124 | W27: 2025-11-03 | X27: =W27-A27 -> 0 | Y27: LD103124 | Z27: LD103123
A28: 2025-11-04 | B28: 4 | C28: 11 | D28: 6 | E28: 1 | F28: LD110325 | G28: LD080524 | H28: LD110422 | I28: LD080224 | J28: LD110323 | K28: LD110422 | L28: =C28&N28 -> 1119 | M28: =A28 -> 2025-11-04 | N28: 19 | O28: LD110424 | P28: LD110323 | Q28: =F28 -> LD110325 | R28: =Q27 -> LD103125 | S28: =Q27 -> LD103125 | T28: =+O28 -> LD110424 | W28: 2025-11-04 | X28: =W28-A28 -> 0 | Y28: LD110424 | Z28: LD110323
A29: 2025-11-05 | B29: 4 | C29: 11 | D29: 6 | E29: 2 | F29: LD110425 | G29: LD080624 | H29: LD110722 | I29: LD080524 | J29: LD110623 | K29: LD110722 | L29: =C29&N29 -> 1118 | M29: =A29 -> 2025-11-05 | N29: 18 | O29: LD110524 | P29: LD110623 | Q29: =F29 -> LD110425 | R29: =Q28 -> LD110325 | S29: =Q27 -> LD103125 | T29: =+O29 -> LD110524 | W29: 2025-11-05 | X29: =W29-A29 -> 0 | Y29: LD110524 | Z29: LD110623
A30: 2025-11-06 | B30: 4 | C30: 11 | D30: 6 | E30: 3 | F30: LD110525 | G30: LD080724 | H30: LD110822 | I30: LD080624 | J30: LD110723 | K30: LD110822 | L30: =C30&N30 -> 1117 | M30: =A30 -> 2025-11-06 | N30: 17 | O30: LD110624 | P30: LD110723 | Q30: =F30 -> LD110525 | R30: =Q29 -> LD110425 | S30: =S29 -> LD103125 | T30: =+O30 -> LD110624 | W30: 2025-11-06 | X30: =W30-A30 -> 0 | Y30: LD110624 | Z30: LD110723
A31: 2025-11-07 | B31: 4 | C31: 11 | D31: 6 | E31: 4 | F31: LD110625 | G31: LD080824 | H31: LD110922 | I31: LD080724 | J31: LD110823 | K31: LD110922 | L31: =C31&N31 -> 1116 | M31: =A31 -> 2025-11-07 | N31: 16 | O31: LD110724 | P31: LD110823 | Q31: =F31 -> LD110625 | R31: =Q30 -> LD110525 | S31: =S30 -> LD103125 | T31: =+O31 -> LD110724 | W31: 2025-11-07 | X31: =W31-A31 -> 0 | Y31: LD110724 | Z31: LD110823
A32: 2025-11-10 | B32: 4 | C32: 11 | D32: 6 | E32: 5 | F32: LD110725 | G32: LD080924 | H32: LD111022 | I32: LD080824 | J32: LD110923 | K32: LD111022 | L32: =C32&N32 -> 1115 | M32: =A32 -> 2025-11-10 | N32: 15 | O32: LD110824 | P32: LD110923 | Q32: =F32 -> LD110725 | R32: =Q31 -> LD110625 | S32: =S31 -> LD103125 | T32: =+O32 -> LD110824 | W32: 2025-11-10 | X32: =W32-A32 -> 0 | Y32: LD110824 | Z32: LD110923
A33: 2025-11-11 | B33: 4 | C33: 11 | D33: 7 | E33: 1 | F33: LD111025 | G33: LD081224 | H33: LD021023 | I33: LD080924 | J33: LD111023 | K33: LD111122 | L33: =C33&N33 -> 1114 | M33: =A33 -> 2025-11-11 | N33: 14 | O33: LD111124 | P33: LD111023 | Q33: =F33 -> LD111025 | R33: =Q32 -> LD110725 | S33: =Q32 -> LD110725 | T33: =+O33 -> LD111124 | W33: 2025-11-11 | X33: =W33-A33 -> 0 | Y33: LD111124 | Z33: LD111023
A34: 2025-11-12 | B34: 4 | C34: 11 | D34: 7 | E34: 2 | F34: LD111125 | G34: LD081324 | H34: LD111422 | I34: LD081224 | J34: LD111323 | K34: LD111422 | L34: =C34&N34 -> 1113 | M34: =A34 -> 2025-11-12 | N34: 13 | O34: LD111224 | P34: LD111323 | Q34: =F34 -> LD111125 | R34: =Q33 -> LD111025 | S34: =S33 -> LD110725 | T34: =+O34 -> LD111224 | W34: 2025-11-12 | X34: =W34-A34 -> 0 | Y34: LD111224 | Z34: LD111323
A35: 2025-11-13 | B35: 4 | C35: 11 | D35: 7 | E35: 3 | F35: LD111225 | G35: LD081424 | H35: LD111522 | I35: LD081324 | J35: LD111423 | K35: LD111522 | L35: =C35&N35 -> 1112 | M35: =A35 -> 2025-11-13 | N35: 12 | O35: LD111324 | P35: LD111423 | Q35: =F35 -> LD111225 | R35: =Q34 -> LD111125 | S35: =S34 -> LD110725 | T35: =+O35 -> LD111324 | W35: 2025-11-13 | X35: =W35-A35 -> 0 | Y35: LD111324 | Z35: LD111423
A36: 2025-11-14 | B36: 4 | C36: 11 | D36: 7 | E36: 4 | F36: LD111325 | G36: LD081524 | H36: LD111622 | I36: LD081424 | J36: LD111523 | K36: LD111622 | L36: =C36&N36 -> 1111 | M36: =A36 -> 2025-11-14 | N36: 11 | O36: LD111424 | P36: LD111523 | Q36: =F36 -> LD111325 | R36: =Q35 -> LD111225 | S36: =S35 -> LD110725 | T36: =+O36 -> LD111424 | W36: 2025-11-14 | X36: =W36-A36 -> 0 | Y36: LD111424 | Z36: LD111523
A37: 2025-11-17 | B37: 4 | C37: 11 | D37: 7 | E37: 5 | F37: LD111425 | G37: LD081624 | H37: LD111722 | I37: LD081524 | J37: LD111623 | K37: LD111722 | L37: =C37&N37 -> 1110 | M37: =A37 -> 2025-11-17 | N37: 10 | O37: LD111524 | P37: LD111623 | Q37: =F37 -> LD111425 | R37: =Q36 -> LD111325 | S37: =S36 -> LD110725 | T37: =+O37 -> LD111524 | W37: 2025-11-17 | X37: =W37-A37 -> 0 | Y37: LD111524 | Z37: LD111623
A38: 2025-11-18 | B38: 4 | C38: 11 | D38: 8 | E38: 1 | F38: LD111725 | G38: LD081924 | H38: LD021723 | I38: LD081624 | J38: LD111723 | K38: LD111822 | L38: =C38&N38 -> 119 | M38: =A38 -> 2025-11-18 | N38: 9 | O38: LD111824 | P38: LD111723 | Q38: =F38 -> LD111725 | R38: =Q37 -> LD111425 | S38: =Q37 -> LD111425 | T38: =+O38 -> LD111824 | W38: 2025-11-18 | X38: =W38-A38 -> 0 | Y38: LD111824 | Z38: LD111723
A39: 2025-11-19 | B39: 4 | C39: 11 | D39: 8 | E39: 2 | F39: LD111825 | G39: LD082024 | H39: LD112122 | I39: LD081924 | J39: LD112023 | K39: LD112122 | L39: =C39&N39 -> 118 | M39: =A39 -> 2025-11-19 | N39: 8 | O39: LD111924 | P39: LD112023 | Q39: =F39 -> LD111825 | R39: =Q38 -> LD111725 | S39: =S38 -> LD111425 | T39: =+O39 -> LD111924 | W39: 2025-11-19 | X39: =W39-A39 -> 0 | Y39: LD111924 | Z39: LD112023
A40: 2025-11-20 | B40: 4 | C40: 11 | D40: 8 | E40: 3 | F40: LD111925 | G40: LD082124 | H40: LD112222 | I40: LD082024 | J40: LD112123 | K40: LD112222 | L40: =C40&N40 -> 117 | M40: =A40 -> 2025-11-20 | N40: 7 | O40: LD112024 | P40: LD112123 | Q40: =F40 -> LD111925 | R40: =Q39 -> LD111825 | S40: =S39 -> LD111425 | T40: =+O40 -> LD112024 | W40: 2025-11-20 | X40: =W40-A40 -> 0 | Y40: LD112024 | Z40: LD112123
A41: 2025-11-21 | B41: 4 | C41: 11 | D41: 8 | E41: 4 | F41: LD112025 | G41: LD082224 | H41: LD112322 | I41: LD082124 | J41: LD112223 | K41: LD112322 | L41: =C41&N41 -> 116 | M41: =A41 -> 2025-11-21 | N41: 6 | O41: LD112124 | P41: LD112223 | Q41: =F41 -> LD112025 | R41: =Q40 -> LD111925 | S41: =S40 -> LD111425 | T41: =+O41 -> LD112124 | W41: 2025-11-21 | X41: =W41-A41 -> 0 | Y41: LD112124 | Z41: LD112223
A42: 2025-11-24 | B42: 4 | C42: 11 | D42: 8 | E42: 5 | F42: LD112125 | G42: LD082324 | H42: LD112422 | I42: LD082224 | J42: LD112323 | K42: LD112422 | L42: =C42&N42 -> 115 | M42: =A42 -> 2025-11-24 | N42: 5 | O42: LD112224 | P42: LD112323 | Q42: =F42 -> LD112125 | R42: =Q41 -> LD112025 | S42: =S41 -> LD111425 | T42: =+O42 -> LD112224 | W42: 2025-11-24 | X42: =W42-A42 -> 0 | Y42: LD112224 | Z42: LD112323
A43: 2025-11-25 | B43: 4 | C43: 11 | D43: 9 | E43: 1 | F43: LD112425 | G43: LD082624 | H43: LD112522 | I43: LD082324 | J43: LD112423 | K43: LD112522 | L43: =C43&N43 -> 114 | M43: =A43 -> 2025-11-25 | N43: 4 | O43: LD112524 | P43: LD112423 | Q43: =F43 -> LD112425 | R43: =Q42 -> LD112125 | S43: =Q42 -> LD112125 | T43: =+O43 -> LD112524 | W43: 2025-11-25 | X43: =W43-A43 -> 0 | Y43: LD112524 | Z43: LD112423
A44: 2025-11-26 | B44: 4 | C44: 11 | D44: 9 | E44: 2 | F44: LD112525 | G44: LD082724 | H44: LD112522 | I44: LD082324 | J44: LD112423 | K44: LD112522 | L44: =C44&N44 -> 113 | M44: =A44 -> 2025-11-26 | N44: 3 | O44: LD112624 | P44: LD112723 | Q44: =F44 -> LD112525 | R44: =Q43 -> LD112425 | S44: =S43 -> LD112125 | T44: =+O44 -> LD112624 | W44: 2025-11-26 | X44: =W44-A44 -> 0 | Y44: LD112624 | Z44: LD112723
A45: 2025-11-27 | B45: 4 | C45: 11 | D45: 9 | E45: 3 | F45: LD112625 | G45: LD082824 | H45: LD112822 | I45: LD082624 | J45: LD112723 | K45: LD112822 | L45: =C45&N45 -> 112 | M45: =A45 -> 2025-11-27 | N45: 2 | O45: LD112724 | P45: LD112823 | Q45: =F45 -> LD112625 | R45: =Q44 -> LD112525 | S45: =S44 -> LD112125 | T45: =+O45 -> LD112724 | W45: 2025-11-27 | X45: =W45-A45 -> 0 | Y45: LD112724 | Z45: LD112823
A46: 2025-11-28 | B46: 4 | C46: 11 | D46: 9 | E46: 4 | F46: LD112725 | G46: LD082924 | H46: LD112922 | I46: LD082724 | J46: LD112823 | K46: LD112922 | L46: =C46&N46 -> 111 | M46: =A46 -> 2025-11-28 | N46: 1 | O46: LD112824 | P46: LD112923 | Q46: =F46 -> LD112725 | R46: =Q45 -> LD112625 | S46: =S45 -> LD112125 | T46: =+O46 -> LD112824 | W46: 2025-11-28 | X46: =W46-A46 -> 0 | Y46: LD112824 | Z46: LD112923
A47: 2025-12-01 | B47: 4 | C47: 11 | D47: 9 | E47: 5 | F47: LD112825 | G47: LD083024 | H47: LD113022 | I47: LD082824 | J47: LD112923 | K47: LD113022 | L47: =C47&N47 -> 110 | M47: =A47 -> 2025-12-01 | N47: 0 | O47: LD112924 | P47: LD113023 | Q47: =F47 -> LD112825 | R47: =Q46 -> LD112725 | S47: =S46 -> LD112125 | T47: =+O47 -> LD112924 | W47: 2025-12-01 | X47: =W47-A47 -> 0 | Y47: LD112924 | Z47: LD113023
A48: 2025-12-02 | B48: 4 | C48: 12 | D48: 10 | E48: 1 | F48: LD120125 | G48: LD090224 | H48: LD120222 | I48: LD083024 | J48: LD120123 | K48: LD120222 | L48: =C48&N48 -> 1221 | M48: =A48 -> 2025-12-02 | N48: 21 | O48: LD120124 | P48: LD120123 | Q48: =F48 -> LD120125 | R48: =Q47 -> LD112825 | S48: =Q47 -> LD112825 | T48: =+O48 -> LD120124 | W48: 2025-12-02 | X48: =W48-A48 -> 0 | Y48: LD120124 | Z48: LD120123
A49: 2025-12-03 | B49: 4 | C49: 12 | D49: 10 | E49: 2 | F49: LD120225 | G49: LD090324 | H49: LD120222 | I49: LD083024 | J49: LD120123 | K49: LD120222 | L49: =C49&N49 -> 1220 | M49: =A49 -> 2025-12-03 | N49: 20 | O49: LD120224 | P49: LD120223 | Q49: =F47 -> LD112825 | R49: =Q48 -> LD120125 | S49: =S48 -> LD112825 | T49: =+O49 -> LD120224 | W49: 2025-12-03 | X49: =W49-A49 -> 0 | Y49: LD120224 | Z49: LD120223
A50: 2025-12-04 | B50: 4 | C50: 12 | D50: 10 | E50: 3 | F50: LD120325 | G50: LD090424 | H50: LD120522 | I50: LD090224 | J50: LD120423 | K50: LD120522 | L50: =C50&N50 -> 1219 | M50: =A50 -> 2025-12-04 | N50: 19 | O50: LD120324 | P50: LD120323 | Q50: =F50 -> LD120325 | R50: =Q49 -> LD112825 | S50: =Q49 -> LD112825 | T50: =+O50 -> LD120324 | W50: 2025-12-04 | X50: =W50-A50 -> 0 | Y50: LD120324 | Z50: LD120323
A51: 2025-12-05 | B51: 4 | C51: 12 | D51: 10 | E51: 4 | F51: LD120425 | G51: LD090524 | H51: LD120622 | I51: LD090324 | J51: LD120523 | K51: LD120622 | L51: =C51&N51 -> 1218 | M51: =A51 -> 2025-12-05 | N51: 18 | O51: LD120424 | P51: LD120423 | Q51: =F51 -> LD120425 | R51: =Q50 -> LD120325 | S51: =S50 -> LD112825 | T51: =+O51 -> LD120424 | W51: 2025-12-05 | X51: =W51-A51 -> 0 | Y51: LD120424 | Z51: LD120423
A52: 2025-12-08 | B52: 4 | C52: 12 | D52: 10 | E52: 5 | F52: LD120525 | G52: LD090624 | H52: LD120722 | I52: LD090424 | J52: LD120623 | K52: LD120722 | L52: =C52&N52 -> 1217 | M52: =A52 -> 2025-12-08 | N52: 17 | O52: LD120524 | P52: LD120523 | Q52: =F52 -> LD120525 | R52: =Q51 -> LD120425 | S52: =S51 -> LD112825 | T52: =+O52 -> LD120524 | W52: 2025-12-08 | X52: =W52-A52 -> 0 | Y52: LD120524 | Z52: LD120523
A53: 2025-12-09 | B53: 4 | C53: 12 | D53: 11 | E53: 1 | F53: LD120825 | G53: LD090924 | H53: LD120822 | I53: LD090524 | J53: LD120723 | K53: LD120822 | L53: =C53&N53 -> 1216 | M53: =A53 -> 2025-12-09 | N53: 16 | O53: LD120624 | P53: LD120623 | Q53: =F53 -> LD120825 | R53: =Q52 -> LD120525 | S53: =Q52 -> LD120525 | T53: =+O53 -> LD120624 | W53: 2025-12-09 | X53: =W53-A53 -> 0 | Y53: LD120624 | Z53: LD120623
A54: 2025-12-10 | B54: 4 | C54: 12 | D54: 11 | E54: 2 | F54: LD120925 | G54: LD091024 | H54: LD120922 | I54: LD090624 | J54: LD120823 | K54: LD120922 | L54: =C54&N54 -> 1215 | M54: =A54 -> 2025-12-10 | N54: 15 | O54: LD120924 | P54: LD120723 | Q54: =F54 -> LD120925 | R54: =Q53 -> LD120825 | S54: =S53 -> LD120525 | T54: =+O54 -> LD120924 | W54: 2025-12-10 | X54: =W54-A54 -> 0 | Y54: LD120924 | Z54: LD120723
A55: 2025-12-11 | B55: 4 | C55: 12 | D55: 11 | E55: 3 | F55: LD121025 | G55: LD091124 | H55: LD121222 | I55: LD090924 | J55: LD121123 | K55: LD121222 | L55: =C55&N55 -> 1214 | M55: =A55 -> 2025-12-11 | N55: 14 | O55: LD121024 | P55: LD120823 | Q55: =F55 -> LD121025 | R55: =Q54 -> LD120925 | S55: =S54 -> LD120525 | T55: =+O55 -> LD121024 | W55: 2025-12-11 | X55: =W55-A55 -> 0 | Y55: LD121024 | Z55: LD120823
A56: 2025-12-12 | B56: 4 | C56: 12 | D56: 11 | E56: 4 | F56: LD121125 | G56: LD091224 | H56: LD121322 | I56: LD091024 | J56: LD121223 | K56: LD121322 | L56: =C56&N56 -> 1213 | M56: =A56 -> 2025-12-12 | N56: 13 | O56: LD121124 | P56: LD121123 | Q56: =F56 -> LD121125 | R56: =Q55 -> LD121025 | S56: =S55 -> LD120525 | T56: =+O56 -> LD121124 | W56: 2025-12-12 | X56: =W56-A56 -> 0 | Y56: LD121124 | Z56: LD121123
A57: 2025-12-15 | B57: 4 | C57: 12 | D57: 11 | E57: 5 | F57: LD121225 | G57: LD091324 | H57: LD121422 | I57: LD091124 | J57: LD121323 | K57: LD121422 | L57: =C57&N57 -> 1212 | M57: =A57 -> 2025-12-15 | N57: 12 | O57: LD121224 | P57: LD121223 | Q57: =F57 -> LD121225 | R57: =Q56 -> LD121125 | S57: =S56 -> LD120525 | T57: =+O57 -> LD121224 | W57: 2025-12-15 | X57: =W57-A57 -> 0 | Y57: LD121224 | Z57: LD121223
A58: 2025-12-16 | B58: 4 | C58: 12 | D58: 12 | E58: 1 | F58: LD121525 | G58: LD091624 | H58: LD121522 | I58: LD091224 | J58: LD121423 | K58: LD121522 | L58: =C58&N58 -> 1211 | M58: =A58 -> 2025-12-16 | N58: 11 | O58: LD121324 | P58: LD121323 | Q58: =F58 -> LD121525 | R58: =Q57 -> LD121225 | S58: =Q57 -> LD121225 | T58: =+O58 -> LD121324 | W58: 2025-12-16 | X58: =W58-A58 -> 0 | Y58: LD121324 | Z58: LD121323
A59: 2025-12-17 | B59: 4 | C59: 12 | D59: 12 | E59: 2 | F59: LD121625 | G59: LD091724 | H59: LD121622 | I59: LD091324 | J59: LD121523 | K59: LD121622 | L59: =C59&N59 -> 1210 | M59: =A59 -> 2025-12-17 | N59: 10 | O59: LD121624 | P59: LD121423 | Q59: =F59 -> LD121625 | R59: =Q58 -> LD121525 | S59: =S58 -> LD121225 | T59: =+O59 -> LD121624 | W59: 2025-12-17 | X59: =W59-A59 -> 0 | Y59: LD121624 | Z59: LD121423
A60: 2025-12-18 | B60: 4 | C60: 12 | D60: 12 | E60: 3 | F60: LD121725 | G60: LD091824 | H60: LD121922 | I60: LD091624 | J60: LD121823 | K60: LD121922 | L60: =C60&N60 -> 129 | M60: =A60 -> 2025-12-18 | N60: 9 | O60: LD121724 | P60: LD121523 | Q60: =F60 -> LD121725 | R60: =Q59 -> LD121625 | S60: =S59 -> LD121225 | T60: =+O60 -> LD121724 | W60: 2025-12-18 | X60: =W60-A60 -> 0 | Y60: LD121724 | Z60: LD121523
A61: 2025-12-19 | B61: 4 | C61: 12 | D61: 12 | E61: 4 | F61: LD121825 | G61: LD091924 | H61: LD122022 | I61: LD091724 | J61: LD121923 | K61: LD122022 | L61: =C61&N61 -> 128 | M61: =A61 -> 2025-12-19 | N61: 8 | O61: LD121824 | P61: LD121823 | Q61: =F61 -> LD121825 | R61: =Q60 -> LD121725 | S61: =S60 -> LD121225 | T61: =+O61 -> LD121824 | W61: 2025-12-19 | X61: =W61-A61 -> 0 | Y61: LD121824 | Z61: LD121823
A62: 2025-12-22 | B62: 4 | C62: 12 | D62: 12 | E62: 5 | F62: LD121925 | G62: LD092024 | H62: LD122122 | I62: LD091824 | J62: LD122023 | K62: LD122122 | L62: =C62&N62 -> 127 | M62: =A62 -> 2025-12-22 | N62: 7 | O62: LD121924 | P62: LD121923 | Q62: =F62 -> LD121925 | R62: =Q60 -> LD121725 | S62: =S60 -> LD121225 | T62: =+O62 -> LD121924 | U62: Saturday | W62: 2025-12-22 | X62: =W62-A62 -> 0 | Y62: LD121924 | Z62: LD121923
A63: 2025-12-23 | B63: 4 | C63: 12 | D63: 13 | E63: 1 | F63: LD122225 | G63: LD092024 | H63: LD122122 | I63: LD091824 | J63: LD122023 | K63: LD122122 | L63: =C63&N63 -> 127 | M63: =A63 -> 2025-12-23 | N63: 7 | O63: LD122024 | P63: LD122023 | Q63: =F63 -> LD122225 | R63: =Q61 -> LD121825 | S63: =S61 -> LD121225 | T63: =+O63 -> LD122024 | W63: 2025-12-23 | X63: =W63-A63 -> 0 | Y63: LD122024 | Z63: LD122023
A64: 2025-12-24 | B64: 4 | C64: 12 | D64: 13 | E64: 2 | F64: LD122325 | G64: LD092324 | H64: LD122222 | I64: LD091924 | J64: LD122123 | K64: LD122222 | L64: =C64&N64 -> 126 | M64: =A64 -> 2025-12-24 | N64: 6 | O64: LD122324 | P64: LD122123 | Q64: =F64 -> LD122325 | R64: =Q63 -> LD122225 | S64: =Q63 -> LD122225 | T64: =+O64 -> LD122324 | W64: 2025-12-24 | X64: =W64-A64 -> 0 | Y64: LD122324 | Z64: LD122123
A65: 2025-12-25 | B65: 4 | C65: 12 | D65: 13 | E65: 3 | F65: LD122425 | G65: LD092424 | H65: LD122322 | I65: LD092024 | J65: LD122223 | K65: LD122322 | L65: =C65&N65 -> 125 | M65: =A65 -> 2025-12-25 | N65: 5 | O65: LD122424 | P65: LD122223 | Q65: =F65 -> LD122425 | R65: =Q64 -> LD122325 | S65: =S64 -> LD122225 | T65: =+O65 -> LD122424 | W65: 2025-12-25 | X65: =W65-A65 -> 0 | Y65: LD122424 | Z65: LD122223
A66: 2025-12-26 | B66: 4 | C66: 12 | D66: 13 | E66: 4 | F66: LD122525 | G66: LD092524 | H66: LD122622 | I66: LD092324 | J66: LD122523 | K66: LD122622 | L66: =C66&N66 -> 124 | M66: =A66 -> 2025-12-26 | N66: 4 | O66: LD122524 | P66: LD122523 | Q66: =F66 -> LD122525 | R66: =Q65 -> LD122425 | S66: =S65 -> LD122225 | T66: =+O66 -> LD122524 | W66: 2025-12-26 | X66: =W66-A66 -> 0 | Y66: LD122524 | Z66: LD122523
A67: 2025-12-29 | B67: 4 | C67: 12 | D67: 13 | E67: 5 | F67: LD122625 | G67: LD092624 | H67: LD122822 | I67: LD092524 | J67: LD122723 | K67: LD122822 | L67: =C67&N67 -> 123 | M67: =A67 -> 2025-12-29 | N67: 3 | O67: LD122624 | P67: LD122623 | Q67: =F67 -> LD122625 | R67: =Q66 -> LD122525 | S67: =S66 -> LD122225 | T67: =+O67 -> LD122624 | W67: 2025-12-29 | X67: =W67-A67 -> 0 | Y67: LD122624 | Z67: LD122623
A68: 2025-12-30 | B68: 4 | C68: 12 | D68: 13 | E68: 6 | F68: LD122925 | G68: LD092624 | H68: LD122822 | I68: LD092524 | J68: LD122723 | K68: LD122822 | L68: =C68&N68 -> 122 | M68: =A68 -> 2025-12-30 | N68: 2 | O68: LD122724 | P68: LD122723 | Q68: =F68 -> LD122925 | R68: =Q65 -> LD122425 | S68: =S65 -> LD122225 | T68: =+O68 -> LD122724 | W68: 2025-12-30 | X68: =W68-A68 -> 0 | Y68: LD122724 | Z68: LD122723
A69: 2025-12-31 | B69: 4 | C69: 12 | D69: 13 | E69: 7 | F69: LD123025 | G69: LD092624 | H69: LD122822 | I69: LD092524 | J69: LD122723 | K69: LD122822 | L69: =C69&N69 -> 122 | M69: =A69 -> 2025-12-31 | N69: 2 | O69: LD123024 | P69: LD122823 | Q69: =F69 -> LD123025 | R69: =Q66 -> LD122525 | S69: =S66 -> LD122225 | T69: =+O69 -> LD123024 | U69: Saturday | W69: 2025-12-31 | X69: =W69-A69 -> 0 | Y69: LD123024 | Z69: LD122823
B70: 4 | C70: 12 | D70: 13 | E70: 8 | F70: LD123125 | G70: LD092724 | H70: LD122922 | I70: LD092624 | J70: LD122823 | K70: LD122922 | L70: =C70&N70 -> 122 | M70: =A70 -> 0 | N70: 2 | O70: LD4Q24FINAL | P70: LD4Q23FINAL | Q70: =F70 -> LD123125 | R70: =Q67 -> LD122625 | S70: =S67 -> LD122225 | T70: =+O70 -> LD4Q24FINAL | U70: Sunday | W70: 2026-01-02 | X70: =W70-A70 -> 46024 | Y70: LD4Q24FINAL | Z70: LD4Q23FINAL
A71: 2026-01-02 | B71: 4 | C71: 12 | D71: 13 | E71: 8 | F71: LD4Q25FINAL | G71: LD093024 | H71: LD122922 | I71: LD092624 | J71: LD122823 | K71: LD122922 | L71: =C71&N71 -> 121 | M71: =A71 -> 2026-01-02 | N71: 1 | O71: Ld092724 | P71: Ld092823 | Q71: =F71 -> LD4Q25FINAL | R71: =Q67 -> LD122625 | S71: =Q67 -> LD122625 | T71: =+O71 -> Ld092724
A72: 2025-10-01 | B72: 4 | C72: 9 | D72: 13 | E72: 7 | F72: LD100925 | G72: LD3Q24FINAL | H72: LD123022 | I72: LD092724 | J72: LD122923 | K72: LD123022 | L72: =C72&N72 -> 90 | M72: =A72 -> 2025-10-01 | N72: 0 | O72: LD100925 | P72: Ld3Q23Final | Q72: =F72 -> LD100925 | R72: =Q71 -> LD4Q25FINAL | S72: =S71 -> LD122625 | T72: =+O72 -> LD100925
A73: 2025-10-01 | B73: 4 | C73: 9 | D73: 13 | E73: 7 | F73: LD3Q25FINAL | G73: LD3Q24FINAL

Sheet INPUT
A1: CURR YEAR | B1: 25 | D1: TODAY | E1: =TODAY() -> 45975
A2: CURR QTR | B2: 4Q | D2: CD | E2: =VLOOKUP($B$5&$G$6,Ref!$L$7:$T$72,6,0) -> LD111325 | G2: CQ Stream | I2: Consol case MT | J2: BUDcm | K2: PY Consol | L2: AAP2024 | P2: CW Tracks | Q2: WK7 | AH2: Jan | AI2: 1Q
A3: NQ | B3: 1Q | D3: PD | E3: =VLOOKUP($B$5&$G$6,Ref!$L$7:$T$72,7,0) -> LD111225 | G3: 4Q Stream | I3: Consol case QTR | J3: FCTcm | K3: PPY Consol | L3: AAP2023 | P3: PW Tracks | Q3: WK6 | W3: WW | Y3: WW | Z3: W | AA3: WW | AH3: Apr | AI3: 2Q
A4: CURR MTH | B4: NovQTD | C4: FebYTD | D4: PW | E4: =VLOOKUP($B$5&$G$6,Ref!$L$7:$T$72,8,0) -> LD110725 | W4: Americas | Y4: Americas | Z4: AM | AA4: Americas | AH4: Jul | AI4: 3Q
A5: CURR MTH | B5: 11 | D5: PY | E5: =VLOOKUP($B$5&$G$6,Ref!$L$7:$T$72,9,0) -> LD111424 | W5: EMEA | Y5: Europe | Z5: EM | AA5: EMEA | AH5: Oct | AI5: 4Q
E6: PROJECTION | F6: Days to go | G6: 11 | W6: Japan | Y6: Japan | Z6: JN | AA6: Japan | AH6: FebQTD
E7: z | L7: MTH1 | M7: MTH2QTD | N7: CQ | W7: APAC | Y7: AsiaPacific | Z7: AP | AA7: APAC | AH7: MayQTD
E8: CASE PY | F8: =VLOOKUP(G6,INPUT!A20:U41,2,FALSE) -> Ld101624 | I8: updated each month!! --> | K8: CASE PY | L8: 2 | M8: 9 | N8: 16 | AH8: AugQTD
E9: PY FINAL MTH | F9: =VLOOKUP(0,INPUT!A20:U41,2,FALSE) -> Ld103124 | I9: updated each month!! --> | K9: PY FINAL MTH | L9: 2 | M9: 9 | N9: 16 | AH9: NovQTD
E10: PY FINAL QTR | F10: =VLOOKUP(0,INPUT!A20:U41,16,FALSE) -> Ld3Q24Final | G10: =RIGHT(LEFT(F10,4),2) -> 3Q | K10: PY FINAL QTR | L10: 16 | M10: 16 | N10: 16
E11: CASEPPY | F11: =VLOOKUP(G6,INPUT!A20:U41,17,FALSE) -> Ld091423 | I11: updated each month!! --> | K11: CASEPPY | L11: 3 | M11: 10 | N11: 17
E12: PPY FINAL MTH | F12: =VLOOKUP(0,INPUT!A20:U41,17,FALSE) -> Ld3Q23Final | I12: updated each month!! --> | K12: PPY FINAL MTH | L12: 3 | M12: 10 | N12: 17
E13: PPY FINAL QTR | F13: =VLOOKUP(0,INPUT!A20:U41,17,FALSE) -> Ld3Q23Final | G13: =RIGHT(LEFT(F13,4),2) -> 3Q | K13: PPY FINAL QTR | L13: 17 | M13: 17 | N13: 17
A14: =COLUMN() -> 1 | B14: =COLUMN() -> 2 | C14: =COLUMN() -> 3 | D14: =COLUMN() -> 4 | E14: =COLUMN() -> 5 | F14: =COLUMN() -> 6 | G14: =COLUMN() -> 7 | H14: =COLUMN() -> 8 | ... U14: =COLUMN() -> 21
A15: PROJECTION CASES
B16: <-------------------- Month 1 QTD ------------------------> | I16: <-------------------- Month 2 QTD ------------------------> | P16: <-------------------- Month 3 FULL QTR ------------------------>
B17: <-- 2 yr avg --> | D17: <-------------- 4Q Average --------------> | I17: <-- 2 yr avg --> | K17: <-------------- 4Q Average --------------> | P17: <-- 2 yr avg --> | R17: <-------------- 4Q Average -------------->
B18: PY | C18: PY 2 | D18: Prior Qtr | E18: 2 qtrs ago | F18: 3 qtrs ago | G18: 4 qtrs ago | I18: PY | J18: PY 2 | K18: Prior Qtr | L18: 2 qtrs ago | M18: 3 qtrs ago | N18: 4 qtrs ago | P18: PY | Q18: PY 2 | R18: Prior Qtr | S18: 2 qtrs ago | T18: 3 qtrs ago | U18: 4 qtrs ago
A19: Days to Go | B19: 4Q24 | C19: 4Q23 | D19: 3Q25 | E19: 2Q25 | F19: 1Q25 | G19: 4Q24 | I19: 4Q24 | J19: 4Q23 | K19: 3Q25 | L19: 2Q25 | M19: 1Q25 | N19: 4Q24 | P19: 4Q24 | Q19: 4Q23 | R19: 3Q25 | S19: 2Q25 | T19: 1Q25 | U19: 4Q24
A20: 21 | B20: Ld070224 | C20: Ld070223 | D20: Ld040125 | I20: Ld050424 | P20: Ld060124 | Q20: Ld090223
A21: 20 | B21: Ld070324 | C21: Ld070323 | D21: Ld040225 | I21: Ld050524 | J21: Ld080323 | K21: LD050425 | L21: Ld020225 | M21: Ld110324 | N21: Ld080323 | P21: Ld060324 | Q21: Ld090323
A22: 19 | B22: Ld100424 | C22: Ld100423 | D22: Ld070425 | E22: Ld040325 | F22: Ld010625 | G22: Ld100423 | I22: Ld110424 | J22: ld110323 | K22: Ld080425 | L22: LD050525 | M22: Ld020325 | N22: ld110323 | P22: Ld090324 | Q22: Ld090423 | R22: Ld060325 | S22: Ld090425 | T22: Ld120424 | U22: Ld090423
A23: 18 | B23: Ld100724 | C23: Ld100523 | D23: Ld070725 | E23: LD040425 | F23: Ld010725 | G23: Ld100523 | I23: Ld110524 | J23: ld110623 | K23: Ld080525 | L23: LD050625 | M23: Ld020425 | N23: ld110623 | P23: Ld090424 | Q23: Ld090523 | R23: Ld060425 | S23: Ld090525 | T23: Ld120524 | U23: Ld090523
A24: 17 | B24: Ld100824 | C24: Ld100623 | D24: Ld070825 | E24: LD040725 | F24: Ld010825 | G24: Ld100623 | I24: Ld110624 | J24: ld110723 | K24: Ld080625 | L24: LD050725 | M24: Ld020525 | N24: ld110723 | P24: Ld090524 | Q24: Ld090623 | R24: Ld060525 | S24: Ld090625 | T24: Ld120624 | U24: Ld090623
A25: 16 | B25: Ld100924 | C25: Ld100923 | D25: Ld070925 | E25: LD040825 | F25: Ld010925 | G25: Ld100923 | I25: Ld110724 | J25: ld110823 | K25: Ld080725 | L25: LD050825 | M25: Ld020625 | N25: ld110823 | P25: Ld090624 | Q25: Ld090723 | R25: Ld060625 | S25: Ld090725 | T25: Ld120924 | U25: Ld090723
A26: 15 | B26: Ld101024 | C26: Ld101023 | D26: Ld071025 | E26: LD040925 | F26: Ld011025 | G26: Ld101023 | I26: Ld110824 | J26: ld110923 | K26: Ld080825 | L26: LD050925 | M26: Ld020725 | N26: ld110923 | P26: Ld090924 | Q26: Ld090823 | R26: Ld060925 | S26: Ld091025 | T26: Ld121024 | U26: Ld090823
A27: 14 | B27: Ld101124 | C27: Ld101123 | D27: Ld071125 | E27: LD041025 | F27: Ld011325 | G27: Ld101123 | I27: Ld111124 | J27: ld111023 | K27: Ld081125 | L27: LD051225 | M27: Ld021025 | N27: ld111023 | P27: Ld091024 | Q27: Ld091123 | R27: Ld061025 | S27: Ld091125 | T27: Ld121124 | U27: Ld091123
A28: 13 | B28: Ld101424 | C28: Ld101223 | D28: Ld071425 | E28: LD041125 | F28: Ld011425 | G28: Ld101223 | I28: Ld111224 | J28: ld111323 | K28: Ld081225 | L28: LD051325 | M28: Ld021125 | N28: ld111323 | P28: Ld091124 | Q28: Ld091223 | R28: Ld061125 | S28: Ld091225 | T28: Ld121224 | U28: Ld091223
A29: 12 | B29: Ld101524 | C29: Ld101323 | D29: Ld071525 | E29: LD041425 | F29: Ld011525 | G29: Ld101323 | I29: Ld111324 | J29: ld111423 | K29: Ld081325 | L29: LD051425 | M29: Ld021225 | N29: ld111423 | P29: Ld091224 | Q29: Ld091323 | R29: Ld061225 | S29: Ld091325 | T29: Ld121324 | U29: Ld091323
A30: 11 | B30: Ld101624 | C30: Ld101623 | D30: Ld071625 | E30: LD041525 | F30: Ld011625 | G30: Ld101623 | I30: Ld111424 | J30: ld111523 | K30: Ld081425 | L30: LD051525 | M30: Ld021325 | N30: ld111523 | P30: Ld091324 | Q30: Ld091423 | R30: Ld061325 | S30: Ld091425 | T30: Ld121624 | U30: Ld091423
A31: 10 | B31: Ld101724 | C31: Ld101723 | D31: Ld071725 | E31: LD041625 | F31: Ld011725 | G31: Ld101723 | I31: Ld111524 | J31: ld111623 | K31: Ld081525 | L31: LD051625 | M31: Ld021425 | N31: ld111623 | P31: Ld091624 | Q31: Ld091523 | R31: Ld061625 | S31: Ld091725 | T31: Ld121724 | U31: Ld091523
A32: 9 | B32: Ld101824 | C32: Ld101823 | D32: Ld071825 | E32: LD041725 | F32: Ld012025 | G32: Ld101823 | I32: Ld111824 | J32: ld111723 | K32: Ld081825 | L32: LD051925 | M32: Ld021725 | N32: ld111723 | P32: Ld091724 | Q32: Ld091823 | R32: Ld061725 | S32: Ld091825 | T32: Ld121824 | U32: Ld091823
A33: 8 | B33: Ld102124 | C33: Ld101923 | D33: Ld072125 | E33: LD041825 | F33: Ld012125 | G33: Ld101923 | I33: Ld111924 | J33: ld112023 | K33: Ld081925 | L33: LD052025 | M33: Ld021825 | N33: ld112023 | P33: Ld091824 | Q33: Ld091923 | R33: Ld061825 | S33: Ld091925 | T33: Ld121924 | U33: Ld091923
... A41: 0 | B41: Ld103124 | C41: Ld103123 | D41: Ld073125 | E41: LD043025 | F41: Ld013125 | G41: Ld103124 | I41: Ld112924 | J41: ld113023 | K41: Ld082925 | L41: LD053025 | M41: Ld022825 | N41: ld113023 | P41: Ld3Q24Final | Q41: Ld3Q23Final | R41: LD2Q25 Final | S41: Ld1Q25Final | T41: Ld4Q24Final | U41: Ld3Q23Final

Sheet WW
Q2: =D9-H9 -> 2837.7679
D3: Console | E3: Console | H3: Load | K3: Load | L3: Load | M3: Load | N3: Load | O3: Load | P3: Console | R3: CW Tracks | T3: PW track | W3: Trans | Y3: Annuity
D4: F | E4: T | H4: E | K4: T | L4: F | M4: G | P4: G | R4: E | T4: G | W4: F | Y4: E
C5: GEO: | D5: bud23 | E5: act22 | H5: CD1Q | J5: PY1Q | L5: PD1Q | M5: PW1Q | W5: CY1Q
C6: WW | D6: Budget | H6: FIRM LOAD (HW) | W6: NonHW | AD6: TOTAL LOAD
C7: Full QTR | D7: =INPUT!$B$2 -> 4Q | F7: YtY | H7: Load | I7: o/w shipped | J7: PY | K7: YtY | L7: PD | M7: PW | N7: DtD | O7: WtW | P7: HW Budget | Q7: B/(W) to Budget | R7: =CONCATENATE("Track ", +'Tracks Pull'!E12) -> Track WK7 | S7: B/(W) Track | T7: =+'Tracks Pull'!G12 -> WtW | U7: WtW B/(W) Track | W7: SW Tx Firm | X7: SW Tx ToGo | Y7: ISC Annuity | Z7: NonHW Trans+Annuity | AA7: NonHW Budget | AB7: B/(W) Bgt | AD7: FIRM + NonHW | AE7: YtY | AF7: B/(W) to Budget
A9: BRAND | C9: Systems w/o TPS | D9: =SUM(D10:D15) -> 3286.3575 | E9: =SUM(E10:E15) -> 2838.1265 | F9: =+D9/E9-1 -> 0.15793201 | H9: =SUM(H10:H15) -> 448.58962 | I9: =SUM(I10:I15) -> 256.76876 | J9: =SUM(J10:J15) -> 386.76836 | K9: =H9/J9-1 -> 0.15984053 | L9: =SUM(L10:L15) -> 416.87528 | M9: =SUM(M10:M15) -> 361.87233 | N9: =SUM(N10:N15) -> 31.714339 | O9: =SUM(O10:O15) -> 86.71729 | P9: =SUM(P10:P15) -> 2715.9684 | Q9: =SUM(Q10:Q15) -> -2267.3788 | R9: =SUM(R10:R15) -> 674.61809 | S9: =SUM(S10:S15) -> -217.51703 | ... U9: =SUM(U10:U15) -> -41.418297 | W9: =SUM(W10:W15) -> 15.083014 | X9: =SUM(X10:X15) -> 157.72682 | Y9: =SUM(Y10:Y14) -> 408.405 | Z9: =SUM(Z10:Z14) -> 581.21483 | AA9: =SUM(AA10:AA15) -> 570.3891 | AB9: =SUM(AB10:AB15) -> 10.825731 | AD9: =SUM(AD10:AD14) -> 1029.8044 | AE9: =AD9/E9-1 -> -0.63715343 | AF9: =SUM(AF10:AF15) -> -2256.5531
A10: 26 | C10: Traditional z | D10: =SUMIFS('Consol Pull'!$F:$F,'Consol Pull'!$A:$A,$A10,'Consol Pull'!$B:$B,$C$6) -> 1670.7777 | E10: =SUMIFS('Consol Pull'!$T:$T,'Consol Pull'!$A:$A,$A10,'Consol Pull'!$B:$B,$C$6) -> 1223.6108 | F10: =+D10/E10-1 -> 0.3654486 | H10: =SUMIFS('FIRM Load Pull'!$E:$E,'FIRM Load Pull'!$A:$A,$A10,'FIRM Load Pull'!$B:$B,$C$6) -> 129.49898 | I10: =SUMIFS('Ship Load Pull'!$E:$E,'Ship Load Pull'!$A:$A,$A10,'Ship Load Pull'!$B:$B,$C$6) -> 34.804885 | J10: =SUMIFS('FIRM Load Pull'!$Q:$Q,'FIRM Load Pull'!$A:$A,$A10,'FIRM Load Pull'!$B:$B,$C$6) -> 64.110296 | K10: =H10/J10-1 -> 1.0199404 | L10: =SUMIFS('FIRM Load Pull'!$F:$F,'FIRM Load Pull'!$A:$A,$A10,'FIRM Load Pull'!$B:$B,$C$6) -> 109.46743 | M10: =SUMIFS('FIRM Load Pull'!$G:$G,'FIRM Load Pull'!$A:$A,$A10,'FIRM Load Pull'!$B:$B,$C$6) -> 74.14456 | N10: =H10-L10 -> 20.031546 | O10: =+H10-M10 -> 55.354417 | P10: =SUMIFS('Consol Pull'!$G:$G,'Consol Pull'!$A:$A,$A10,'Consol Pull'!$B:$B,$C$6) -> 1440.3421 | Q10: =H10-P10 -> -1310.8432 | R10: =SUMIFS('Tracks Pull'!$E:$E,'Tracks Pull'!$A:$A,$A10,'Tracks Pull'!$B:$B,$C$6) -> 78.144301 | S10: =H10-R10 -> 51.354676 | T10: =SUMIFS('Tracks Pull'!$G:$G,'Tracks Pull'!$A:$A,$A10,'Tracks Pull'!$B:$B,$C$6) -> 6.2485135 | U10: =O10-T10 -> 49.105904 | W10: =SUMIFS('Stream Pull'!G:G,'Stream Pull'!A:A,$A$10,'Stream Pull'!B:B,$C$6) -> 1.0072507 | X10: =SUMIFS('Stream Pull'!H:H,'Stream Pull'!A:A,$A$10,'Stream Pull'!B:B,$C$6) -> 58.941317 | Y10: =SUMIFS('Stream Pull'!M:M,'Stream Pull'!A:A,$A$10,'Stream Pull'!B:B,$C$6) -> 249.32861 | Z10: =SUM(W10:Y10) -> 309.27718 | AA10: =D10-P10 -> 230.43557 | AB10: =Z10-AA10 -> 78.841612 | AD10: =H10+Z10 -> 438.77616 | AE10: =AD10/E10-1 -> -0.64140873 | AF10: =AD10-D10 -> -1232.0015
A11: Power | C11: Power HW | D11: =SUMIFS('Consol Pull'!$F:$F,'Consol Pull'!$A:$A,$A11,'Consol Pull'!$B:$B,$C$6) -> 705.49744 | E11: =SUMIFS('Consol Pull'!$T:$T,'Consol Pull'!$A:$A,$A11,'Consol Pull'!$B:$B,$C$6) -> 628.39572 | F11: =+D11/E11-1 -> 0.12269612 | H11: =SUMIFS('FIRM Load Pull'!$E:$E,'FIRM Load Pull'!$A:$A,$A11,'FIRM Load Pull'!$B:$B,$C$6) -> 79.56673 | I11: =SUMIFS('Ship Load Pull'!$E:$E,'Ship Load Pull'!$A:$A,$A11,'Ship Load Pull'!$B:$B,$C$6) -> 62.466535 | J11: =SUMIFS('FIRM Load Pull'!$Q:$Q,'FIRM Load Pull'!$A:$A,$A11,'FIRM Load Pull'!$B:$B,$C$6) -> 94.516456 | K11: =H11/J11-1 -> -0.15817061 | L11: =SUMIFS('FIRM Load Pull'!$F:$F,'FIRM Load Pull'!$A:$A,$A11,'FIRM Load Pull'!$B:$B,$C$6) -> 77.039396 | M11: =SUMIFS('FIRM Load Pull'!$G:$G,'FIRM Load Pull'!$A:$A,$A11,'FIRM Load Pull'!$B:$B,$C$6) -> 68.131159 | N11: =H11-L11 -> 2.527334 | O11: =+H11-M11 -> 11.435571 | P11: =SUMIFS('Consol Pull'!$G:$G,'Consol Pull'!$A:$A,$A11,'Consol Pull'!$B:$B,$C$6) -> 487.89249 | Q11: =H11-P11 -> -408.32576 | R11: =SUMIFS('Tracks Pull'!$E:$E,'Tracks Pull'!$A:$A,$A11,'Tracks Pull'!$B:$B,$C$6) -> 174.74552 | S11: =H11-R11 -> -95.178792 | T11: =SUMIFS('Tracks Pull'!$G:$G,'Tracks Pull'!$A:$A,$A11,'Tracks Pull'!$B:$B,$C$6) -> 39.714158 | U11: =O11-T11 -> -28.278587 | W11: =SUMIFS('Stream Pull'!G:G,'Stream Pull'!A:A,$A$11,'Stream Pull'!B:B,$C$6) -> 14.19578 | X11: =SUMIFS('Stream Pull'!H:H,'Stream Pull'!A:A,$A$11,'Stream Pull'!B:B,$C$6) -> 58.905516 | Y11: =SUMIFS('Stream Pull'!M:M,'Stream Pull'!A:A,$A$11,'Stream Pull'!B:B,$C$6) -> 122.24172 | Z11: =SUM(W11:Y11) -> 195.34302 | AA11: =D11-P11 -> 217.60495 | AB11: =Z11-AA11 -> -22.261933 | AD11: =H11+Z11 -> 274.90975 | AE11: =AD11/E11-1 -> -0.56252129 | AF11: =AD11-D11 -> -430.58769
A12: Storage | C12: Storage HW | D12: =SUMIFS('Consol Pull'!$F:$F,'Consol Pull'!$A:$A,$A12,'Consol Pull'!$B:$B,$C$6) -> 836.85793 | E12: =SUMIFS('Consol Pull'!$T:$T,'Consol Pull'!$A:$A,$A12,'Consol Pull'!$B:$B,$C$6) -> 938.76306 | F12: =+D12/E12-1 -> -0.10855255 | H12: =SUMIFS('FIRM Load Pull'!$E:$E,'FIRM Load Pull'!$A:$A,$A12,'FIRM Load Pull'!$B:$B,$C$6) -> 233.99971 | I12: =SUMIFS('Ship Load Pull'!$E:$E,'Ship Load Pull'!$A:$A,$A12,'Ship Load Pull'!$B:$B,$C$6) -> 159.49734 | J12: =SUMIFS('FIRM Load Pull'!$Q:$Q,'FIRM Load Pull'!$A:$A,$A12,'FIRM Load Pull'!$B:$B,$C$6) -> 211.7155 | K12: =H12/J12-1 -> 0.10525547 | L12: =SUMIFS('FIRM Load Pull'!$F:$F,'FIRM Load Pull'!$A:$A,$A12,'FIRM Load Pull'!$B:$B,$C$6) -> 224.84425 | M12: =SUMIFS('FIRM Load Pull'!$G:$G,'FIRM Load Pull'!$A:$A,$A12,'FIRM Load Pull'!$B:$B,$C$6) -> 214.07241 | N12: =H12-L12 -> 9.1554589 | O12: =+H12-M12 -> 19.927302 | P12: =SUMIFS('Consol Pull'!$G:$G,'Consol Pull'!$A:$A,$A12,'Consol Pull'!$B:$B,$C$6) -> 815.63814 | Q12: =H12-P12 -> -581.63843 | R12: =SUMIFS('Tracks Pull'!$E:$E,'Tracks Pull'!$A:$A,$A12,'Tracks Pull'!$B:$B,$C$6) -> 407.69262 | S12: =H12-R12 -> -173.69291 | T12: =SUMIFS('Tracks Pull'!$G:$G,'Tracks Pull'!$A:$A,$A12,'Tracks Pull'!$B:$B,$C$6) -> 82.172916 | U12: =O12-T12 -> -62.245614 | W12: =SUMIFS('Stream Pull'!G:G,'Stream Pull'!A:A,$A$12,'Stream Pull'!B:B,$C$6) -> -0.1200171 | X12: =SUMIFS('Stream Pull'!F:F,'Stream Pull'!A:A,$A$12,'Stream Pull'!B:B,$C$6) -> 39.879983 | Y12: =SUMIFS('Stream Pull'!M:M,'Stream Pull'!A:A,$A$12,'Stream Pull'!B:B,$C$6) -> 20.334665 | Z12: =SUM(W12:Y12) -> 60.09463 | AA12: =D12-P12 -> 21.219791 | AB12: =Z12-AA12 -> 38.87484 | AD12: =H12+Z12 -> 294.09434 | AE12: =AD12/E12-1 -> -0.68672144 | AF12: =AD12-D12 -> -542.76359
A13: Technology | C13: Technology | D13: =SUMIFS('Consol Pull'!$F:$F,'Consol Pull'!$A:$A,$A13,'Consol Pull'!$B:$B,$C$6) -> 18.736803 | E13: =SUMIFS('Consol Pull'!$T:$T,'Consol Pull'!$A:$A,$A13,'Consol Pull'!$B:$B,$C$6) -> 12.229029 | F13: =+D13/E13-1 -> 0.53215791 | P13: =SUMIFS('Consol Pull'!$G:$G,'Consol Pull'!$A:$A,$A13,'Consol Pull'!$B:$B,$C$6) -> 0 | Y13: ='Stream Pull'!E106 -> 16.5 | Z13: =SUM(W13:Y13) -> 16.5 | AA13: =D13-P13 -> 18.736803 | AB13: =Z13-AA13 -> -2.2368029 | AD13: =H13+Z13 -> 16.5 | AE13: =AD13/E13-1 -> 0.34924863 | AF13: =AD13-D13 -> -2.2368029
A14: GARS | C14: GARS | D14: =SUMIFS('Consol Pull'!$F:$F,'Consol Pull'!$A:$A,$A14,'Consol Pull'!$B:$B,$C$6) -> 14.035644 | E14: =SUMIFS('Consol Pull'!$T:$T,'Consol Pull'!$A:$A,$A14,'Consol Pull'!$B:$B,$C$6) -> 20.724697 | F14: =+D14/E14-1 -> -0.32275757 | H14: =SUMIFS('FIRM Load Pull'!$E:$E,'FIRM Load Pull'!$A:$A,$A14,'FIRM Load Pull'!$B:$B,$C$6) -> 5.5241986 | I14: =SUMIFS('Ship Load Pull'!$E:$E,'Ship Load Pull'!$A:$A,$A14,'Ship Load Pull'!$B:$B,$C$6) -> 0 | J14: =SUMIFS('FIRM Load Pull'!$Q:$Q,'FIRM Load Pull'!$A:$A,$A14,'FIRM Load Pull'!$B:$B,$C$6) -> 16.426108 | K14: =H14/J14-1 -> -0.66369401 | L14: =SUMIFS('FIRM Load Pull'!$F:$F,'FIRM Load Pull'!$A:$A,$A14,'FIRM Load Pull'!$B:$B,$C$6) -> 5.5241986 | M14: =SUMIFS('FIRM Load Pull'!$G:$G,'FIRM Load Pull'!$A:$A,$A14,'FIRM Load Pull'!$B:$B,$C$6) -> 5.5241986 | N14: =H14-L14 -> 0 | O14: =+H14-M14 -> 0 | P14: =SUMIFS('Consol Pull'!$G:$G,'Consol Pull'!$A:$A,$A14,'Consol Pull'!$B:$B,$C$6) -> 14.035644 | Q14: =H14-P14 -> -8.5114457 | R14: =+P14 -> 14.035644 | AD14: =H14+Z14 -> 5.5241986 | AE14: =AD14/E14-1 -> -0.73344853 | AF14: =AD14-D14 -> -8.5114457
A15: Division Top | C15: Core HW Top (78, 5R, SP,QS) | D15: =SUMIFS('Consol Pull'!$F:$F,'Consol Pull'!$A:$A,$A15,'Consol Pull'!$B:$B,$C$6) -> 40.451985 | E15: =SUMIFS('Consol Pull'!$T:$T,'Consol Pull'!$A:$A,$A15,'Consol Pull'!$B:$B,$C$6) -> 14.403137 | F15: =+D15/E15-1 -> 1.8085537 | P15: -41.94 | Q15: =H15-P15 -> 41.94 | AA15: =D15-P15 -> 82.391985 | AB15: =Z15-AA15 -> -82.391985 | AF15: =AD15-D15 -> -40.451985
C17: Geography w/o GARS
A18: Systems | C18: Americas | D18: =SUMIFS('Consol Pull'!$F:$F,'Consol Pull'!$A:$A,$A18,'Consol Pull'!$B:$B,$C18) -> 1587.4149 | E18: =SUMIFS('Consol Pull'!$T:$T,'Consol Pull'!$A:$A,$A18,'Consol Pull'!$B:$B,$C18) -> 1228.9529 | F18: =+D18/E18-1 -> 0.2916808 | H18: =SUMIFS('FIRM Load Pull'!$E:$E,'FIRM Load Pull'!$A:$A,$A18,'FIRM Load Pull'!$B:$B,$C18) -> 166.08077 | I18: =SUMIFS('Ship Load Pull'!$E:$E,'Ship Load Pull'!$A:$A,$A18,'Ship Load Pull'!$B:$B,$C18) -> 108.82448 | J18: =SUMIFS('FIRM Load Pull'!$Q:$Q,'FIRM Load Pull'!$A:$A,$A18,'FIRM Load Pull'!$B:$B,$C18) -> 126.8122 | K18: =H18/J18-1 -> 0.30965925 | L18: =SUMIFS('FIRM Load Pull'!$F:$F,'FIRM Load Pull'!$A:$A,$A18,'FIRM Load Pull'!$B:$B,$C18) -> 142.95051 | M18: =SUMIFS('FIRM Load Pull'!$G:$G,'FIRM Load Pull'!$A:$A,$A18,'FIRM Load Pull'!$B:$B,$C18) -> 125.6573 | N18: =H18-L18 -> 23.130262 | O18: =+H18-M18 -> 40.423468 | P18: =SUMIFS('Consol Pull'!$G:$G,'Consol Pull'!$A:$A,$A18,'Consol Pull'!$B:$B,$C18) -> 1363.4667 | Q18: =H18-P18 -> -1197.3859 | R18: =SUMIFS('Tracks Pull'!$E:$E,'Tracks Pull'!$A:$A,$A18,'Tracks Pull'!$B:$B,$C18) -> 250.82298 | S18: =H18-R18 -> -84.742208 | T18: =SUMIFS('Tracks Pull'!$G:$G,'Tracks Pull'!$A:$A,$A18,'Tracks Pull'!$B:$B,$C18) -> 45.494711 | U18: =O18-T18 -> -5.0712433 | W18: =SUMIFS('Stream Pull'!G:G,'Stream Pull'!A:A,$A$18,'Stream Pull'!B:B,$C$18) -> 4.9471084 | X18: =SUMIFS('Stream Pull'!H:H,'Stream Pull'!A:A,$A$18,'Stream Pull'!B:B,$C$18) -> 59.982836 | Y18: =SUMIFS('Stream Pull'!M:M,'Stream Pull'!A:A,$A$18,'Stream Pull'!B:B,$C$18) -> 185.05101 | Z18: =SUM(W18:Y18) -> 249.98096 | AA18: =D18-P18 -> 223.94819 | AB18: =Z18-AA18 -> 26.032764 | AD18: =H18+Z18 -> 416.06173 | AE18: =AD18/E18-1 -> -0.66145023 | AF18: =AD18-D18 -> -1171.3532
A19: Systems | C19: EMEA | D19: =SUMIFS('Consol Pull'!$F:$F,'Consol Pull'!$A:$A,$A19,'Consol Pull'!$B:$B,$C19) -> 1055.6303 | E19: =SUMIFS('Consol Pull'!$T:$T,'Consol Pull'!$A:$A,$A19,'Consol Pull'!$B:$B,$C19) -> 997.63181 | F19: =+D19/E19-1 -> 0.058136175 | H19: =SUMIFS('FIRM Load Pull'!$E:$E,'FIRM Load Pull'!$A:$A,$A19,'FIRM Load Pull'!$B:$B,$C19) -> 173.31338 | I19: =SUMIFS('Ship Load Pull'!$E:$E,'Ship Load Pull'!$A:$A,$A19,'Ship Load Pull'!$B:$B,$C19) -> 94.333667 | J19: =SUMIFS('FIRM Load Pull'!$Q:$Q,'FIRM Load Pull'!$A:$A,$A19,'FIRM Load Pull'!$B:$B,$C19) -> 127.84884 | K19: =H19/J19-1 -> 0.35561173 | L19: =SUMIFS('FIRM Load Pull'!$F:$F,'FIRM Load Pull'!$A:$A,$A19,'FIRM Load Pull'!$B:$B,$C19) -> 165.74581 | M19: =SUMIFS('FIRM Load Pull'!$G:$G,'FIRM Load Pull'!$A:$A,$A19,'FIRM Load Pull'!$B:$B,$C19) -> 137.97891 | N19: =H19-L19 -> 7.5675742 | O19: =+H19-M19 -> 35.33447 | P19: =SUMIFS('Consol Pull'!$G:$G,'Consol Pull'!$A:$A,$A19,'Consol Pull'!$B:$B,$C19) -> 912.1587 | Q19: =H19-P19 -> -738.84531 | R19: =SUMIFS('Tracks Pull'!$E:$E,'Tracks Pull'!$A:$A,$A19,'Tracks Pull'!$B:$B,$C19) -> 254.1138 | S19: =H19-R19 -> -80.800414 | T19: =SUMIFS('Tracks Pull'!$G:$G,'Tracks Pull'!$A:$A,$A19,'Tracks Pull'!$B:$B,$C19) -> 60.192773 | U19: =O19-T19 -> -24.858304 | W19: =SUMIFS('Stream Pull'!G:G,'Stream Pull'!A:A,$A$19,'Stream Pull'!B:B,$C$19) -> 4.0310486 | X19: =SUMIFS('Stream Pull'!H:H,'Stream Pull'!A:A,$A$19,'Stream Pull'!B:B,$C$19) -> 35.227543 | Y19: =SUMIFS('Stream Pull'!M:M,'Stream Pull'!A:A,$A$19,'Stream Pull'!B:B,$C$19) -> 128.72767 | Z19: =SUM(W19:Y19) -> 167.98626 | AA19: =D19-P19 -> 143.47161 | AB19: =Z19-AA19 -> 24.514657 | AD19: =H19+Z19 -> 341.29965 | AE19: =AD19/E19-1 -> -0.65789017 | AF19: =AD19-D19 -> -714.33066
A20: Systems | C20: Japan | D20: =SUMIFS('Consol Pull'!$F:$F,'Consol Pull'!$A:$A,$A20,'Consol Pull'!$B:$B,$C20) -> 219.76523 | E20: =SUMIFS('Consol Pull'!$T:$T,'Consol Pull'!$A:$A,$A20,'Consol Pull'!$B:$B,$C20) -> 226.16138 | F20: =+D20/E20-1 -> -0.02828136 | H20: =SUMIFS('FIRM Load Pull'!$E:$E,'FIRM Load Pull'!$A:$A,$A20,'FIRM Load Pull'!$B:$B,$C20) -> 60.107739 | I20: =SUMIFS('Ship Load Pull'!$E:$E,'Ship Load Pull'!$A:$A,$A20,'Ship Load Pull'!$B:$B,$C20) -> 18.961591 | J20: =SUMIFS('FIRM Load Pull'!$Q:$Q,'FIRM Load Pull'!$A:$A,$A20,'FIRM Load Pull'!$B:$B,$C20) -> 66.651014 | K20: =H20/J20-1 -> -0.098172177 | L20: =SUMIFS('FIRM Load Pull'!$F:$F,'FIRM Load Pull'!$A:$A,$A20,'FIRM Load Pull'!$B:$B,$C20) -> 59.818929 | M20: =SUMIFS('FIRM Load Pull'!$G:$G,'FIRM Load Pull'!$A:$A,$A20,'FIRM Load Pull'!$B:$B,$C20) -> 48.163295 | N20: =H20-L20 -> 0.28880972 | O20: =+H20-M20 -> 11.944444 | P20: =SUMIFS('Consol Pull'!$G:$G,'Consol Pull'!$A:$A,$A20,'Consol Pull'!$B:$B,$C20) -> 160.53057 | Q20: =H20-P20 -> -100.42283 | R20: =SUMIFS('Tracks Pull'!$E:$E,'Tracks Pull'!$A:$A,$A20,'Tracks Pull'!$B:$B,$C20) -> 60.275722 | S20: =H20-R20 -> -0.16798272 | T20: =SUMIFS('Tracks Pull'!$G:$G,'Tracks Pull'!$A:$A,$A20,'Tracks Pull'!$B:$B,$C20) -> 8.0057104 | U20: =O20-T20 -> 3.9387339 | W20: =SUMIFS('Stream Pull'!G:G,'Stream Pull'!A:A,$A$20,'Stream Pull'!B:B,$C$20) -> 3.4392913 | X20: =SUMIFS('Stream Pull'!H:H,'Stream Pull'!A:A,$A$20,'Stream Pull'!B:B,$C$20) -> 6.0735674 | Y20: =SUMIFS('Stream Pull'!M:M,'Stream Pull'!A:A,$A$20,'Stream Pull'!B:B,$C$20) -> 46.623967 | Z20: =SUM(W20:Y20) -> 56.136826 | AA20: =D20-P20 -> 59.234663 | AB20: =Z20-AA20 -> -3.0978372 | AD20: =H20+Z20 -> 116.24456 | AE20: =AD20/E20-1 -> -0.48601055 | AF20: =AD20-D20 -> -103.52067
A21: Systems | C21: APAC | D21: =SUMIFS('Consol Pull'!$F:$F,'Consol Pull'!$A:$A,$A21,'Consol Pull'!$B:$B,$C21) -> 310.08179 | E21: =SUMIFS('Consol Pull'!$T:$T,'Consol Pull'!$A:$A,$A21,'Consol Pull'!$B:$B,$C21) -> 293.28613 | F21: =+D21/E21-1 -> 0.057267152 | H21: =SUMIFS('FIRM Load Pull'!$E:$E,'FIRM Load Pull'!$A:$A,$A21,'FIRM Load Pull'!$B:$B,$C21) -> 43.563528 | I21: =SUMIFS('Ship Load Pull'!$E:$E,'Ship Load Pull'!$A:$A,$A21,'Ship Load Pull'!$B:$B,$C21) -> 34.649021 | J21: =SUMIFS('FIRM Load Pull'!$Q:$Q,'FIRM Load Pull'!$A:$A,$A21,'FIRM Load Pull'!$B:$B,$C21) -> 49.030198 | K21: =H21/J21-1 -> -0.11149597 | L21: =SUMIFS('FIRM Load Pull'!$F:$F,'FIRM Load Pull'!$A:$A,$A21,'FIRM Load Pull'!$B:$B,$C21) -> 42.835836 | M21: =SUMIFS('FIRM Load Pull'!$G:$G,'FIRM Load Pull'!$A:$A,$A21,'FIRM Load Pull'!$B:$B,$C21) -> 44.54862 | N21: =H21-L21 -> 0.72769289 | O21: =+H21-M21 -> -0.9850915 | P21: =SUMIFS('Consol Pull'!$G:$G,'Consol Pull'!$A:$A,$A21,'Consol Pull'!$B:$B,$C21) -> 265.77664 | Q21: =H21-P21 -> -222.21311 | R21: =SUMIFS('Tracks Pull'!$E:$E,'Tracks Pull'!$A:$A,$A21,'Tracks Pull'!$B:$B,$C21) -> 95.36995 | S21: =H21-R21 -> -51.806421 | T21: =SUMIFS('Tracks Pull'!$G:$G,'Tracks Pull'!$A:$A,$A21,'Tracks Pull'!$B:$B,$C21) -> 14.442393 | U21: =O21-T21 -> -15.427484 | W21: =SUMIFS('Stream Pull'!G:G,'Stream Pull'!A:A,$A$21,'Stream Pull'!B:B,$C$21) -> 2.6655652 | X21: =SUMIFS('Stream Pull'!H:H,'Stream Pull'!A:A,$A$21,'Stream Pull'!B:B,$C$21) -> 16.562886 | Y21: =SUMIFS('Stream Pull'!M:M,'Stream Pull'!A:A,$A$21,'Stream Pull'!B:B,$C$21) -> 31.50235 | Z21: =SUM(W21:Y21) -> 50.730801 | AA21: =D21-P21 -> 44.305156 | AB21: =Z21-AA21 -> 6.4256452 | AD21: =H21+Z21 -> 94.29433 | AE21: =AD21/E21-1 -> -0.67849032 | AF21: =AD21-D21 -> -215.78746
A22: Systems | C22: WW Top | D22: =SUMIFS('Consol Pull'!$F:$F,'Consol Pull'!$A:$A,"Systems",'Consol Pull'!$B:$B,"WW",'Consol Pull'!$D:$D,"9op")+D14-'Consol Pull'!F110 -SUMIFS('Consol Pull'!$F:$F,'Consol Pull'!$A:$A,"Systems",'Consol Pull'!$B:$B,"Sum of Geos",'Consol Pull'!$D:$D,"9op") +SUMIFS('Consol Pull'!$F:$F,'Consol Pull'!$A:$A,"M&D OEM",'Consol Pull'!$B:$B,"Sum of Geos") +SUMIFS('Consol Pull'!$F:$F,'Consol Pull'!$A:$A,"Storage OEM",'Consol Pull'!$B:$B,"TOP") +SUM(D13,D15) -> 113.46528 | E22: =SUMIFS('Consol Pull'!$T:$T,'Consol Pull'!$A:$A,"Systems",'Consol Pull'!$B:$B,"WW",'Consol Pull'!$D:$D,"9op") -SUMIFS('Consol Pull'!$T:$T,'Consol Pull'!$A:$A,"Systems",'Consol Pull'!$B:$B,"Sum of Geos",'Consol Pull'!$D:$D,"9op") +SUMIFS('Consol Pull'!$T:$T,'Consol Pull'!$A:$A,"M&D OEM",'Consol Pull'!$B:$B,"Sum of Geos") +SUMIFS('Consol Pull'!$T:$T,'Consol Pull'!$A:$A,"Storage OEM",'Consol Pull'!$B:$B,"TOP")+12.74 +SUM(E13)+E14 -> 92.097483 | F22: =+D22/E22-1 -> 0.23201282 | H22: =+H14 -> 5.5241986 | J22: =SUMIFS('FIRM Load Pull'!$Q:$Q,'FIRM Load Pull'!$A:$A,"GARS",'FIRM Load Pull'!$B:$B,$C$6) -> 16.426108 | L22: =+L14 -> 5.5241986 | M22: =+M14 -> 5.5241986 | N22: =H22-L22 -> 0 | O22: =+H22-M22 -> 0 | P22: =+P14 -> 14.035644 | Q22: =H22-P22 -> -8.5114457 | R22: =R14 -> 14.035644 | W22: =SUMIFS('Stream Pull'!F:F,'Stream Pull'!A:A,$A$22,'Stream Pull'!B:B,$C$22) -> 0 | X22: =X12 -> 39.879983 | Y22: ='Stream Pull'!M106 -> 16.5 | Z22: =SUM(W22:Y22) -> 56.379983 | AA22: =D22-P22 -> 99.429636 | AB22: =Z22-AA22 -> -43.049653 | AD22: =H22+Z22 -> 61.904181 | AE22: =AD22/E22-1 -> -0.32784068 | AF22: =AD22-D22 -> -51.561099
C23: check | D23: =D9-SUM(D18:D22) -> 0 | E23: =E9-SUM(E18:E22) -> -0.00325532 | H23: =H9-SUM(H18:H22) -> 0 | I23: =I9-SUM(I18:I22) -> 0 | J23: =J9-SUM(J18:J22) -> 0 | L23: =L9-SUM(L18:L22) -> 0 | M23: =M9-SUM(M18:M22) -> 0 | N23: =N9-SUM(N18:N22) -> -4.2632564e-14 | O23: =O9-SUM(O18:O22) -> 0 | P23: =P9-SUM(P18:P22) -> 0.00015558617 | Q23: =Q9-SUM(Q18:Q22) -> -0.00015558617 | R23: =R9-SUM(R18:R22) -> 0 | S23: =S9-SUM(S18:S22) -> -3.6948222e-13 | ... U23: =U9-SUM(U18:U22) -> 0 | W23: =W9-SUM(W18:W22) -> 0 | X23: =X9-SUM(X18:X22) -> 0 | Y23: =Y9-SUM(Y18:Y22) -> 0 | Z23: =Z9-SUM(Z18:Z22) -> 0 | AA23: =AA9-SUM(AA18:AA22) -> -0.00015558617 | AB23: =AB9-SUM(AB18:AB22) -> 0.00015558617 | AD23: =AD9-SUM(AD18:AD22) -> 0 | AF23: =AF9-SUM(AF18:AF22) -> 0
C24: o/w GARS, Techn., CoreHW top | D24: =+SUM(D13:D14,D15) -> 73.224432 | E24: =+SUM(E13:E14) -> 32.953726
A25: Systems | B25: Top | C25: o/w Systems OEM | D25: =SUMIFS('Consol Pull'!$F:$F,'Consol Pull'!$A:$A,$A25,'Consol Pull'!$B:$B,$B25) -> 41.940156 | E25: =SUMIFS('Consol Pull'!$T:$T,'Consol Pull'!$A:$A,$A25,'Consol Pull'!$B:$B,$B25) -> 29.928714
A26: Systems | B26: GEO Elims | C26: GEO Elims | D26: =SUMIFS('Consol Pull'!$F:$F,'Consol Pull'!$A:$A,$A26,'Consol Pull'!$B:$B,$B26) -> 0 | E26: =SUMIFS('Consol Pull'!$T:$T,'Consol Pull'!$A:$A,$A26,'Consol Pull'!$B:$B,$B26) -> -10.515255
A27: Storage OEM | B27: Top | C27: Storage OEM (2B) | D27: =SUMIFS('Consol Pull'!$F:$F,'Consol Pull'!$A:$A,$A27,'Consol Pull'!$B:$B,$B27) -> 0 | E27: =SUMIFS('Consol Pull'!$T:$T,'Consol Pull'!$A:$A,$A27,'Consol Pull'!$B:$B,$B27) -> 16.733294
A28: M&D OEM | B28: Sum of Geos | C28: Storage OEM TOP (M&D) | D28: =+SUMIFS('Consol Pull'!$F:$F,'Consol Pull'!$A:$A,"M&D OEM",'Consol Pull'!$B:$B,"Sum of Geos") -> 0 | E28: =+SUMIFS('Consol Pull'!$T:$T,'Consol Pull'!$A:$A,"M&D OEM",'Consol Pull'!$B:$B,"Sum of Geos") -> 10.257005
C29: Other | D29: =+D22-D24-D25-D26-D27-D28 -> -1.6993068 | E29: =+E22-E24-E25-E26-E27-E28 -> 12.74
D45: M | E45: aa | H45: H | J45: R | L45: I | M45: J | P45: N | W45: P | Y45: I
C46: WW | D46: Budget | H46: FIRM LOAD (HW) | W46: NonHW | AD46: TOTAL LOAD
C47: QTD | D47: =INPUT!$B$4 -> NovQTD | F47: YtY | H47: Load | I47: o/w shipped | J47: PY | K47: YtY | L47: PD1Q | M47: PW1Q | N47: DtD | O47: WtW | P47: HW Budget | Q47: B/(W) to Budget | R47: =CONCATENATE("Track ", +'Tracks Pull'!E12) -> Track WK7 | S47: B/(W) Track | T47: =+'Tracks Pull'!G12 -> WtW | U47: WtW B/(W) Track | W47: SW Tx Firm | X47: SW Tx ToGo | Y47: ISC Annuity | Z47: NonHW Trans+Annuity | AA47: NonHW Budget | AB47: B/(W) Bgt | AD47: FIRM + NonHW | AE47: YtY | AF47: B/(W) to Budget
C49: Systems w/o TPS | D49: =SUM(D50:D55) -> 622.38845 | E49: =SUM(E50:E55) -> 635.99271 | F49: =+D49/E49-1 -> -0.021390594 | H49: =SUM(H50:H55) -> 326.86944 | I49: =SUM(I50:I55) -> 255.74594 | J49: =SUM(J50:J55) -> 211.4149 | K49: =H49/J49-1 -> 0.54610409 | L49: =SUM(L50:L55) -> 304.00238 | M49: =SUM(M50:M55) -> 301.65466 | N49: =SUM(N50:N55) -> 22.867062 | O49: =SUM(O50:O55) -> 25.214784 | P49: =SUM(P50:P55) -> 329.3816 | Q49: =SUM(Q50:Q55) -> -2.5121556 | R49: =SUM(R50:R55) -> 666.08143 | S49: =SUM(S50:S54) -> -339.21199 | T49: =SUM(T50:T55) -> 128.13559 | U49: =SUM(U50:U55) -> -102.9208 | W49: =SUM(W50:W54) -> 15.083014 | X49: =SUM(X50:X54) -> 157.72682 | Y49: =SUM(Y50:Y54) -> 259.95653 | Z49: =SUM(Z50:Z54) -> 432.76636 | AA49: =SUM(AA50:AA55) -> 286.77831 | AB49: =SUM(AB50:AB55) -> 145.98805 | AD49: =SUM(AD50:AD55) -> 759.6358 | AE49: =AD49/E49-1 -> 0.1944096 | AF49: =SUM(AF50:AF55) -> 143.47589
A50: 26 | C50: Traditional z | D50: =SUMIFS('Consol Pull'!$M:$M,'Consol Pull'!$A:$A,$A50,'Consol Pull'!$B:$B,$C$6) -> 214.34423 | E50: =SUMIFS('Consol Pull'!$AA:$AA,'Consol Pull'!$A:$A,$A50,'Consol Pull'!$B:$B,$C$6) -> 223.94316 | F50: =+D50/E50-1 -> -0.042863277 | H50: =SUMIFS('FIRM Load Pull'!$K:$K,'FIRM Load Pull'!$A:$A,$A50,'FIRM Load Pull'!$B:$B,$C$6) -> 61.932788 | I50: =SUMIFS('Ship Load Pull'!$H:$H,'Ship Load Pull'!$A:$A,$A50,'Ship Load Pull'!$B:$B,$C6) -> 34.231828 | J50: =SUMIFS('FIRM Load Pull'!$O:$O,'FIRM Load Pull'!$A:$A,$A50,'FIRM Load Pull'!$B:$B,$C$6) -> 40.810043 | K50: =H50/J50-1 -> 0.51758691 | L50: =SUMIFS('FIRM Load Pull'!$L:$L,'FIRM Load Pull'!$A:$A,$A50,'FIRM Load Pull'!$B:$B,$C$6) -> 41.901241 | M50: =SUMIFS('FIRM Load Pull'!$M:$M,'FIRM Load Pull'!$A:$A,$A50,'FIRM Load Pull'!$B:$B,$C$6) -> 33.812883 | N50: =H50-L50 -> 20.031546 | O50: =+H50-M50 -> 28.119905 | P50: =SUMIFS('Consol Pull'!$N:$N,'Consol Pull'!$A:$A,$A50,'Consol Pull'!$B:$B,$C$6) -> 65.657107 | Q50: =H50-P50 -> -3.7243196 | R50: =SUMIFS('Tracks Pull'!$E:$E,'Tracks Pull'!$A:$A,$A50,'Tracks Pull'!$B:$B,$C$6) -> 78.144301 | S50: =H50-R50 -> -16.211514 | T50: =SUMIFS('Tracks Pull'!$G:$G,'Tracks Pull'!$A:$A,$A50,'Tracks Pull'!$B:$B,$C$6) -> 6.2485135 | U50: =O50-T50 -> 21.871391 | W50: =SUMIFS('Stream Pull'!O:O,'Stream Pull'!A:A,$A$50,'Stream Pull'!B:B,$C$6) -> 1.0072507 | X50: =SUMIFS('Stream Pull'!P:P,'Stream Pull'!A:A,$A$50,'Stream Pull'!B:B,$C$6) -> 58.941317 | Y50: =SUMIFS('Stream Pull'!Q:Q,'Stream Pull'!A:A,$A$50,'Stream Pull'!B:B,$C$6) -> 157.03372 | Z50: =SUM(W50:Y50) -> 216.98229 | AA50: =D50-P50 -> 148.68712 | AB50: =Z50-AA50 -> 68.295167 | AD50: =H50+Z50 -> 278.91507 | AE50: =AD50/E50-1 -> 0.24547259 | AF50: =AD50-D50 -> 64.570847
A51: Power | C51: Power HW | D51: =SUMIFS('Consol Pull'!$M:$M,'Consol Pull'!$A:$A,$A51,'Consol Pull'!$B:$B,$C$6) -> 191.71786 | E51: =SUMIFS('Consol Pull'!$AA:$AA,'Consol Pull'!$A:$A,$A51,'Consol Pull'!$B:$B,$C$6) -> 206.01132 | F51: =+D51/E51-1 -> -0.06938192 | H51: =SUMIFS('FIRM Load Pull'!$K:$K,'FIRM Load Pull'!$A:$A,$A51,'FIRM Load Pull'!$B:$B,$C$6) -> 67.451094 | I51: =SUMIFS('Ship Load Pull'!$H:$H,'Ship Load Pull'!$A:$A,$A51,'Ship Load Pull'!$B:$B,$C6) -> 62.466535 | J51: =SUMIFS('FIRM Load Pull'!$O:$O,'FIRM Load Pull'!$A:$A,$A51,'FIRM Load Pull'!$B:$B,$C$6) -> 57.055421 | K51: =H51/J51-1 -> 0.18220308 | L51: =SUMIFS('FIRM Load Pull'!$L:$L,'FIRM Load Pull'!$A:$A,$A51,'FIRM Load Pull'!$B:$B,$C$6) -> 67.082304 | M51: =SUMIFS('FIRM Load Pull'!$M:$M,'FIRM Load Pull'!$A:$A,$A51,'FIRM Load Pull'!$B:$B,$C$6) -> 64.228395 | N51: =H51-L51 -> 0.36879033 | O51: =+H51-M51 -> 3.2226993 | P51: =SUMIFS('Consol Pull'!$N:$N,'Consol Pull'!$A:$A,$A51,'Consol Pull'!$B:$B,$C$6) -> 90.548501 | Q51: =H51-P51 -> -23.097407 | R51: =SUMIFS('Tracks Pull'!$E:$E,'Tracks Pull'!$A:$A,$A51,'Tracks Pull'!$B:$B,$C$6) -> 174.74552 | S51: =H51-R51 -> -107.29443 | T51: =SUMIFS('Tracks Pull'!$G:$G,'Tracks Pull'!$A:$A,$A51,'Tracks Pull'!$B:$B,$C$6) -> 39.714158 | U51: =O51-T51 -> -36.491459 | W51: =SUMIFS('Stream Pull'!O:O,'Stream Pull'!A:A,$A$51,'Stream Pull'!B:B,$C$6) -> 14.19578 | X51: =SUMIFS('Stream Pull'!P:P,'Stream Pull'!A:A,$A$51,'Stream Pull'!B:B,$C$6) -> 58.905516 | Y51: =SUMIFS('Stream Pull'!Q:Q,'Stream Pull'!A:A,$A$51,'Stream Pull'!B:B,$C$6) -> 80.375683 | Z51: =SUM(W51:Y51) -> 153.47698 | AA51: =D51-P51 -> 101.16936 | AB51: =Z51-AA51 -> 52.307623 | AD51: =H51+Z51 -> 220.92807 | AE51: =AD51/E51-1 -> 0.072407454 | AF51: =AD51-D51 -> 29.210216
A52: Storage | C52: Storage HW | D52: =SUMIFS('Consol Pull'!$M:$M,'Consol Pull'!$A:$A,$A52,'Consol Pull'!$B:$B,$C$6) -> 204.59884 | E52: =SUMIFS('Consol Pull'!$AA:$AA,'Consol Pull'!$A:$A,$A52,'Consol Pull'!$B:$B,$C$6) -> 189.68073 | F52: =+D52/E52-1 -> 0.078648506 | H52: =SUMIFS('FIRM Load Pull'!$K:$K,'FIRM Load Pull'!$A:$A,$A52,'FIRM Load Pull'!$B:$B,$C$6) -> 193.22002 | I52: =SUMIFS('Ship Load Pull'!$H:$H,'Ship Load Pull'!$A:$A,$A52,'Ship Load Pull'!$B:$B,$C6) -> 159.04758 | J52: =SUMIFS('FIRM Load Pull'!$O:$O,'FIRM Load Pull'!$A:$A,$A52,'FIRM Load Pull'!$B:$B,$C$6) -> 103.82561 | K52: =H52/J52-1 -> 0.86100549 | L52: =SUMIFS('FIRM Load Pull'!$L:$L,'FIRM Load Pull'!$A:$A,$A52,'FIRM Load Pull'!$B:$B,$C$6) -> 190.7533 | M52: =SUMIFS('FIRM Load Pull'!$M:$M,'FIRM Load Pull'!$A:$A,$A52,'FIRM Load Pull'!$B:$B,$C$6) -> 199.34784 | N52: =H52-L52 -> 2.4667258 | O52: =+H52-M52 -> -6.1278197 | P52: =SUMIFS('Consol Pull'!$N:$N,'Consol Pull'!$A:$A,"Storage",'Consol Pull'!$B:$B,"Sum of Geos",'Consol Pull'!$D:$D,"9op") -> 167.677 | Q52: =H52-P52 -> 25.543021 | R52: =SUMIFS('Tracks Pull'!$E:$E,'Tracks Pull'!$A:$A,$A52,'Tracks Pull'!$B:$B,$C$6) -> 407.69262 | S52: =H52-R52 -> -214.4726 | T52: =SUMIFS('Tracks Pull'!$G:$G,'Tracks Pull'!$A:$A,$A52,'Tracks Pull'!$B:$B,$C$6) -> 82.172916 | U52: =O52-T52 -> -88.300735 | W52: =SUMIFS('Stream Pull'!O:O,'Stream Pull'!A:A,$A$52,'Stream Pull'!B:B,$C$6) -> -0.1200171 | X52: =SUMIFS('Stream Pull'!F:F,'Stream Pull'!A:A,$A$52,'Stream Pull'!B:B,$C$6) -> 39.879983 | Y52: =SUMIFS('Stream Pull'!Q:Q,'Stream Pull'!A:A,$A$52,'Stream Pull'!B:B,$C$6) -> 12.047126 | Z52: =SUM(W52:Y52) -> 51.807092 | AA52: =D52-P52 -> 36.921835 | AB52: =Z52-AA52 -> 14.885256 | AD52: =H52+Z52 -> 245.02711 | AE52: =AD52/E52-1 -> 0.29178706 | AF52: =AD52-D52 -> 40.428278
A53: Technology | C53: Technology | D53: =SUMIFS('Consol Pull'!$M:$M,'Consol Pull'!$A:$A,$A53,'Consol Pull'!$B:$B,$C$6) -> 0 | E53: =SUMIFS('Consol Pull'!$AA:$AA,'Consol Pull'!$A:$A,$A53,'Consol Pull'!$B:$B,$C$6) -> 7.530785 | F53: =+D53/E53-1 -> -1 | Y53: ='Stream Pull'!N106 -> 10.5 | Z53: =SUM(W53:Y53) -> 10.5 | AA53: =D53-P53 -> 0 | AB53: =Z53-AA53 -> 10.5 | AD53: =H53+Z53 -> 10.5 | AE53: =AD53/E53-1 -> 0.39427695 | AF53: =AD53-D53 -> 10.5
A54: GARS | C54: GARS | D54: =SUMIFS('Consol Pull'!$M:$M,'Consol Pull'!$A:$A,$A54,'Consol Pull'!$B:$B,$C$6) -> 5.4989886 | E54: =SUMIFS('Consol Pull'!$AA:$AA,'Consol Pull'!$A:$A,$A54,'Consol Pull'!$B:$B,$C$6) -> 4.5561461 | F54: =+D54/E54-1 -> 0.20693862 | H54: =SUMIFS('FIRM Load Pull'!$K:$K,'FIRM Load Pull'!$A:$A,$A54,'FIRM Load Pull'!$B:$B,$C$6) -> 4.2655386 | I54: =SUMIFS('Ship Load Pull'!$H:$H,'Ship Load Pull'!$A:$A,$A54,'Ship Load Pull'!$B:$B,$C6) -> 0 | J54: =SUMIFS('FIRM Load Pull'!$O:$O,'FIRM Load Pull'!$A:$A,$A54,'FIRM Load Pull'!$B:$B,$C$6) -> 9.723831 | K54: =H54/J54-1 -> -0.56133148 | L54: =SUMIFS('FIRM Load Pull'!$L:$L,'FIRM Load Pull'!$A:$A,$A54,'FIRM Load Pull'!$B:$B,$C$6) -> 4.2655386 | M54: =SUMIFS('FIRM Load Pull'!$M:$M,'FIRM Load Pull'!$A:$A,$A54,'FIRM Load Pull'!$B:$B,$C$6) -> 4.2655386 | N54: =H54-L54 -> 0 | O54: =+H54-M54 -> 0 | P54: =SUMIFS('Consol Pull'!$N:$N,'Consol Pull'!$A:$A,$A54,'Consol Pull'!$B:$B,$C$6) -> 5.4989886 | Q54: =H54-P54 -> -1.2334501 | R54: =P54 -> 5.4989886 | S54: =H54-R54 -> -1.2334501 | AA54: =D54-P54 -> 0 | AD54: =H54+Z54 -> 4.2655386 | AE54: =AD54/E54-1 -> -0.063783622 | AF54: =AD54-D54 -> -1.2334501
A55: Division Top | C55: Core HW Top (78, 5R, SP) | D55: =SUMIFS('Consol Pull'!$M:$M,'Consol Pull'!$A:$A,$A55,'Consol Pull'!$B:$B,$C$6) -> 6.2285389 | E55: =SUMIFS('Consol Pull'!$AA:$AA,'Consol Pull'!$A:$A,$A55,'Consol Pull'!$B:$B,$C$6) -> 4.2705658 | F55: =+D55/E55-1 -> 0.45848095
C57: Geography w/o GARS
A58: Systems | C58: Americas | D58: =SUMIFS('Consol Pull'!$M:$M,'Consol Pull'!$A:$A,$A58,'Consol Pull'!$B:$B,$C58) -> 244.18439 | E58: =SUMIFS('Consol Pull'!$AA:$AA,'Consol Pull'!$A:$A,$A58,'Consol Pull'!$B:$B,$C58) -> 243.69497 | F58: =+D58/E58-1 -> 0.002008339 | H58: =SUMIFS('FIRM Load Pull'!$K:$K,'FIRM Load Pull'!$A:$A,$A58,'FIRM Load Pull'!$B:$B,$C58) -> 147.23285 | I58: =SUMIFS('Ship Load Pull'!$H:$H,'Ship Load Pull'!$A:$A,$A58,'Ship Load Pull'!$B:$B,$C58) -> 108.82448 | J58: =SUMIFS('FIRM Load Pull'!$O:$O,'FIRM Load Pull'!$A:$A,$A58,'FIRM Load Pull'!$B:$B,$C58) -> 67.235771 | K58: =H58/J58-1 -> 1.1897994 | L58: =SUMIFS('FIRM Load Pull'!$L:$L,'FIRM Load Pull'!$A:$A,$A58,'FIRM Load Pull'!$B:$B,$C58) -> 126.92222 | M58: =SUMIFS('FIRM Load Pull'!$M:$M,'FIRM Load Pull'!$A:$A,$A58,'FIRM Load Pull'!$B:$B,$C58) -> 110.65816 | N58: =H58-L58 -> 20.310629 | O58: =+H58-M58 -> 36.574687 | P58: =SUMIFS('Consol Pull'!$N:$N,'Consol Pull'!$A:$A,$A58,'Consol Pull'!$B:$B,$C58) -> 118.32363 | Q58: =H58-P58 -> 28.909214 | R58: =SUMIFS('Tracks Pull'!$E:$E,'Tracks Pull'!$A:$A,$A58,'Tracks Pull'!$B:$B,$C58) -> 250.82298 | S58: =H58-R58 -> -103.59013 | T58: =SUMIFS('Tracks Pull'!$G:$G,'Tracks Pull'!$A:$A,$A58,'Tracks Pull'!$B:$B,$C58) -> 45.494711 | U58: =O58-T58 -> -8.920024 | W58: =SUMIFS('Stream Pull'!O:O,'Stream Pull'!A:A,$A$58,'Stream Pull'!B:B,$C$18) -> 4.9471084 | X58: =SUMIFS('Stream Pull'!H:H,'Stream Pull'!A:A,$A$58,'Stream Pull'!B:B,$C$58) -> 59.982836 | Y58: =SUMIFS('Stream Pull'!Q:Q,'Stream Pull'!A:A,$A$58,'Stream Pull'!B:B,$C$58) -> 118.71689 | Z58: =SUM(W58:Y58) -> 183.64684 | AA58: =D58-P58 -> 125.86076 | AB58: =Z58-AA58 -> 57.78608 | AD58: =H58+Z58 -> 330.87969 | AE58: =AD58/E58-1 -> 0.35776165 | AF58: =AD58-D58 -> 86.695294
A59: Systems | C59: EMEA | D59: =SUMIFS('Consol Pull'!$M:$M,'Consol Pull'!$A:$A,$A59,'Consol Pull'!$B:$B,$C59) -> 194.13479 | E59: =SUMIFS('Consol Pull'!$AA:$AA,'Consol Pull'!$A:$A,$A59,'Consol Pull'!$B:$B,$C59) -> 198.53636 | F59: =+D59/E59-1 -> -0.022170106 | H59: =SUMIFS('FIRM Load Pull'!$K:$K,'FIRM Load Pull'!$A:$A,$A59,'FIRM Load Pull'!$B:$B,$C59) -> 120.02377 | I59: =SUMIFS('Ship Load Pull'!$H:$H,'Ship Load Pull'!$A:$A,$A59,'Ship Load Pull'!$B:$B,$C59) -> 93.310852 | J59: =SUMIFS('FIRM Load Pull'!$O:$O,'FIRM Load Pull'!$A:$A,$A59,'FIRM Load Pull'!$B:$B,$C59) -> 76.798547 | K59: =H59/J59-1 -> 0.56283911 | L59: =SUMIFS('FIRM Load Pull'!$L:$L,'FIRM Load Pull'!$A:$A,$A59,'FIRM Load Pull'!$B:$B,$C59) -> 117.55949 | M59: =SUMIFS('FIRM Load Pull'!$M:$M,'FIRM Load Pull'!$A:$A,$A59,'FIRM Load Pull'!$B:$B,$C59) -> 110.14969 | N59: =H59-L59 -> 2.4642795 | O59: =+H59-M59 -> 9.8740862 | P59: =SUMIFS('Consol Pull'!$N:$N,'Consol Pull'!$A:$A,$A59,'Consol Pull'!$B:$B,$C59) -> 110.47923 | Q59: =H59-P59 -> 9.5445383 | R59: =SUMIFS('Tracks Pull'!$E:$E,'Tracks Pull'!$A:$A,$A59,'Tracks Pull'!$B:$B,$C59) -> 254.1138 | S59: =H59-R59 -> -134.09002 | T59: =SUMIFS('Tracks Pull'!$G:$G,'Tracks Pull'!$A:$A,$A59,'Tracks Pull'!$B:$B,$C59) -> 60.192773 | U59: =O59-T59 -> -50.318687 | W59: =SUMIFS('Stream Pull'!O:O,'Stream Pull'!A:A,$A$59,'Stream Pull'!B:B,$C$19) -> 4.0310486 | X59: =SUMIFS('Stream Pull'!H:H,'Stream Pull'!A:A,$A$59,'Stream Pull'!B:B,$C$59) -> 35.227543 | Y59: =SUMIFS('Stream Pull'!Q:Q,'Stream Pull'!A:A,$A$59,'Stream Pull'!B:B,$C$59) -> 80.201564 | Z59: =SUM(W59:Y59) -> 119.46016 | AA59: =D59-P59 -> 83.655553 | AB59: =Z59-AA59 -> 35.804603 | AD59: =H59+Z59 -> 239.48393 | AE59: =AD59/E59-1 -> 0.2062472 | AF59: =AD59-D59 -> 45.349141
A60: Systems | C60: Japan | D60: =SUMIFS('Consol Pull'!$M:$M,'Consol Pull'!$A:$A,$A60,'Consol Pull'!$B:$B,$C60) -> 69.588246 | E60: =SUMIFS('Consol Pull'!$AA:$AA,'Consol Pull'!$A:$A,$A60,'Consol Pull'!$B:$B,$C60) -> 92.165078 | F60: =+D60/E60-1 -> -0.24496081 | H60: =SUMIFS('FIRM Load Pull'!$K:$K,'FIRM Load Pull'!$A:$A,$A60,'FIRM Load Pull'!$B:$B,$C60) -> 18.138723 | I60: =SUMIFS('Ship Load Pull'!$H:$H,'Ship Load Pull'!$A:$A,$A60,'Ship Load Pull'!$B:$B,$C60) -> 18.961591 | J60: =SUMIFS('FIRM Load Pull'!$O:$O,'FIRM Load Pull'!$A:$A,$A60,'FIRM Load Pull'!$B:$B,$C60) -> 28.703528 | K60: =H60/J60-1 -> -0.36806644 | L60: =SUMIFS('FIRM Load Pull'!$L:$L,'FIRM Load Pull'!$A:$A,$A60,'FIRM Load Pull'!$B:$B,$C60) -> 18.138723 | M60: =SUMIFS('FIRM Load Pull'!$M:$M,'FIRM Load Pull'!$A:$A,$A60,'FIRM Load Pull'!$B:$B,$C60) -> 35.549125 | N60: =H60-L60 -> 2.9999999e-08 | O60: =+H60-M60 -> -17.410402 | P60: =SUMIFS('Consol Pull'!$N:$N,'Consol Pull'!$A:$A,$A60,'Consol Pull'!$B:$B,$C60) -> 39.455971 | Q60: =H60-P60 -> -21.317248 | R60: =SUMIFS('Tracks Pull'!$E:$E,'Tracks Pull'!$A:$A,$A60,'Tracks Pull'!$B:$B,$C60) -> 60.275722 | S60: =H60-R60 -> -42.136999 | T60: =SUMIFS('Tracks Pull'!$G:$G,'Tracks Pull'!$A:$A,$A60,'Tracks Pull'!$B:$B,$C60) -> 8.0057104 | U60: =O60-T60 -> -25.416112 | W60: =SUMIFS('Stream Pull'!O:O,'Stream Pull'!A:A,$A$60,'Stream Pull'!B:B,$C$20) -> 3.4392913 | X60: =SUMIFS('Stream Pull'!H:H,'Stream Pull'!A:A,$A$60,'Stream Pull'!B:B,$C$60) -> 6.0735674 | Y60: =SUMIFS('Stream Pull'!Q:Q,'Stream Pull'!A:A,$A$60,'Stream Pull'!B:B,$C$60) -> 32.108 | Z60: =SUM(W60:Y60) -> 41.620859 | AA60: =D60-P60 -> 30.132275 | AB60: =Z60-AA60 -> 11.488583 | AD60: =H60+Z60 -> 59.759582 | AE60: =AD60/E60-1 -> -0.35160277 | AF60: =AD60-D60 -> -9.8286645
A61: Systems | C61: APAC | D61: =SUMIFS('Consol Pull'!$M:$M,'Consol Pull'!$A:$A,$A61,'Consol Pull'!$B:$B,$C61) -> 75.191163 | E61: =SUMIFS('Consol Pull'!$AA:$AA,'Consol Pull'!$A:$A,$A61,'Consol Pull'!$B:$B,$C61) -> 57.215342 | F61: =+D61/E61-1 -> 0.31417835 | H61: =SUMIFS('FIRM Load Pull'!$K:$K,'FIRM Load Pull'!$A:$A,$A61,'FIRM Load Pull'!$B:$B,$C61) -> 37.20856 | I61: =SUMIFS('Ship Load Pull'!$H:$H,'Ship Load Pull'!$A:$A,$A61,'Ship Load Pull'!$B:$B,$C61) -> 34.649021 | J61: =SUMIFS('FIRM Load Pull'!$O:$O,'FIRM Load Pull'!$A:$A,$A61,'FIRM Load Pull'!$B:$B,$C61) -> 28.953224 | K61: =H61/J61-1 -> 0.28512666 | L61: =SUMIFS('FIRM Load Pull'!$L:$L,'FIRM Load Pull'!$A:$A,$A61,'FIRM Load Pull'!$B:$B,$C61) -> 37.116406 | M61: =SUMIFS('FIRM Load Pull'!$M:$M,'FIRM Load Pull'!$A:$A,$A61,'FIRM Load Pull'!$B:$B,$C61) -> 41.032148 | N61: =H61-L61 -> 0.092154097 | O61: =+H61-M61 -> -3.8235875 | P61: =SUMIFS('Consol Pull'!$N:$N,'Consol Pull'!$A:$A,$A61,'Consol Pull'!$B:$B,$C61) -> 55.62377 | Q61: =H61-P61 -> -18.41521 | R61: =SUMIFS('Tracks Pull'!$E:$E,'Tracks Pull'!$A:$A,$A61,'Tracks Pull'!$B:$B,$C61) -> 95.36995 | S61: =H61-R61 -> -58.161389 | T61: =SUMIFS('Tracks Pull'!$G:$G,'Tracks Pull'!$A:$A,$A61,'Tracks Pull'!$B:$B,$C61) -> 14.442393 | U61: =O61-T61 -> -18.26598 | W61: =SUMIFS('Stream Pull'!O:O,'Stream Pull'!A:A,$A$61,'Stream Pull'!B:B,$C$21) -> 2.6655652 | X61: =SUMIFS('Stream Pull'!H:H,'Stream Pull'!A:A,$A$61,'Stream Pull'!B:B,$C$61) -> 16.562886 | Y61: =SUMIFS('Stream Pull'!Q:Q,'Stream Pull'!A:A,$A$61,'Stream Pull'!B:B,$C$61) -> 18.430069 | Z61: =SUM(W61:Y61) -> 37.658521 | AA61: =D61-P61 -> 19.567393 | AB61: =Z61-AA61 -> 18.091128 | AD61: =H61+Z61 -> 74.867081 | AE61: =AD61/E61-1 -> 0.30851409 | AF61: =AD61-D61 -> -0.32408246
A62: Systems | C62: Top | D62: =SUMIFS('Consol Pull'!$M:$M,'Consol Pull'!$A:$A,"Systems",'Consol Pull'!$B:$B,"WW",'Consol Pull'!$D:$D,"9op")+D54 -SUMIFS('Consol Pull'!$M:$M,'Consol Pull'!$A:$A,"Systems",'Consol Pull'!$B:$B,"Sum of Geos",'Consol Pull'!$D:$D,"9op") +SUMIFS('Consol Pull'!$M:$M,'Consol Pull'!$A:$A,"M&D OEM",'Consol Pull'!$B:$B,"Sum of Geos") +SUMIFS('Consol Pull'!$M:$M,'Consol Pull'!$A:$A,"Storage OEM",'Consol Pull'!$B:$B,"TOP")+5.1 +SUM(D53) -> 39.289689 | E62: =SUMIFS('Consol Pull'!$AA:$AA,'Consol Pull'!$A:$A,"Systems",'Consol Pull'!$B:$B,"WW",'Consol Pull'!$D:$D,"9op") -SUMIFS('Consol Pull'!$AA:$AA,'Consol Pull'!$A:$A,"Systems",'Consol Pull'!$B:$B,"Sum of Geos",'Consol Pull'!$D:$D,"9op") +SUMIFS('Consol Pull'!$AA:$AA,'Consol Pull'!$A:$A,"M&D OEM",'Consol Pull'!$B:$B,"Sum of Geos") +SUMIFS('Consol Pull'!$AA:$AA,'Consol Pull'!$A:$A,"Storage OEM",'Consol Pull'!$B:$B,"TOP")+7.69 +SUM(E53) -> 44.381454 | F62: =+D62/E62-1 -> -0.11472732 | H62: =H54 -> 4.2655386 | J62: =SUMIFS('FIRM Load Pull'!$O:$O,'FIRM Load Pull'!$A:$A,"GARS",'FIRM Load Pull'!$B:$B,$C$6) -> 9.723831 | L62: =L54 -> 4.2655386 | M62: =M54 -> 4.2655386 | N62: =H62-L62 -> 0 | O62: =+H62-M62 -> 0 | P62: =+P54 -> 5.4989886 | Q62: =H62-P62 -> -1.2334501 | R62: =P62 -> 5.4989886 | S62: =H62-R62 -> -1.2334501 | T62: =T54 -> 0 | X62: =X52 -> 39.879983 | Y62: =Y53 -> 10.5 | Z62: =SUM(W62:Y62) -> 50.379983 | AA62: =D62-P62-6.23 -> 27.5607 | AB62: =Z62-AA62 -> 22.819283 | AD62: =H62+Z62 -> 54.645521 | AE62: =AD62/E62-1 -> 0.23126928 | AF62: =AD62-D62+6.23 -> 21.585833
C63: check | D63: =D49-SUM(D58:D62) -> 0.00016851861 | E63: =E49-SUM(E58:E62) -> -0.0004951 | H63: =H49-SUM(H58:H62) -> 0 | J63: =J49-SUM(J58:J62) -> 0 | L63: =L49-SUM(L58:L62) -> 0 | M63: =M49-SUM(M58:M62) -> 0 | N63: =N49-SUM(N58:N62) -> 0 | O63: =O49-SUM(O58:O62) -> 0 | P63: =P49-SUM(P58:P62) -> 0 | Q63: =Q49-SUM(Q58:Q62) -> -2.8776981e-13 | R63: =R49-SUM(R58:R62) -> 0 | S63: =S49-SUM(S58:S62) -> 0 | ... U63: =U49-SUM(U58:U62) -> 0 | W63: =W49-SUM(W58:W62) -> 0 | X63: =X49-SUM(X58:X62) -> 0 | Y63: =Y49-SUM(Y58:Y62) -> 0 | Z63: =Z49-SUM(Z58:Z62) -> 0 | AA63: =AA49-SUM(AA58:AA62) -> 0.0016295717 | AB63: =AB49-SUM(AB58:AB62) -> -0.0016295717 | AD63: =AD49-SUM(AD58:AD62) -> 0 | AF63: =AF49-SUM(AF58:AF62) -> -0.0016295717
C64: o/w GARS, Technology | D64: =+D53+D54 -> 5.4989886 | E64: =+E53+E54 -> 12.086931
A65: Systems | B65: Top | C65: o/w Systems OEM | D65: =SUMIFS('Consol Pull'!$M:$M,'Consol Pull'!$A:$A,$A65,'Consol Pull'!$B:$B,$B65) -> 28.6907 | E65: =SUMIFS('Consol Pull'!$AA:$AA,'Consol Pull'!$A:$A,$A65,'Consol Pull'!$B:$B,$B65) -> 15.88469
A66: Systems | B66: GEO Elims | C66: GEO Elims | D66: =SUMIFS('Consol Pull'!$M:$M,'Consol Pull'!$A:$A,$A66,'Consol Pull'!$B:$B,$B66) -> 0 | E66: =SUMIFS('Consol Pull'!$AA:$AA,'Consol Pull'!$A:$A,$A66,'Consol Pull'!$B:$B,$B66) -> -9.4089798
A67: Storage OEM | B67: Top | C67: Storage OEM (2B) | D67: =SUMIFS('Consol Pull'!$M:$M,'Consol Pull'!$A:$A,$A67,'Consol Pull'!$B:$B,$B67) -> 0 | E67: =SUMIFS('Consol Pull'!$AA:$AA,'Consol Pull'!$A:$A,$A67,'Consol Pull'!$B:$B,$B67) -> 10.468269
A68: M&D OEM | B68: Sum of Geos | C68: Storage OEM TOP (M&D) | D68: =+SUMIFS('Consol Pull'!$M:$M,'Consol Pull'!$A:$A,"M&D OEM",'Consol Pull'!$B:$B,"Sum of Geos") -> 0 | E68: =+SUMIFS('Consol Pull'!$AA:$AA,'Consol Pull'!$A:$A,"M&D OEM",'Consol Pull'!$B:$B,"Sum of Geos") -> 12.21669
C69: Other | D69: =+D62-D64-D65-D66-D67-D68 -> 5.1 | E69: =+E62-E64-E65-E66-E67-E68 -> 3.1338539

Sheet Geos
E10: Budget | I10: FIRM LOAD (HW) | AC10: NonHW | AK10: TOTAL LOAD | AO10: PROJECTED *
E11: =INPUT!B2 -> 4Q | G11: YtY | I11: Load | J11: o/w shipped | K11: YtY | L11: DtD | M11: WtW | N11: HW Budget | O11: B/(W) to Budget | P11: B/(W) Track | Q11: WtW B/(W) Track | R11: YtY | U11: DtD | V11: WtW | W11: B/(W) to Budget | Y11: B/(W) Track | AA11: WtW B/(W) Track | AC11: Trans modeled | AD11: SW Tx Firm | AE11: SW Tx ToGo | AF11: ISC Annuity | AG11: NonHW Trans+Annuity | AH11: NonHW Budget | AI11: B/(W) Bgt | AK11: Load + NonHW | AL11: YtY | AM11: B/(W) to Budget | AO11: PROJECTED Unfirm | AP11: Proj Load | AQ11: B/(W) to Budget
A12: BRAND | B12: GEO | E12: =WW!D10 -> 1670.7777 | F12: =WW!E10 -> 1223.6108 | G12: =WW!F10 -> 0.3654486 | H12: =WW!G10 -> 0 | I12: =WW!H10 -> 129.49898 | J12: =WW!J10 -> 64.110296 | K12: =WW!K10 -> 1.0199404 | L12: =WW!N10 -> 20.031546 | M12: =WW!O10 -> 55.354417 | N12: =WW!P10 -> 1440.3421 | O12: =WW!Q10 -> -1310.8432 | P12: =WW!S10 -> 51.354676 | Q12: =WW!U10 -> 49.105904 | R12: =WW!#REF! -> #REF! | S12: =WW!#REF! -> #REF! | T12: =WW!#REF! -> #REF! | U12: =WW!#REF! -> #REF! | V12: =WW!#REF! -> #REF! | W12: =WW!#REF! -> #REF! | X12: =WW!#REF! -> #REF! | Y12: =WW!#REF! -> #REF! | ... AB12: =WW!#REF! -> #REF! | AC12: =WW!W10 -> 1.0072507 | AF12: =WW!Y10 -> 249.32861 | AG12: =WW!Z10 -> 309.27718 | AH12: =WW!AA10 -> 230.43557 | AI12: =WW!AB10 -> 78.841612 | AJ12: =WW!AC10 -> 0 | AK12: =WW!AD10 -> 438.77616 | AL12: =WW!AE10 -> -0.64140873 | AM12: =WW!AF10 -> -1232.0015 | AR12: check
A13: 26 | B13: WW | C13: WW | D13: Traditional z | E13: ='Consol Pull'!F13 -> 1670.7777 | G13: =IF(ISERROR(E13/'Consol Pull'!T13-1),"-",IF(ABS(E13/'Consol Pull'!T13-1)>1000%," - ",(E13/'Consol Pull'!T13-1))) -> 0.3654486 | I13: ='FIRM Load Pull'!E13 -> 129.49898 | J13: ='Ship Load Pull'!E13 -> 34.804885 | K13: =I13/'FIRM Load Pull'!Q13-1 -> 1.0199404 | L13: ='FIRM Load Pull'!E13-'FIRM Load Pull'!F13 -> 20.031546 | M13: ='FIRM Load Pull'!E13-'FIRM Load Pull'!G13 -> 55.354417 | N13: ='Consol Pull'!G13 -> 1440.3421 | O13: =I13-N13 -> -1310.8432 | P13: =I13-'Tracks Pull'!E13 -> 51.354676 | Q13: =M13-'Tracks Pull'!G13 -> 49.105904 | R13: =IF(ISERROR(#REF!/'RETAIL Load Pull'!N13-1),"-",IF(ABS(#REF!/'RETAIL Load Pull'!N13-1)>1000%," - ",(#REF!/'RETAIL Load Pull'!N13-1))) -> - | U13: ='RETAIL Load Pull'!E13-'RETAIL Load Pull'!F13 -> 20.747526 | V13: ='RETAIL Load Pull'!E13-'RETAIL Load Pull'!G13 -> 304.69636 | W13: =#REF!-N13 -> #REF! | Y13: =#REF!-'Tracks Pull'!M13 -> #REF! | AA13: =V13-'Tracks Pull'!O13 -> 298.44785 | AC13: ='Stream Pull'!F13 -> 59.948568 | AD13: ='Stream Pull'!G13 -> 1.0072507 | AE13: ='Stream Pull'!H13 -> 58.941317 | AF13: ='Stream Pull'!M13 -> 249.32861 | AG13: =AC13+AF13 -> 309.27718 | AH13: ='Consol Pull'!F13-'Consol Pull'!G13 -> 230.43557 | AI13: =AG13-AH13 -> 78.841612 | AK13: =I13+AG13 -> 438.77616 | AM13: =AK13-E13 -> -1232.0015 | AO13: ='FIRM Load Pull'!#REF! -> #REF! | AP13: =I13+AG13+AO13 -> #REF! | AQ13: =AP13-E13 -> #REF!
A14: 26 | B14: Sum of Geos | C14: Sum of Geos | D14: Sum of Geos | E14: ='Consol Pull'!F14 -> 1670.7777 | G14: =IF(ISERROR(E14/'Consol Pull'!T14-1),"-",IF(ABS(E14/'Consol Pull'!T14-1)>1000%," - ",(E14/'Consol Pull'!T14-1))) -> 0.36179049 | I14: ='FIRM Load Pull'!E14 -> 0 | J14: ='Ship Load Pull'!E14 -> 0 | K14: =IF(ISERROR(I14/'FIRM Load Pull'!Q14-1),"-",IF(ABS(I14/'FIRM Load Pull'!Q14-1)>1000%," - ",(I14/'FIRM Load Pull'!Q14-1))) -> - | L14: ='FIRM Load Pull'!E14-'FIRM Load Pull'!F14 -> 0 | M14: ='FIRM Load Pull'!E14-'FIRM Load Pull'!G14 -> 0 | N14: ='Consol Pull'!G14 -> 1440.3421 | O14: =I14-N14 -> -1440.3421 | P14: =I14-'Tracks Pull'!E14 -> 0 | Q14: =M14-'Tracks Pull'!G14 -> 0 | R14: =IF(ISERROR(#REF!/'RETAIL Load Pull'!N14-1),"-",IF(ABS(#REF!/'RETAIL Load Pull'!N14-1)>1000%," - ",(#REF!/'RETAIL Load Pull'!N14-1))) -> - | U14: ='RETAIL Load Pull'!E14-'RETAIL Load Pull'!F14 -> 0 | V14: ='RETAIL Load Pull'!E14-'RETAIL Load Pull'!G14 -> 0 | W14: =#REF!-N14 -> #REF! | Y14: =#REF!-'Tracks Pull'!M14 -> #REF! | AA14: =V14-'Tracks Pull'!O14 -> 0 | AC14: ='Stream Pull'!F14 -> 0 | AD14: ='Stream Pull'!G14 -> 0 | AE14: ='Stream Pull'!H14 -> 0 | AF14: ='Stream Pull'!M14 -> 0 | AG14: =AC14+AF14 -> 0 | AH14: ='Consol Pull'!F14-'Consol Pull'!G14 -> 230.43557 | AI14: =AG14-AH14 -> -230.43557 | AK14: =I14+AG14 -> 0 | AM14: =AK14-E14 -> -1670.7777 | AO14: ='FIRM Load Pull'!#REF! -> #REF! | AP14: =I14+AG14+AO14 -> #REF! | AQ14: =AP14-E14 -> #REF!
A15: 26 | B15: WW Top | C15: WW Top | D15: WW Top | E15: ='Consol Pull'!F15 -> 0 | G15: =IF(ISERROR(E15/'Consol Pull'!T15-1),"-",IF(ABS(E15/'Consol Pull'!T15-1)>1000%," - ",(E15/'Consol Pull'!T15-1))) -> - | I15: ='FIRM Load Pull'!E15 -> 0 | J15: ='Ship Load Pull'!E15 -> 0 | K15: =IF(ISERROR(I15/'FIRM Load Pull'!Q15-1),"-",IF(ABS(I15/'FIRM Load Pull'!Q15-1)>1000%," - ",(I15/'FIRM Load Pull'!Q15-1))) -> - | L15: ='FIRM Load Pull'!E15-'FIRM Load Pull'!F15 -> 0 | M15: ='FIRM Load Pull'!E15-'FIRM Load Pull'!G15 -> 0 | N15: ='Consol Pull'!G15 -> 0 | O15: =I15-N15 -> 0 | P15: =I15-'Tracks Pull'!E15 -> 0 | Q15: =M15-'Tracks Pull'!G15 -> 0 | R15: =IF(ISERROR(#REF!/'RETAIL Load Pull'!N15-1),"-",IF(ABS(#REF!/'RETAIL Load Pull'!N15-1)>1000%," - ",(#REF!/'RETAIL Load Pull'!N15-1))) -> - | U15: ='RETAIL Load Pull'!E15-'RETAIL Load Pull'!F15 -> 0 | V15: ='RETAIL Load Pull'!E15-'RETAIL Load Pull'!G15 -> 0 | W15: =#REF!-N15 -> #REF! | Y15: =#REF!-'Tracks Pull'!M15 -> #REF! | AA15: =V15-'Tracks Pull'!O15 -> 0 | AC15: ='Stream Pull'!F15 -> 0 | AD15: ='Stream Pull'!G15 -> 0 | AE15: ='Stream Pull'!H15 -> 0 | AF15: ='Stream Pull'!M15 -> 0 | AG15: =AC15+AF15 -> 0 | AH15: ='Consol Pull'!F15-'Consol Pull'!G15 -> 0 | AI15: =AG15-AH15 -> 0 | AK15: =I15+AG15 -> 0 | AM15: =AK15-E15 -> 0 | AO15: ='FIRM Load Pull'!#REF! -> #REF! | AP15: =I15+AG15+AO15 -> #REF! | AQ15: =AP15-E15 -> #REF!
A16: 26 | B16: Americas | C16: Americas | D16: Americas | E16: ='Consol Pull'!F16 -> 917.3554 | G16: =IF(ISERROR(E16/'Consol Pull'!T16-1),"-",IF(ABS(E16/'Consol Pull'!T16-1)>1000%," - ",(E16/'Consol Pull'!T16-1))) -> 0.4612651 | I16: ='FIRM Load Pull'!E16 -> 52.782368 | J16: ='Ship Load Pull'!E16 -> 20.502923 | K16: =IF(ISERROR(I16/'FIRM Load Pull'!Q16-1),"-",IF(ABS(I16/'FIRM Load Pull'!Q16-1)>1000%," - ",(I16/'FIRM Load Pull'!Q16-1))) -> 3.3876191 | L16: ='FIRM Load Pull'!E16-'FIRM Load Pull'!F16 -> 19.733146 | M16: ='FIRM Load Pull'!E16-'FIRM Load Pull'!G16 -> 32.797158 | N16: ='Consol Pull'!G16 -> 804.79775 | O16: =I16-N16 -> -752.01538 | P16: =I16-'Tracks Pull'!E16 -> 20.997429 | Q16: =M16-'Tracks Pull'!G16 -> 34.078587 | R16: =IF(ISERROR(#REF!/'RETAIL Load Pull'!N16-1),"-",IF(ABS(#REF!/'RETAIL Load Pull'!N16-1)>1000%," - ",(#REF!/'RETAIL Load Pull'!N16-1))) -> - | U16: ='RETAIL Load Pull'!E16-'RETAIL Load Pull'!F16 -> 10.268646 | V16: ='RETAIL Load Pull'!E16-'RETAIL Load Pull'!G16 -> 60.996435 | W16: =#REF!-N16 -> #REF! | Y16: =#REF!-'Tracks Pull'!M16 -> #REF! | AA16: =V16-'Tracks Pull'!O16 -> 62.277864 | AC16: ='Stream Pull'!F16 -> 30.57235 | AD16: ='Stream Pull'!G16 -> 0.67842125 | AE16: ='Stream Pull'!H16 -> 29.893929 | AF16: ='Stream Pull'!M16 -> 121.15263 | AG16: =AC16+AF16 -> 151.72498 | AH16: ='Consol Pull'!F16-'Consol Pull'!G16 -> 112.55765 | AI16: =AG16-AH16 -> 39.167323 | AK16: =I16+AG16 -> 204.50734 | AM16: =AK16-E16 -> -712.84806 | AO16: ='FIRM Load Pull'!#REF! -> #REF! | AP16: =I16+AG16+AO16 -> #REF! | AQ16: =AP16-E16 -> #REF!
A17: 26 | B17: 4A | C17: 4A | D17: US Industry | E17: ='Consol Pull'!F17 -> 158.86589 | G17: =IF(ISERROR(E17/'Consol Pull'!T17-1),"-",IF(ABS(E17/'Consol Pull'!T17-1)>1000%," - ",(E17/'Consol Pull'!T17-1))) -> - | I17: ='FIRM Load Pull'!E17 -> 10.148708 | J17: ='Ship Load Pull'!E17 -> 4.8705776 | K17: =IF(ISERROR(I17/'FIRM Load Pull'!Q17-1),"-",IF(ABS(I17/'FIRM Load Pull'!Q17-1)>1000%," - ",(I17/'FIRM Load Pull'!Q17-1))) -> 2.989554 | L17: ='FIRM Load Pull'!E17-'FIRM Load Pull'!F17 -> 4.5009744 | M17: ='FIRM Load Pull'!E17-'FIRM Load Pull'!G17 -> 5.5738317 | N17: ='Consol Pull'!G17 -> 127.91037 | O17: =I17-N17 -> -117.76166 | P17: =I17-'Tracks Pull'!E17 -> 5.0969748 | Q17: =M17-'Tracks Pull'!G17 -> 5.7774953 | R17: =IF(ISERROR(#REF!/'RETAIL Load Pull'!N17-1),"-",IF(ABS(#REF!/'RETAIL Load Pull'!N17-1)>1000%," - ",(#REF!/'RETAIL Load Pull'!N17-1))) -> - | U17: ='RETAIL Load Pull'!E17-'RETAIL Load Pull'!F17 -> 0.00097457 | V17: ='RETAIL Load Pull'!E17-'RETAIL Load Pull'!G17 -> -0.4515681 | W17: =#REF!-N17 -> #REF! | Y17: =#REF!-'Tracks Pull'!M17 -> #REF! | AA17: =V17-'Tracks Pull'!O17 -> -0.24790452 | AC17: ='Stream Pull'!F17 -> 4.8963497 | AD17: ='Stream Pull'!G17 -> 0.26739983 | AE17: ='Stream Pull'!H17 -> 4.6289498 | AF17: ='Stream Pull'!M17 -> 28.079707 | AG17: =AC17+AF17 -> 32.976056 | AH17: ='Consol Pull'!F17-'Consol Pull'!G17 -> 30.955522 | AI17: =AG17-AH17 -> 2.0205345 | AK17: =I17+AG17 -> 43.124764 | AM17: =AK17-E17 -> -115.74112 | AO17: ='FIRM Load Pull'!#REF! -> #REF! | AP17: =I17+AG17+AO17 -> #REF! | AQ17: =AP17-E17 -> #REF!
A18: 26 | B18: 4O | C18: 4O | D18: US Build/Service Partners | E18: ='Consol Pull'!F18 -> 2.6281159 | G18: =IF(ISERROR(E18/'Consol Pull'!T18-1),"-",IF(ABS(E18/'Consol Pull'!T18-1)>1000%," - ",(E18/'Consol Pull'!T18-1))) -> - | I18: ='FIRM Load Pull'!E18 -> 0 | J18: ='Ship Load Pull'!E18 -> 0 | K18: =IF(ISERROR(I18/'FIRM Load Pull'!Q18-1),"-",IF(ABS(I18/'FIRM Load Pull'!Q18-1)>1000%," - ",(I18/'FIRM Load Pull'!Q18-1))) -> -1 | L18: ='FIRM Load Pull'!E18-'FIRM Load Pull'!F18 -> 0 | M18: ='FIRM Load Pull'!E18-'FIRM Load Pull'!G18 -> 0 | N18: ='Consol Pull'!G18 -> 2.4989439 | O18: =I18-N18 -> -2.4989439 | P18: =I18-'Tracks Pull'!E18 -> -0.098694088 | Q18: =M18-'Tracks Pull'!G18 -> 0.0039789102 | R18: =IF(ISERROR(#REF!/'RETAIL Load Pull'!N18-1),"-",IF(ABS(#REF!/'RETAIL Load Pull'!N18-1)>1000%," - ",(#REF!/'RETAIL Load Pull'!N18-1))) -> - | U18: ='RETAIL Load Pull'!E18-'RETAIL Load Pull'!F18 -> 0 | V18: ='RETAIL Load Pull'!E18-'RETAIL Load Pull'!G18 -> 0 | W18: =#REF!-N18 -> #REF! | Y18: =#REF!-'Tracks Pull'!M18 -> #REF! | AA18: =V18-'Tracks Pull'!O18 -> 0.0039789102 | AC18: ='Stream Pull'!F18 -> 0 | AD18: ='Stream Pull'!G18 -> 0 | AE18: ='Stream Pull'!H18 -> 0 | AF18: ='Stream Pull'!M18 -> 0.19032484 | AG18: =AC18+AF18 -> 0.19032484 | AH18: ='Consol Pull'!F18-'Consol Pull'!G18 -> 0.12917202 | AI18: =AG18-AH18 -> 0.06115282 | AK18: =I18+AG18 -> 0.19032484 | AM18: =AK18-E18 -> -2.4377911 | AO18: ='FIRM Load Pull'!#REF! -> #REF! | AP18: =I18+AG18+AO18 -> #REF! | AQ18: =AP18-E18 -> #REF!
A19: 26 | B19: 4J | C19: 4J | D19: US National | E19: ='Consol Pull'!F19 -> 57.255864 | G19: =IF(ISERROR(E19/'Consol Pull'!T19-1),"-",IF(ABS(E19/'Consol Pull'!T19-1)>1000%," - ",(E19/'Consol Pull'!T19-1))) -> - | I19: ='FIRM Load Pull'!E19 -> 3.7106993 | J19: ='Ship Load Pull'!E19 -> 1.7956988 | K19: =IF(ISERROR(I19/'FIRM Load Pull'!Q19-1),"-",IF(ABS(I19/'FIRM Load Pull'!Q19-1)>1000%," - ",(I19/'FIRM Load Pull'!Q19-1))) -> 5.00364 | L19: ='FIRM Load Pull'!E19-'FIRM Load Pull'!F19 -> 0 | M19: ='FIRM Load Pull'!E19-'FIRM Load Pull'!G19 -> 0.0942247 | N19: ='Consol Pull'!G19 -> 38.2857 | O19: =I19-N19 -> -34.575 | P19: =I19-'Tracks Pull'!E19 -> 2.1986316 | Q19: =M19-'Tracks Pull'!G19 -> 0.1551846 | R19: =IF(ISERROR(#REF!/'RETAIL Load Pull'!N19-1),"-",IF(ABS(#REF!/'RETAIL Load Pull'!N19-1)>1000%," - ",(#REF!/'RETAIL Load Pull'!N19-1))) -> - | U19: ='RETAIL Load Pull'!E19-'RETAIL Load Pull'!F19 -> 0.2168 | V19: ='RETAIL Load Pull'!E19-'RETAIL Load Pull'!G19 -> 1.6743247 | W19: =#REF!-N19 -> #REF! | Y19: =#REF!-'Tracks Pull'!M19 -> #REF! | AA19: =V19-'Tracks Pull'!O19 -> 1.7352846 | AC19: ='Stream Pull'!F19 -> 2.0429218 | AD19: ='Stream Pull'!G19 -> 0.072870571 | AE19: ='Stream Pull'!H19 -> 1.9700513 | AF19: ='Stream Pull'!M19 -> 20.742741 | AG19: =AC19+AF19 -> 22.785662 | AH19: ='Consol Pull'!F19-'Consol Pull'!G19 -> 18.970164 | AI19: =AG19-AH19 -> 3.8154985 | AK19: =I19+AG19 -> 26.496362 | AM19: =AK19-E19 -> -30.759502 | AO19: ='FIRM Load Pull'!#REF! -> #REF! | AP19: =I19+AG19+AO19 -> #REF! | AQ19: =AP19-E19 -> #REF!
A20: 26 | B20: 4L | C20: 4L | D20: FSS | E20: ='Consol Pull'!F20 -> 452.05485 | G20: =IF(ISERROR(E20/'Consol Pull'!T20-1),"-",IF(ABS(E20/'Consol Pull'!T20-1)>1000%," - ",(E20/'Consol Pull'!T20-1))) -> - | I20: ='FIRM Load Pull'!E20 -> 21.200062 | J20: ='Ship Load Pull'!E20 -> 6.7396119 | K20: =IF(ISERROR(I20/'FIRM Load Pull'!Q20-1),"-",IF(ABS(I20/'FIRM Load Pull'!Q20-1)>1000%," - ",(I20/'FIRM Load Pull'!Q20-1))) -> - | L20: ='FIRM Load Pull'!E20-'FIRM Load Pull'!F20 -> 15.232171 | M20: ='FIRM Load Pull'!E20-'FIRM Load Pull'!G20 -> 15.862444 | N20: ='Consol Pull'!G20 -> 428.30566 | O20: =I20-N20 -> -407.10559 | P20: =I20-'Tracks Pull'!E20 -> 4.2844219 | Q20: =M20-'Tracks Pull'!G20 -> 16.544408 | R20: =IF(ISERROR(#REF!/'RETAIL Load Pull'!N20-1),"-",IF(ABS(#REF!/'RETAIL Load Pull'!N20-1)>1000%," - ",(#REF!/'RETAIL Load Pull'!N20-1))) -> - | U20: ='RETAIL Load Pull'!E20-'RETAIL Load Pull'!F20 -> 10.050871 | V20: ='RETAIL Load Pull'!E20-'RETAIL Load Pull'!G20 -> 10.82946 | W20: =#REF!-N20 -> #REF! | Y20: =#REF!-'Tracks Pull'!M20 -> #REF! | AA20: =V20-'Tracks Pull'!O20 -> 11.511424 | AC20: ='Stream Pull'!F20 -> 15.467131 | AD20: ='Stream Pull'!G20 -> 0.25233589 | AE20: ='Stream Pull'!H20 -> 15.214795 | AF20: ='Stream Pull'!M20 -> 25.606788 | AG20: =AC20+AF20 -> 41.07392 | AH20: ='Consol Pull'!F20-'Consol Pull'!G20 -> 23.749191 | AI20: =AG20-AH20 -> 17.324729 | AK20: =I20+AG20 -> 62.273982 | AM20: =AK20-E20 -> -389.78087 | AO20: ='FIRM Load Pull'!#REF! -> #REF! | AP20: =I20+AG20+AO20 -> #REF! | AQ20: =AP20-E20 -> #REF!
A21: 26 | B21: 4P | C21: 4P | D21: Public | E21: ='Consol Pull'!F21 -> 73.275013 | G21: =IF(ISERROR(E21/'Consol Pull'!T21-1),"-",IF(ABS(E21/'Consol Pull'!T21-1)>1000%," - ",(E21/'Consol Pull'!T21-1))) -> - | I21: ='FIRM Load Pull'!E21 -> 1.3673398 | J21: ='Ship Load Pull'!E21 -> 1.3673398 | K21: =IF(ISERROR(I21/'FIRM Load Pull'!Q21-1),"-",IF(ABS(I21/'FIRM Load Pull'!Q21-1)>1000%," - ",(I21/'FIRM Load Pull'!Q21-1))) -> - | L21: ='FIRM Load Pull'!E21-'FIRM Load Pull'!F21 -> 0 | M21: ='FIRM Load Pull'!E21-'FIRM Load Pull'!G21 -> 0.03218292 | N21: ='Consol Pull'!G21 -> 62.50173 | O21: =I21-N21 -> -61.13439 | P21: =I21-'Tracks Pull'!E21 -> -1.1011234 | Q21: =M21-'Tracks Pull'!G21 -> 0.13170047 | R21: =IF(ISERROR(#REF!/'RETAIL Load Pull'!N21-1),"-",IF(ABS(#REF!/'RETAIL Load Pull'!N21-1)>1000%," - ",(#REF!/'RETAIL Load Pull'!N21-1))) -> - | U21: ='RETAIL Load Pull'!E21-'RETAIL Load Pull'!F21 -> 0 | V21: ='RETAIL Load Pull'!E21-'RETAIL Load Pull'!G21 -> 30.330252 | W21: =#REF!-N21 -> #REF! | Y21: =#REF!-'Tracks Pull'!M21 -> #REF! | AA21: =V21-'Tracks Pull'!O21 -> 30.429769 | AC21: ='Stream Pull'!F21 -> 0.57109071 | AD21: ='Stream Pull'!G21 -> 0 | AE21: ='Stream Pull'!H21 -> 0.57109071 | AF21: ='Stream Pull'!M21 -> 10.462581 | AG21: =AC21+AF21 -> 11.033672 | AH21: ='Consol Pull'!F21-'Consol Pull'!G21 -> 10.773283 | AI21: =AG21-AH21 -> 0.26038906 | AK21: =I21+AG21 -> 12.401012 | AM21: =AK21-E21 -> -60.874001 | AO21: ='FIRM Load Pull'!#REF! -> #REF! | AP21: =I21+AG21+AO21 -> #REF! | AQ21: =AP21-E21 -> #REF!
A22: 26 | B22: 4X | C22: 4X | D22: Federal | E22: ='Consol Pull'!F22 -> 24.875635 | G22: =IF(ISERROR(E22/'Consol Pull'!T23-1),"-",IF(ABS(E22/'Consol Pull'!T23-1)>1000%," - ",(E22/'Consol Pull'!T23-1))) -> - | I22: ='FIRM Load Pull'!E22 -> -0.03261459 | J22: ='Ship Load Pull'!E22 -> -0.03261459 | K22: =IF(ISERROR(I22/'FIRM Load Pull'!Q22-1),"-",IF(ABS(I22/'FIRM Load Pull'!Q22-1)>1000%," - ",(I22/'FIRM Load Pull'!Q22-1))) -> - | L22: ='FIRM Load Pull'!E22-'FIRM Load Pull'!F22 -> 0 | M22: ='FIRM Load Pull'!E22-'FIRM Load Pull'!G22 -> -0.03261465 | N22: ='Consol Pull'!G22 -> 19.850659 | O22: =I22-N22 -> -19.883274 | P22: =I22-'Tracks Pull'!E22 -> -0.81660287 | Q22: =M22-'Tracks Pull'!G22 -> -0.0010077014 | R22: =IF(ISERROR(#REF!/'RETAIL Load Pull'!N23-1),"-",IF(ABS(#REF!/'RETAIL Load Pull'!N23-1)>1000%," - ",(#REF!/'RETAIL Load Pull'!N23-1))) -> - | U22: ='RETAIL Load Pull'!E23-'RETAIL Load Pull'!F23 -> 0 | V22: ='RETAIL Load Pull'!E23-'RETAIL Load Pull'!G23 -> -0.85850693 | W22: =#REF!-N22 -> #REF! | Y22: =#REF!-'Tracks Pull'!M23 -> #REF! | AA22: =V22-'Tracks Pull'!O23 -> -0.85848892 | AC22: ='Stream Pull'!F22 -> 0.01727083 | AD22: ='Stream Pull'!G22 -> 0 | AE22: ='Stream Pull'!H22 -> 0.01727083 | AF22: ='Stream Pull'!M22 -> 3.3514822 | AG22: =AC22+AF22 -> 3.368753 | AH22: ='Consol Pull'!F23-'Consol Pull'!G23 -> -0.41919114 | AI22: =AG22-AH22 -> 3.7879442 | AK22: =I22+AG22 -> 3.3361384 | AM22: =AK22-E22 -> -21.539496 | AO22: ='FIRM Load Pull'!#REF! -> #REF! | AP22: =I22+AG22+AO22 -> #REF! | AQ22: =AP22-E22 -> #REF!
A23: 26 | B23: 4V | C23: 4V | D23: US Top | E23: ='Consol Pull'!F23 -> -0.40787851 | G23: =IF(ISERROR(E23/'Consol Pull'!T24-1),"-",IF(ABS(E23/'Consol Pull'!T24-1)>1000%," - ",(E23/'Consol Pull'!T24-1))) -> -1.0061454 | I23: ='FIRM Load Pull'!E23 -> -1.9340589 | J23: ='Ship Load Pull'!E23 -> -0.85850693 | K23: =IF(ISERROR(I23/'FIRM Load Pull'!Q23-1),"-",IF(ABS(I23/'FIRM Load Pull'!Q23-1)>1000%," - ",(I23/'FIRM Load Pull'!Q23-1))) -> 0.97576131 | L23: ='FIRM Load Pull'!E23-'FIRM Load Pull'!F23 -> 0 | M23: ='FIRM Load Pull'!E23-'FIRM Load Pull'!G23 -> -0.53400693 | N23: ='Consol Pull'!G23 -> 0.01131263 | O23: =I23-N23 -> -1.9453716 | P23: =I23-'Tracks Pull'!E23 -> -1.9345057 | Q23: =M23-'Tracks Pull'!G23 -> -0.53398892 | R23: =IF(ISERROR(#REF!/'RETAIL Load Pull'!N24-1),"-",IF(ABS(#REF!/'RETAIL Load Pull'!N24-1)>1000%," - ",(#REF!/'RETAIL Load Pull'!N24-1))) -> - | U23: ='RETAIL Load Pull'!E24-'RETAIL Load Pull'!F24 -> 0 | V23: ='RETAIL Load Pull'!E24-'RETAIL Load Pull'!G24 -> 0.00492244 | W23: =#REF!-N23 -> #REF! | Y23: =#REF!-'Tracks Pull'!M24 -> #REF! | AA23: =V23-'Tracks Pull'!O24 -> 0.036467017 | AC23: ='Stream Pull'!F23 -> 0 | AD23: ='Stream Pull'!G23 -> 0 | AE23: ='Stream Pull'!H23 -> 0 | AF23: ='Stream Pull'!M23 -> 5.3615874 | AG23: =AC23+AF23 -> 5.3615874 | AH23: ='Consol Pull'!F24-'Consol Pull'!G24 -> 6.0757375 | AI23: =AG23-AH23 -> -0.71415014 | AK23: =I23+AG23 -> 3.4275285 | AM23: =AK23-E23 -> 3.835407 | AO23: ='FIRM Load Pull'!#REF! -> #REF! | AP23: =I23+AG23+AO23 -> #REF! | AQ23: =AP23-E23 -> #REF!
A24: 26 | B24: Canada | C24: Canada | D24: Canada | E24: ='Consol Pull'!F24 -> 25.887224 | G24: =IF(ISERROR(E24/'Consol Pull'!T25-1),"-",IF(ABS(E24/'Consol Pull'!T25-1)>1000%," - ",(E24/'Consol Pull'!T25-1))) -> -0.5583143 | I24: ='FIRM Load Pull'!E24 -> -0.20970486 | J24: ='Ship Load Pull'!E24 -> 0.00492244 | K24: =IF(ISERROR(I24/'FIRM Load Pull'!Q24-1),"-",IF(ABS(I24/'FIRM Load Pull'!Q24-1)>1000%," - ",(I24/'FIRM Load Pull'!Q24-1))) -> -1.4720435 | L24: ='FIRM Load Pull'!E24-'FIRM Load Pull'!F24 -> 0 | M24: ='FIRM Load Pull'!E24-'FIRM Load Pull'!G24 -> -0.20911286 | N24: ='Consol Pull'!G24 -> 19.811487 | O24: =I24-N24 -> -20.021192 | P24: =I24-'Tracks Pull'!E24 -> -0.99214605 | Q24: =M24-'Tracks Pull'!G24 -> -0.17756828 | R24: =IF(ISERROR(#REF!/'RETAIL Load Pull'!N25-1),"-",IF(ABS(#REF!/'RETAIL Load Pull'!N25-1)>1000%," - ",(#REF!/'RETAIL Load Pull'!N25-1))) -> - | U24: ='RETAIL Load Pull'!E25-'RETAIL Load Pull'!F25 -> 0 | V24: ='RETAIL Load Pull'!E25-'RETAIL Load Pull'!G25 -> 19.500166 | W24: =#REF!-N24 -> #REF! | Y24: =#REF!-'Tracks Pull'!M25 -> #REF! | AA24: =V24-'Tracks Pull'!O25 -> 19.668341 | AC24: ='Stream Pull'!F24 -> 1.466034 | AD24: ='Stream Pull'!G24 -> 0 | AE24: ='Stream Pull'!H24 -> 1.466034 | AF24: ='Stream Pull'!M24 -> 6.1600698 | AG24: =AC24+AF24 -> 7.6261038 | AH24: ='Consol Pull'!F25-'Consol Pull'!G25 -> 17.2988 | AI24: =AG24-AH24 -> -9.6726963 | AK24: =I24+AG24 -> 7.4163989 | AM24: =AK24-E24 -> -18.470825 | AO24: ='FIRM Load Pull'!#REF! -> #REF! | AP24: =I24+AG24+AO24 -> #REF! | AQ24: =AP24-E24 -> #REF!
A25: 26 | B25: LA | C25: LA | D25: LA | E25: ='Consol Pull'!F25 -> 122.92069 | I25: ='FIRM Load Pull'!E25 -> 18.531937 | J25: ='Ship Load Pull'!E25 -> 6.6158936 | K25: =IF(ISERROR(I25/'FIRM Load Pull'!Q25-1),"-",IF(ABS(I25/'FIRM Load Pull'!Q25-1)>1000%," - ",(I25/'FIRM Load Pull'!Q25-1))) -> 3.3419556 | L25: ='FIRM Load Pull'!E25-'FIRM Load Pull'!F25 -> 0 | M25: ='FIRM Load Pull'!E25-'FIRM Load Pull'!G25 -> 12.01021 | N25: ='Consol Pull'!G25 -> 105.62189 | O25: =I25-N25 -> -87.089957 | P25: =I25-'Tracks Pull'!E25 -> 14.360472 | Q25: =M25-'Tracks Pull'!G25 -> 12.178385 | AC25: ='Stream Pull'!F25 -> 6.1115517 | AD25: ='Stream Pull'!G25 -> 0.085814961 | AE25: ='Stream Pull'!H25 -> 6.0257368 | AF25: ='Stream Pull'!M25 -> 21.197345
A26: 26 | B26: EMEA | C26: EMEA | D26: EMEA | E26: ='Consol Pull'!F26 -> 531.4386 | G26: =IF(ISERROR(E26/'Consol Pull'!T26-1),"-",IF(ABS(E26/'Consol Pull'!T26-1)>1000%," - ",(E26/'Consol Pull'!T26-1))) -> 0.41693339 | I26: ='FIRM Load Pull'!E26 -> 51.441421 | J26: ='Ship Load Pull'!E26 -> 4.7004963 | K26: =IF(ISERROR(I26/'FIRM Load Pull'!Q26-1),"-",IF(ABS(I26/'FIRM Load Pull'!Q26-1)>1000%," - ",(I26/'FIRM Load Pull'!Q26-1))) -> 2.9892077 | L26: ='FIRM Load Pull'!E26-'FIRM Load Pull'!F26 -> 0.29840039 | M26: ='FIRM Load Pull'!E26-'FIRM Load Pull'!G26 -> 23.41064 | N26: ='Consol Pull'!G26 -> 457.09575 | O26: =I26-N26 -> -405.65433 | P26: =I26-'Tracks Pull'!E26 -> 24.773257 | Q26: =M26-'Tracks Pull'!G26 -> 17.541383 | R26: =IF(ISERROR(#REF!/'RETAIL Load Pull'!N26-1),"-",IF(ABS(#REF!/'RETAIL Load Pull'!N26-1)>1000%," - ",(#REF!/'RETAIL Load Pull'!N26-1))) -> - | U26: ='RETAIL Load Pull'!E26-'RETAIL Load Pull'!F26 -> 1.2304764 | V26: ='RETAIL Load Pull'!E26-'RETAIL Load Pull'!G26 -> 74.400857 | W26: =#REF!-N26 -> #REF! | Y26: =#REF!-'Tracks Pull'!M26 -> #REF! | AA26: =V26-'Tracks Pull'!O26 -> 68.531599 | AC26: ='Stream Pull'!F26 -> 19.081219 | AD26: ='Stream Pull'!G26 -> -0.05033249 | AE26: ='Stream Pull'!H26 -> 19.131551 | AF26: ='Stream Pull'!M26 -> 85.998684 | AG26: =AC26+AF26 -> 105.0799 | AH26: ='Consol Pull'!F26-'Consol Pull'!G26 -> 74.342854 | AI26: =AG26-AH26 -> 30.737049 | AK26: =I26+AG26 -> 156.52132 | AM26: =AK26-E26 -> -374.91728 | AO26: ='FIRM Load Pull'!#REF! -> #REF! | AP26: =I26+AG26+AO26 -> #REF! | AQ26: =AP26-E26 -> #REF!
A27: 26 | B27: Dach | C27: Dach | D27: Dach | E27: ='Consol Pull'!F27 -> 107.28944 | G27: =IF(ISERROR(E27/'Consol Pull'!T27-1),"-",IF(ABS(E27/'Consol Pull'!T27-1)>1000%," - ",(E27/'Consol Pull'!T27-1))) -> -0.27981633 | I27: ='FIRM Load Pull'!E27 -> 4.6295061 | J27: ='Ship Load Pull'!E27 -> 0.46999839 | K27: =IF(ISERROR(I27/'FIRM Load Pull'!Q27-1),"-",IF(ABS(I27/'FIRM Load Pull'!Q27-1)>1000%," - ",(I27/'FIRM Load Pull'!Q27-1))) -> - | L27: ='FIRM Load Pull'!E27-'FIRM Load Pull'!F27 -> 9.9999999e-09 | M27: ='FIRM Load Pull'!E27-'FIRM Load Pull'!G27 -> 4.4385867 | N27: ='Consol Pull'!G27 -> 91.216898 | O27: =I27-N27 -> -86.587391 | P27: =I27-'Tracks Pull'!E27 -> -0.69232671 | Q27: =M27-'Tracks Pull'!G27 -> 3.2673322 | R27: =IF(ISERROR(#REF!/'RETAIL Load Pull'!N27-1),"-",IF(ABS(#REF!/'RETAIL Load Pull'!N27-1)>1000%," - ",(#REF!/'RETAIL Load Pull'!N27-1))) -> - | U27: ='RETAIL Load Pull'!E27-'RETAIL Load Pull'!F27 -> 0.93207601 | V27: ='RETAIL Load Pull'!E27-'RETAIL Load Pull'!G27 -> 14.736309 | W27: =#REF!-N27 -> #REF! | Y27: =#REF!-'Tracks Pull'!M27 -> #REF! | AA27: =V27-'Tracks Pull'!O27 -> 13.565054 | AC27: ='Stream Pull'!F27 -> 15.687454 | AD27: ='Stream Pull'!G27 -> 0 | AE27: ='Stream Pull'!H27 -> 15.687454 | AF27: ='Stream Pull'!M27 -> 18.943944 | AG27: =AC27+AF27 -> 34.631398 | AH27: ='Consol Pull'!F27-'Consol Pull'!G27 -> 16.072543 | AI27: =AG27-AH27 -> 18.558855 | AK27: =I27+AG27 -> 39.260904 | AM27: =AK27-E27 -> -68.028537 | AO27: ='FIRM Load Pull'!#REF! -> #REF! | AP27: =I27+AG27+AO27 -> #REF! | AQ27: =AP27-E27 -> #REF!
A28: 26 | B28: France | C28: France | D28: France | E28: ='Consol Pull'!F28 -> 106.15289 | G28: =IF(ISERROR(E28/'Consol Pull'!T28-1),"-",IF(ABS(E28/'Consol Pull'!T28-1)>1000%," - ",(E28/'Consol Pull'!T28-1))) -> 1.5244429 | I28: ='FIRM Load Pull'!E28 -> 0.34107437 | J28: ='Ship Load Pull'!E28 -> 0.34176505 | K28: =IF(ISERROR(I28/'FIRM Load Pull'!Q28-1),"-",IF(ABS(I28/'FIRM Load Pull'!Q28-1)>1000%," - ",(I28/'FIRM Load Pull'!Q28-1))) -> 3.6225071 | L28: ='FIRM Load Pull'!E28-'FIRM Load Pull'!F28 -> 1e-08 | M28: ='FIRM Load Pull'!E28-'FIRM Load Pull'!G28 -> -0.04052806 | N28: ='Consol Pull'!G28 -> 93.798678 | O28: =I28-N28 -> -93.457604 | P28: =I28-'Tracks Pull'!E28 -> -5.1313863 | Q28: =M28-'Tracks Pull'!G28 -> -1.2449335 | R28: =IF(ISERROR(#REF!/'RETAIL Load Pull'!N28-1),"-",IF(ABS(#REF!/'RETAIL Load Pull'!N28-1)>1000%," - ",(#REF!/'RETAIL Load Pull'!N28-1))) -> - | U28: ='RETAIL Load Pull'!E28-'RETAIL Load Pull'!F28 -> 9.9999795e-09 | V28: ='RETAIL Load Pull'!E28-'RETAIL Load Pull'!G28 -> 4.9330999 | W28: =#REF!-N28 -> #REF! | Y28: =#REF!-'Tracks Pull'!M28 -> #REF! | AA28: =V28-'Tracks Pull'!O28 -> 3.7286945 | AC28: ='Stream Pull'!F28 -> 0.056384899 | AD28: ='Stream Pull'!G28 -> 0 | AE28: ='Stream Pull'!H28 -> 0.056384899 | AF28: ='Stream Pull'!M28 -> 13.351457 | AG28: =AC28+AF28 -> 13.407842 | AH28: ='Consol Pull'!F28-'Consol Pull'!G28 -> 12.35421 | AI28: =AG28-AH28 -> 1.0536314 | AK28: =I28+AG28 -> 13.748916 | AM28: =AK28-E28 -> -92.403973 | AO28: ='FIRM Load Pull'!#REF! -> #REF! | AP28: =I28+AG28+AO28 -> #REF! | AQ28: =AP28-E28 -> #REF!
A29: 26 | B29: UKI | C29: UKI | D29: UKI | E29: ='Consol Pull'!F29 -> 78.034503 | G29: =IF(ISERROR(E29/'Consol Pull'!T29-1),"-",IF(ABS(E29/'Consol Pull'!T29-1)>1000%," - ",(E29/'Consol Pull'!T29-1))) -> 0.7846407 | I29: ='FIRM Load Pull'!E29 -> -0.35621768 | J29: ='Ship Load Pull'!E29 -> 0.16948955 | K29: =IF(ISERROR(I29/'FIRM Load Pull'!Q29-1),"-",IF(ABS(I29/'FIRM Load Pull'!Q29-1)>1000%," - ",(I29/'FIRM Load Pull'!Q29-1))) -> -1.4344081 | L29: ='FIRM Load Pull'!E29-'FIRM Load Pull'!F29 -> 0 | M29: ='FIRM Load Pull'!E29-'FIRM Load Pull'!G29 -> -0.33097013 | N29: ='Consol Pull'!G29 -> 68.177592 | O29: =I29-N29 -> -68.53381 | P29: =I29-'Tracks Pull'!E29 -> -4.3338771 | Q29: =M29-'Tracks Pull'!G29 -> -1.2063925 | R29: =IF(ISERROR(#REF!/'RETAIL Load Pull'!N29-1),"-",IF(ABS(#REF!/'RETAIL Load Pull'!N29-1)>1000%," - ",(#REF!/'RETAIL Load Pull'!N29-1))) -> - | U29: ='RETAIL Load Pull'!E29-'RETAIL Load Pull'!F29 -> 0 | V29: ='RETAIL Load Pull'!E29-'RETAIL Load Pull'!G29 -> 13.177508 | W29: =#REF!-N29 -> #REF! | Y29: =#REF!-'Tracks Pull'!M29 -> #REF! | AA29: =V29-'Tracks Pull'!O29 -> 12.302086 | AC29: ='Stream Pull'!F29 -> 0.35117192 | AD29: ='Stream Pull'!G29 -> 0 | AE29: ='Stream Pull'!H29 -> 0.35117192 | AF29: ='Stream Pull'!M29 -> 10.480832 | AG29: =AC29+AF29 -> 10.832004 | AH29: ='Consol Pull'!F29-'Consol Pull'!G29 -> 9.8569109 | AI29: =AG29-AH29 -> 0.97509322 | AK29: =I29+AG29 -> 10.475786 | AM29: =AK29-E29 -> -67.558717 | AO29: ='FIRM Load Pull'!#REF! -> #REF! | AP29: =I29+AG29+AO29 -> #REF! | AQ29: =AP29-E29 -> #REF!
A30: 26 | B30: Italy | C30: Italy | D30: Italy | E30: ='Consol Pull'!F30 -> 67.267898 | G30: =IF(ISERROR(E30/'Consol Pull'!T30-1),"-",IF(ABS(E30/'Consol Pull'!T30-1)>1000%," - ",(E30/'Consol Pull'!T30-1))) -> 1.4023389 | I30: ='FIRM Load Pull'!E30 -> 29.203711 | J30: ='Ship Load Pull'!E30 -> 0 | K30: =IF(ISERROR(I30/'FIRM Load Pull'!Q30-1),"-",IF(ABS(I30/'FIRM Load Pull'!Q30-1)>1000%," - ",(I30/'FIRM Load Pull'!Q30-1))) -> - | L30: ='FIRM Load Pull'!E30-'FIRM Load Pull'!F30 -> 0 | M30: ='FIRM Load Pull'!E30-'FIRM Load Pull'!G30 -> 11.45445 | N30: ='Consol Pull'!G30 -> 60.962307 | O30: =I30-N30 -> -31.758596 | P30: =I30-'Tracks Pull'!E30 -> 25.64701 | Q30: =M30-'Tracks Pull'!G30 -> 10.671675 | R30: =IF(ISERROR(#REF!/'RETAIL Load Pull'!N30-1),"-",IF(ABS(#REF!/'RETAIL Load Pull'!N30-1)>1000%," - ",(#REF!/'RETAIL Load Pull'!N30-1))) -> - | U30: ='RETAIL Load Pull'!E30-'RETAIL Load Pull'!F30 -> 0 | V30: ='RETAIL Load Pull'!E30-'RETAIL Load Pull'!G30 -> 48.756844 | W30: =#REF!-N30 -> #REF! | Y30: =#REF!-'Tracks Pull'!M30 -> #REF! | AA30: =V30-'Tracks Pull'!O30 -> 47.974069 | AC30: ='Stream Pull'!F30 -> 0.099696648 | AD30: ='Stream Pull'!G30 -> 0.00648472 | AE30: ='Stream Pull'!H30 -> 0.093211928 | AF30: ='Stream Pull'!M30 -> 8.0489838 | AG30: =AC30+AF30 -> 8.1486804 | AH30: ='Consol Pull'!F30-'Consol Pull'!G30 -> 6.3055908 | AI30: =AG30-AH30 -> 1.8430896 | AK30: =I30+AG30 -> 37.352392 | AM30: =AK30-E30 -> -29.915506 | AO30: ='FIRM Load Pull'!#REF! -> #REF! | AP30: =I30+AG30+AO30 -> #REF! | AQ30: =AP30-E30 -> #REF!
A31: 26 | B31: SPIGI | C31: SPIGI | D31: SPIGI | E31: ='Consol Pull'!F31 -> 34.302743 | G31: =IF(ISERROR(E31/'Consol Pull'!T31-1),"-",IF(ABS(E31/'Consol Pull'!T31-1)>1000%," - ",(E31/'Consol Pull'!T31-1))) -> 0.045634975 | I31: ='FIRM Load Pull'!E31 -> 1.3247823 | J31: ='Ship Load Pull'!E31 -> 1.3590831 | K31: =IF(ISERROR(I31/'FIRM Load Pull'!Q31-1),"-",IF(ABS(I31/'FIRM Load Pull'!Q31-1)>1000%," - ",(I31/'FIRM Load Pull'!Q31-1))) -> 0.25476502 | L31: ='FIRM Load Pull'!E31-'FIRM Load Pull'!F31 -> 0.02164725 | M31: ='FIRM Load Pull'!E31-'FIRM Load Pull'!G31 -> 0.04899748 | N31: ='Consol Pull'!G31 -> 25.579059 | O31: =I31-N31 -> -24.254277 | P31: =I31-'Tracks Pull'!E31 -> -0.16756704 | Q31: =M31-'Tracks Pull'!G31 -> -0.27944592 | R31: =IF(ISERROR(#REF!/'RETAIL Load Pull'!N31-1),"-",IF(ABS(#REF!/'RETAIL Load Pull'!N31-1)>1000%," - ",(#REF!/'RETAIL Load Pull'!N31-1))) -> - | U31: ='RETAIL Load Pull'!E31-'RETAIL Load Pull'!F31 -> 0.02164725 | V31: ='RETAIL Load Pull'!E31-'RETAIL Load Pull'!G31 -> 0.0043246 | W31: =#REF!-N31 -> #REF! | Y31: =#REF!-'Tracks Pull'!M31 -> #REF! | AA31: =V31-'Tracks Pull'!O31 -> -0.3241188 | AC31: ='Stream Pull'!F31 -> 0.17716702 | AD31: ='Stream Pull'!G31 -> 0 | AE31: ='Stream Pull'!H31 -> 0.17716702 | AF31: ='Stream Pull'!M31 -> 9.5717392 | AG31: =AC31+AF31 -> 9.7489063 | AH31: ='Consol Pull'!F31-'Consol Pull'!G31 -> 8.723684 | AI31: =AG31-AH31 -> 1.0252222 | AK31: =I31+AG31 -> 11.073689 | AM31: =AK31-E31 -> -23.229055 | AO31: ='FIRM Load Pull'!#REF! -> #REF! | AP31: =I31+AG31+AO31 -> #REF! | AQ31: =AP31-E31 -> #REF!
A32: 26 | B32: NCEE | C32: NCEE | D32: NCEE | E32: ='Consol Pull'!F32 -> 64.205525 | G32: =IF(ISERROR(E32/'Consol Pull'!T32-1),"-",IF(ABS(E32/'Consol Pull'!T32-1)>1000%," - ",(E32/'Consol Pull'!T32-1))) -> 0.33739206 | I32: ='FIRM Load Pull'!E32 -> 1.107257 | J32: ='Ship Load Pull'!E32 -> 1.1920084 | K32: =IF(ISERROR(I32/'FIRM Load Pull'!Q32-1),"-",IF(ABS(I32/'FIRM Load Pull'!Q32-1)>1000%," - ",(I32/'FIRM Load Pull'!Q32-1))) -> -0.87771942 | L32: ='FIRM Load Pull'!E32-'FIRM Load Pull'!F32 -> 0.27675312 | M32: ='FIRM Load Pull'!E32-'FIRM Load Pull'!G32 -> 0.55537279 | N32: ='Consol Pull'!G32 -> 49.114134 | O32: =I32-N32 -> -48.006877 | P32: =I32-'Tracks Pull'!E32 -> -1.7581903 | Q32: =M32-'Tracks Pull'!G32 -> -0.075268596 | R32: =IF(ISERROR(#REF!/'RETAIL Load Pull'!N32-1),"-",IF(ABS(#REF!/'RETAIL Load Pull'!N32-1)>1000%," - ",(#REF!/'RETAIL Load Pull'!N32-1))) -> - | U32: ='RETAIL Load Pull'!E32-'RETAIL Load Pull'!F32 -> 0.27675312 | V32: ='RETAIL Load Pull'!E32-'RETAIL Load Pull'!G32 -> 0.43670282 | W32: =#REF!-N32 -> #REF! | Y32: =#REF!-'Tracks Pull'!M32 -> #REF! | AA32: =V32-'Tracks Pull'!O32 -> -0.19393857 | AC32: ='Stream Pull'!F32 -> 1.7842683 | AD32: ='Stream Pull'!G32 -> 0.00018623 | AE32: ='Stream Pull'!H32 -> 1.7840821 | AF32: ='Stream Pull'!M32 -> 17.413852 | AG32: =AC32+AF32 -> 19.198121 | AH32: ='Consol Pull'!F32-'Consol Pull'!G32 -> 15.091391 | AI32: =AG32-AH32 -> 4.10673 | AK32: =I32+AG32 -> 20.305378 | AM32: =AK32-E32 -> -43.900147 | AO32: ='FIRM Load Pull'!#REF! -> #REF! | AP32: =I32+AG32+AO32 -> #REF! | AQ32: =AP32-E32 -> #REF!
A33: 26 | B33: MEA | C33: MEA | D33: MEA | E33: ='Consol Pull'!F33 -> 74.185651 | G33: =IF(ISERROR(E33/'Consol Pull'!T33-1),"-",IF(ABS(E33/'Consol Pull'!T33-1)>1000%," - ",(E33/'Consol Pull'!T33-1))) -> 1.4833315 | I33: ='FIRM Load Pull'!E33 -> 15.191307 | J33: ='Ship Load Pull'!E33 -> 1.1681518 | K33: =IF(ISERROR(I33/'FIRM Load Pull'!Q33-1),"-",IF(ABS(I33/'FIRM Load Pull'!Q33-1)>1000%," - ",(I33/'FIRM Load Pull'!Q33-1))) -> 7.1216265 | L33: ='FIRM Load Pull'!E33-'FIRM Load Pull'!F33 -> 0 | M33: ='FIRM Load Pull'!E33-'FIRM Load Pull'!G33 -> 7.2847312 | N33: ='Consol Pull'!G33 -> 68.247081 | O33: =I33-N33 -> -53.055774 | P33: =I33-'Tracks Pull'!E33 -> 11.209594 | Q33: =M33-'Tracks Pull'!G33 -> 6.4084166 | R33: =IF(ISERROR(#REF!/'RETAIL Load Pull'!N33-1),"-",IF(ABS(#REF!/'RETAIL Load Pull'!N33-1)>1000%," - ",(#REF!/'RETAIL Load Pull'!N33-1))) -> - | U33: ='RETAIL Load Pull'!E33-'RETAIL Load Pull'!F33 -> 0 | V33: ='RETAIL Load Pull'!E33-'RETAIL Load Pull'!G33 -> -7.6439315 | W33: =#REF!-N33 -> #REF! | Y33: =#REF!-'Tracks Pull'!M33 -> #REF! | AA33: =V33-'Tracks Pull'!O33 -> -8.5202462 | AC33: ='Stream Pull'!F33 -> 0.92507586 | AD33: ='Stream Pull'!G33 -> -0.05700344 | AE33: ='Stream Pull'!H33 -> 0.9820793 | AF33: ='Stream Pull'!M33 -> 7.3978763 | AG33: =AC33+AF33 -> 8.3229522 | AH33: ='Consol Pull'!F33-'Consol Pull'!G33 -> 5.9385698 | AI33: =AG33-AH33 -> 2.3843823 | AK33: =I33+AG33 -> 23.514259 | AM33: =AK33-E33 -> -50.671392 | AO33: ='FIRM Load Pull'!#REF! -> #REF! | AP33: =I33+AG33+AO33 -> #REF! | AQ33: =AP33-E33 -> #REF!
A34: 26 | B34: EMEA Top | C34: EMEA Top | D34: EMEA Top | E34: ='Consol Pull'!F34 -> 0 | I34: ='FIRM Load Pull'!E34 -> 0 | J34: ='Ship Load Pull'!E34 -> 0 | K34: =IF(ISERROR(I34/'FIRM Load Pull'!Q34-1),"-",IF(ABS(I34/'FIRM Load Pull'!Q34-1)>1000%," - ",(I34/'FIRM Load Pull'!Q34-1))) -> - | L34: ='FIRM Load Pull'!E34-'FIRM Load Pull'!F34 -> 0 | M34: ='FIRM Load Pull'!E34-'FIRM Load Pull'!G34 -> 0 | N34: ='Consol Pull'!G34 -> 0 | O34: =I34-N34 -> 0 | P34: =I34-'Tracks Pull'!E34 -> 0 | Q34: =M34-'Tracks Pull'!G34 -> 0 | AC34: ='Stream Pull'!F34 -> 0 | AD34: ='Stream Pull'!G34 -> 0 | AE34: ='Stream Pull'!H34 -> 0 | AF34: ='Stream Pull'!M34 -> 0.79
A35: 26 | B35: Japan | C35: Japan | D35: Japan | E35: ='Consol Pull'!F35 -> 109.75344 | G35: =IF(ISERROR(E35/'Consol Pull'!T35-1),"-",IF(ABS(E35/'Consol Pull'!T35-1)>1000%," - ",(E35/'Consol Pull'!T35-1))) -> 0.048849215 | I35: ='FIRM Load Pull'!E35 -> 22.302881 | J35: ='Ship Load Pull'!E35 -> 6.4719128 | K35: =IF(ISERROR(I35/'FIRM Load Pull'!Q35-1),"-",IF(ABS(I35/'FIRM Load Pull'!Q35-1)>1000%," - ",(I35/'FIRM Load Pull'!Q35-1))) -> -0.35455551 | L35: ='FIRM Load Pull'!E35-'FIRM Load Pull'!F35 -> 0 | M35: ='FIRM Load Pull'!E35-'FIRM Load Pull'!G35 -> -2.7e-07 | N35: ='Consol Pull'!G35 -> 78.851257 | O35: =I35-N35 -> -56.548376 | P35: =I35-'Tracks Pull'!E35 -> 10.120684 | Q35: =M35-'Tracks Pull'!G35 -> -1.2436605 | R35: =IF(ISERROR(#REF!/'RETAIL Load Pull'!N35-1),"-",IF(ABS(#REF!/'RETAIL Load Pull'!N35-1)>1000%," - ",(#REF!/'RETAIL Load Pull'!N35-1))) -> - | U35: ='RETAIL Load Pull'!E35-'RETAIL Load Pull'!F35 -> 9.3762 | V35: ='RETAIL Load Pull'!E35-'RETAIL Load Pull'!G35 -> 10.4622 | W35: =#REF!-N35 -> #REF! | Y35: =#REF!-'Tracks Pull'!M35 -> #REF! | AA35: =V35-'Tracks Pull'!O35 -> 9.2185395 | AC35: ='Stream Pull'!F35 -> 4.6391715 | AD35: ='Stream Pull'!G35 -> 0.31194496 | AE35: ='Stream Pull'!H35 -> 4.3272266 | AF35: ='Stream Pull'!M35 -> 27.671 | AG35: =AC35+AF35 -> 32.310172 | AH35: ='Consol Pull'!F35-'Consol Pull'!G35 -> 30.902184 | AI35: =AG35-AH35 -> 1.4079877 | AK35: =I35+AG35 -> 54.613052 | AM35: =AK35-E35 -> -55.140388 | AO35: ='FIRM Load Pull'!#REF! -> #REF! | AP35: =I35+AG35+AO35 -> #REF! | AQ35: =AP35-E35 -> #REF!
A36: 26 | B36: APAC | C36: APAC | D36: APAC | E36: ='Consol Pull'!F36 -> 112.23025 | G36: =IF(ISERROR(E36/'Consol Pull'!T36-1),"-",IF(ABS(E36/'Consol Pull'!T36-1)>1000%," - ",(E36/'Consol Pull'!T36-1))) -> -0.026835602 | I36: ='FIRM Load Pull'!E36 -> 2.9723074 | J36: ='Ship Load Pull'!E36 -> 3.1295536 | K36: =IF(ISERROR(I36/'FIRM Load Pull'!Q36-1),"-",IF(ABS(I36/'FIRM Load Pull'!Q36-1)>1000%," - ",(I36/'FIRM Load Pull'!Q36-1))) -> -0.35817268 | L36: ='FIRM Load Pull'!E36-'FIRM Load Pull'!F36 -> 0 | M36: ='FIRM Load Pull'!E36-'FIRM Load Pull'!G36 -> -0.85338134 | N36: ='Consol Pull'!G36 -> 99.597372 | O36: =I36-N36 -> -96.625064 | P36: =I36-'Tracks Pull'!E36 -> -4.536694 | Q36: =M36-'Tracks Pull'!G36 -> -1.2704056 | R36: =IF(ISERROR(#REF!/'RETAIL Load Pull'!N36-1),"-",IF(ABS(#REF!/'RETAIL Load Pull'!N36-1)>1000%," - ",(#REF!/'RETAIL Load Pull'!N36-1))) -> - | U36: ='RETAIL Load Pull'!E36-'RETAIL Load Pull'!F36 -> -0.12779642 | V36: ='RETAIL Load Pull'!E36-'RETAIL Load Pull'!G36 -> 158.83687 | W36: =#REF!-N36 -> #REF! | Y36: =#REF!-'Tracks Pull'!M36 -> #REF! | AA36: =V36-'Tracks Pull'!O36 -> 158.41985 | AC36: ='Stream Pull'!F36 -> 5.6558276 | AD36: ='Stream Pull'!G36 -> 0.067217 | AE36: ='Stream Pull'!H36 -> 5.5886106 | AF36: ='Stream Pull'!M36 -> 14.506302 | AG36: =AC36+AF36 -> 20.16213 | AH36: ='Consol Pull'!F36-'Consol Pull'!G36 -> 12.632878 | AI36: =AG36-AH36 -> 7.5292524 | AK36: =I36+AG36 -> 23.134438 | AM36: =AK36-E36 -> -89.095812 | AO36: ='FIRM Load Pull'!#REF! -> #REF! | AP36: =I36+AG36+AO36 -> #REF! | AQ36: =AP36-E36 -> #REF!
A37: 26 | B37: ASE | C37: Asean | D37: Asean | E37: ='Consol Pull'!F37 -> 39.424849 | I37: ='FIRM Load Pull'!E37 -> -0.06128845 | J37: ='Ship Load Pull'!E37 -> 0.01517575 | K37: =IF(ISERROR(I37/'FIRM Load Pull'!Q37-1),"-",IF(ABS(I37/'FIRM Load Pull'!Q37-1)>1000%," - ",(I37/'FIRM Load Pull'!Q37-1))) -> -1.0201572 | L37: ='FIRM Load Pull'!E37-'FIRM Load Pull'!F37 -> 0 | M37: ='FIRM Load Pull'!E37-'FIRM Load Pull'!G37 -> -0.06128851 | N37: ='Consol Pull'!G37 -> 35.695532 | O37: =I37-N37 -> -35.756821 | P37: =I37-'Tracks Pull'!E37 -> -2.7525021 | Q37: =M37-'Tracks Pull'!G37 -> -0.21074931 | AC37: ='Stream Pull'!F37 -> 0.42152158 | AD37: ='Stream Pull'!G37 -> 0.00453933 | AE37: ='Stream Pull'!H37 -> 0.41698225 | AF37: ='Stream Pull'!M37 -> 4.3903275
A38: 26 | B38: AZK | C38: Australia/NZ | D38: Australia/NZ | E38: ='Consol Pull'!F38 -> 35.712806 | I38: ='FIRM Load Pull'!E38 -> 0.06069938 | J38: ='Ship Load Pull'!E38 -> 0.0906233 | K38: =IF(ISERROR(I38/'FIRM Load Pull'!Q38-1),"-",IF(ABS(I38/'FIRM Load Pull'!Q38-1)>1000%," - ",(I38/'FIRM Load Pull'!Q38-1))) -> -0.93997033 | L38: ='FIRM Load Pull'!E38-'FIRM Load Pull'!F38 -> 0 | M38: ='FIRM Load Pull'!E38-'FIRM Load Pull'!G38 -> -0.02997472 | N38: ='Consol Pull'!G38 -> 31.279433 | O38: =I38-N38 -> -31.218733 | P38: =I38-'Tracks Pull'!E38 -> -0.13534929 | Q38: =M38-'Tracks Pull'!G38 -> -0.040862593 | AC38: ='Stream Pull'!F38 -> 3.6338327 | AD38: ='Stream Pull'!G38 -> 0 | AE38: ='Stream Pull'!H38 -> 3.6338327 | AF38: ='Stream Pull'!M38 -> 3.8542591
A39: 26 | B39: KOR | C39: Korea | D39: Korea | E39: ='Consol Pull'!F39 -> 2.7695171 | G39: =IF(ISERROR(E39/'Consol Pull'!T37-1),"-",IF(ABS(E39/'Consol Pull'!T37-1)>1000%," - ",(E39/'Consol Pull'!T37-1))) -> -0.84104031 | I39: ='FIRM Load Pull'!E39 -> 0 | J39: ='Ship Load Pull'!E39 -> 0 | K39: =IF(ISERROR(I39/'FIRM Load Pull'!Q39-1),"-",IF(ABS(I39/'FIRM Load Pull'!Q39-1)>1000%," - ",(I39/'FIRM Load Pull'!Q39-1))) -> - | L39: ='FIRM Load Pull'!E39-'FIRM Load Pull'!F39 -> 0 | M39: ='FIRM Load Pull'!E39-'FIRM Load Pull'!G39 -> 0 | N39: ='Consol Pull'!G39 -> 2.6003368 | O39: =I39-N39 -> -2.6003368 | P39: =I39-'Tracks Pull'!E39 -> -2.3582681 | Q39: =M39-'Tracks Pull'!G39 -> -0.13097014 | R39: =IF(ISERROR(#REF!/'RETAIL Load Pull'!N37-1),"-",IF(ABS(#REF!/'RETAIL Load Pull'!N37-1)>1000%," - ",(#REF!/'RETAIL Load Pull'!N37-1))) -> - | U39: ='RETAIL Load Pull'!E37-'RETAIL Load Pull'!F37 -> 3.58e-06 | V39: ='RETAIL Load Pull'!E37-'RETAIL Load Pull'!G37 -> 0.01517927 | W39: =#REF!-N39 -> #REF! | Y39: =#REF!-'Tracks Pull'!#REF! -> #REF! | AA39: =V39-'Tracks Pull'!#REF! -> #REF! | AC39: ='Stream Pull'!F39 -> 0 | AD39: ='Stream Pull'!G39 -> 0 | AE39: ='Stream Pull'!H39 -> 0 | AF39: ='Stream Pull'!M39 -> 0.29 | AG39: =AC39+AF39 -> 0.29 | AH39: ='Consol Pull'!F37-'Consol Pull'!G37 -> 3.7293166 | AI39: =AG39-AH39 -> -3.4393166 | AK39: =I39+AG39 -> 0.29 | AM39: =AK39-E39 -> -2.4795171 | AO39: ='FIRM Load Pull'!#REF! -> #REF! | AP39: =I39+AG39+AO39 -> #REF! | AQ39: =AP39-E39 -> #REF!
A40: 26 | B40: ISA | C40: ISA | D40: ISA | E40: ='Consol Pull'!F40 -> 11.019942 | G40: =IF(ISERROR(E40/'Consol Pull'!T40-1),"-",IF(ABS(E40/'Consol Pull'!T40-1)>1000%," - ",(E40/'Consol Pull'!T40-1))) -> 0.66885638 | I40: ='FIRM Load Pull'!E40 -> 0.83044725 | J40: ='Ship Load Pull'!E40 -> 0.8544059 | K40: =IF(ISERROR(I40/'FIRM Load Pull'!Q40-1),"-",IF(ABS(I40/'FIRM Load Pull'!Q40-1)>1000%," - ",(I40/'FIRM Load Pull'!Q40-1))) -> - | L40: ='FIRM Load Pull'!E40-'FIRM Load Pull'!F40 -> 0 | M40: ='FIRM Load Pull'!E40-'FIRM Load Pull'!G40 -> -0.03421546 | N40: ='Consol Pull'!G40 -> 9.9285586 | O40: =I40-N40 -> -9.0981113 | P40: =I40-'Tracks Pull'!E40 -> 0.081897769 | Q40: =M40-'Tracks Pull'!G40 -> -0.075787337 | R40: =IF(ISERROR(#REF!/'RETAIL Load Pull'!N40-1),"-",IF(ABS(#REF!/'RETAIL Load Pull'!N40-1)>1000%," - ",(#REF!/'RETAIL Load Pull'!N40-1))) -> - | U40: ='RETAIL Load Pull'!E40-'RETAIL Load Pull'!F40 -> 0 | V40: ='RETAIL Load Pull'!E40-'RETAIL Load Pull'!G40 -> 159.65054 | W40: =#REF!-N40 -> #REF! | Y40: =#REF!-'Tracks Pull'!M40 -> #REF! | AA40: =V40-'Tracks Pull'!O40 -> 159.60897 | AC40: ='Stream Pull'!F40 -> 0.067319353 | AD40: ='Stream Pull'!G40 -> 0.06267767 | AE40: ='Stream Pull'!H40 -> 0.0046416833 | AF40: ='Stream Pull'!M40 -> 0.88036124 | AG40: =AC40+AF40 -> 0.94768059 | AH40: ='Consol Pull'!F40-'Consol Pull'!G40 -> 1.0913834 | AI40: =AG40-AH40 -> -0.14370277 | AK40: =I40+AG40 -> 1.7781278 | AM40: =AK40-E40 -> -9.2418141 | AO40: ='FIRM Load Pull'!#REF! -> #REF! | AP40: =I40+AG40+AO40 -> #REF! | AQ40: =AP40-E40 -> #REF!
A41: 26 | B41: China | C41: China | D41: China | E41: ='Consol Pull'!F41 -> 23.303135 | G41: =IF(ISERROR(E41/'Consol Pull'!T41-1),"-",IF(ABS(E41/'Consol Pull'!T41-1)>1000%," - ",(E41/'Consol Pull'!T41-1))) -> -0.22464264 | I41: ='FIRM Load Pull'!E41 -> 2.1424493 | J41: ='Ship Load Pull'!E41 -> 2.1693486 | K41: =IF(ISERROR(I41/'FIRM Load Pull'!Q41-1),"-",IF(ABS(I41/'FIRM Load Pull'!Q41-1)>1000%," - ",(I41/'FIRM Load Pull'!Q41-1))) -> 2.6981935 | L41: ='FIRM Load Pull'!E41-'FIRM Load Pull'!F41 -> 0 | M41: ='FIRM Load Pull'!E41-'FIRM Load Pull'!G41 -> -0.72790265 | N41: ='Consol Pull'!G41 -> 20.093511 | O41: =I41-N41 -> -17.951062 | P41: =I41-'Tracks Pull'!E41 -> 0.62752769 | Q41: =M41-'Tracks Pull'!G41 -> -0.81203621 | R41: =IF(ISERROR(#REF!/'RETAIL Load Pull'!N41-1),"-",IF(ABS(#REF!/'RETAIL Load Pull'!N41-1)>1000%," - ",(#REF!/'RETAIL Load Pull'!N41-1))) -> - | U41: ='RETAIL Load Pull'!E41-'RETAIL Load Pull'!F41 -> 0 | V41: ='RETAIL Load Pull'!E41-'RETAIL Load Pull'!G41 -> -0.7010033 | W41: =#REF!-N41 -> #REF! | Y41: =#REF!-'Tracks Pull'!M41 -> #REF! | AA41: =V41-'Tracks Pull'!O41 -> -0.78513686 | AC41: ='Stream Pull'!F41 -> 1.5331539 | AD41: ='Stream Pull'!G41 -> 0 | AE41: ='Stream Pull'!H41 -> 1.5331539 | AF41: ='Stream Pull'!M41 -> 5.0913546 | AG41: =AC41+AF41 -> 6.6245086 | AH41: ='Consol Pull'!F41-'Consol Pull'!G41 -> 3.2096238 | AI41: =AG41-AH41 -> 3.4148848 | AK41: =I41+AG41 -> 8.7669578 | AM41: =AK41-E41 -> -14.536177 | AO41: ='FIRM Load Pull'!#REF! -> #REF! | AP41: =I41+AG41+AO41 -> #REF! | AQ41: =AP41-E41 -> #REF!
A42: 26 | B42: APAC Top | C42: AP Top | D42: APAC Top | E42: ='Consol Pull'!F42 -> 0 | F42: =WW!E11 -> 628.39572 | G42: =WW!F11 -> 0.12269612 | H42: =WW!G11 -> 0 | I42: ='FIRM Load Pull'!E42 -> 0 | J42: ='Ship Load Pull'!E42 -> 0 | K42: =IF(ISERROR(I42/'FIRM Load Pull'!Q42-1),"-",IF(ABS(I42/'FIRM Load Pull'!Q42-1)>1000%," - ",(I42/'FIRM Load Pull'!Q42-1))) -> - | L42: ='FIRM Load Pull'!E42-'FIRM Load Pull'!F42 -> 0 | M42: ='FIRM Load Pull'!E42-'FIRM Load Pull'!G42 -> 0 | N42: ='Consol Pull'!G42 -> 0 | O42: =I42-N42 -> 0 | P42: =I42-'Tracks Pull'!E42 -> 0 | Q42: =M42-'Tracks Pull'!G42 -> 0 | R42: =WW!#REF! -> #REF! | S42: =WW!#REF! -> #REF! | T42: =WW!#REF! -> #REF! | U42: =WW!#REF! -> #REF! | V42: =WW!#REF! -> #REF! | W42: =WW!#REF! -> #REF! | X42: =WW!#REF! -> #REF! | Y42: =WW!#REF! -> #REF! | ... AB42: =WW!#REF! -> #REF! | AC42: ='Stream Pull'!F42 -> 0 | AD42: ='Stream Pull'!G42 -> 0 | AE42: ='Stream Pull'!H42 -> 0 | AF42: ='Stream Pull'!M42 -> 0 | AG42: =WW!Z11 -> 195.34302 | AH42: =WW!AA11 -> 217.60495 | AI42: =WW!AB11 -> -22.261933 | AJ42: =WW!AC11 -> 0 | AK42: =WW!AD11 -> 274.90975 | AL42: =WW!AE11 -> -0.56252129 | AM42: =WW!AF11 -> -430.58769
B43: nic | E43: ='Consol Pull'!F43 -> 0 | I43: ='FIRM Load Pull'!E43 -> 0 | J43: ='Ship Load Pull'!E43 -> 0 | K43: =IF(ISERROR(I43/'FIRM Load Pull'!Q43-1),"-",IF(ABS(I43/'FIRM Load Pull'!Q43-1)>1000%," - ",(I43/'FIRM Load Pull'!Q43-1))) -> - | L43: ='FIRM Load Pull'!E43-'FIRM Load Pull'!F43 -> 0 | M43: ='FIRM Load Pull'!E43-'FIRM Load Pull'!G43 -> 0 | N43: ='Consol Pull'!G43 -> 0 | O43: =I43-N43 -> 0 | P43: =I43-'Tracks Pull'!E43 -> -174.74552 | Q43: =M43-'Tracks Pull'!G43 -> -39.714158 | AC43: ='Stream Pull'!F43 -> 0 | AD43: ='Stream Pull'!G43 -> 0 | AE43: ='Stream Pull'!H43 -> 0 | AF43: ='Stream Pull'!M43 -> 0
A44: Power | B44: WW | C44: WW | D44: Power | E44: ='Consol Pull'!F44 -> 705.49744 | G44: =IF(ISERROR(E44/'Consol Pull'!T44-1),"-",IF(ABS(E44/'Consol Pull'!T44-1)>1000%," - ",(E44/'Consol Pull'!T44-1))) -> 0.12269612 | I44: ='FIRM Load Pull'!E44 -> 79.56673 | J44: ='Ship Load Pull'!E44 -> 62.466535 | K44: =IF(ISERROR(I44/'FIRM Load Pull'!Q44-1),"-",IF(ABS(I44/'FIRM Load Pull'!Q44-1)>1000%," - ",(I44/'FIRM Load Pull'!Q44-1))) -> -0.15817061 | L44: ='FIRM Load Pull'!E44-'FIRM Load Pull'!F44 -> 2.527334 | M44: ='FIRM Load Pull'!E44-'FIRM Load Pull'!G44 -> 11.435571 | N44: ='Consol Pull'!G44 -> 487.89249 | O44: =I44-N44 -> -408.32576 | P44: =I44-'Tracks Pull'!E44 -> 79.56673 | Q44: =M44-'Tracks Pull'!G44 -> 11.435571 | R44: =IF(ISERROR(#REF!/'RETAIL Load Pull'!N44-1),"-",IF(ABS(#REF!/'RETAIL Load Pull'!N44-1)>1000%," - ",(#REF!/'RETAIL Load Pull'!N44-1))) -> - | U44: ='RETAIL Load Pull'!E44-'RETAIL Load Pull'!F44 -> 14.825574 | V44: ='RETAIL Load Pull'!E44-'RETAIL Load Pull'!G44 -> 54.558178 | W44: =#REF!-N44 -> #REF! | Y44: =#REF!-'Tracks Pull'!M43 -> #REF! | AA44: =V44-'Tracks Pull'!O43 -> 14.84402 | AC44: ='Stream Pull'!F44 -> 73.101296 | AD44: ='Stream Pull'!G44 -> 14.19578 | AE44: ='Stream Pull'!H44 -> 58.905516 | AF44: ='Stream Pull'!M44 -> 122.24172 | AG44: =AC44+AF44 -> 195.34302 | AH44: ='Consol Pull'!F44-'Consol Pull'!G44 -> 217.60495 | AI44: =AG44-AH44 -> -22.261933 | AK44: =I44+AG44 -> 274.90975 | AM44: =AK44-E44 -> -430.58769 | AO44: ='FIRM Load Pull'!#REF! -> #REF! | AP44: =I44+AG44+AO44 -> #REF! | AQ44: =AP44-E44 -> #REF!
A45: Power | B45: Sum of Geos | C45: Sum of Geos | D45: Sum of Geos | E45: ='Consol Pull'!F45 -> 705.49744 | G45: =IF(ISERROR(E45/'Consol Pull'!T45-1),"-",IF(ABS(E45/'Consol Pull'!T45-1)>1000%," - ",(E45/'Consol Pull'!T45-1))) -> 0.12099988 | I45: ='FIRM Load Pull'!E45 -> 0 | J45: ='Ship Load Pull'!E45 -> 0 | K45: =IF(ISERROR(I45/'FIRM Load Pull'!Q45-1),"-",IF(ABS(I45/'FIRM Load Pull'!Q45-1)>1000%," - ",(I45/'FIRM Load Pull'!Q45-1))) -> - | L45: ='FIRM Load Pull'!E45-'FIRM Load Pull'!F45 -> 0 | M45: ='FIRM Load Pull'!E45-'FIRM Load Pull'!G45 -> 0 | N45: ='Consol Pull'!G45 -> 487.89249 | O45: =I45-N45 -> -487.89249 | P45: =I45-'Tracks Pull'!E45 -> 0 | Q45: =M45-'Tracks Pull'!G45 -> 0 | R45: =IF(ISERROR(#REF!/'RETAIL Load Pull'!N45-1),"-",IF(ABS(#REF!/'RETAIL Load Pull'!N45-1)>1000%," - ",(#REF!/'RETAIL Load Pull'!N45-1))) -> - | U45: ='RETAIL Load Pull'!E45-'RETAIL Load Pull'!F45 -> 0 | V45: ='RETAIL Load Pull'!E45-'RETAIL Load Pull'!G45 -> 0 | W45: =#REF!-N45 -> #REF! | Y45: =#REF!-'Tracks Pull'!M44 -> #REF! | AA45: =V45-'Tracks Pull'!O44 -> 0 | AC45: ='Stream Pull'!F45 -> 0 | AD45: ='Stream Pull'!G45 -> 0 | AE45: ='Stream Pull'!H45 -> 0 | AF45: ='Stream Pull'!M45 -> 0 | AG45: =AC45+AF45 -> 0 | AH45: ='Consol Pull'!F45-'Consol Pull'!G45 -> 217.60495 | AI45: =AG45-AH45 -> -217.60495 | AK45: =I45+AG45 -> 0 | AM45: =AK45-E45 -> -705.49744 | AO45: ='FIRM Load Pull'!#REF! -> #REF! | AP45: =I45+AG45+AO45 -> #REF! | AQ45: =AP45-E45 -> #REF!
A46: Power | B46: WW Top | C46: WW Top | D46: WW Top | E46: ='Consol Pull'!F46 -> 0 | G46: =IF(ISERROR(E46/'Consol Pull'!T46-1),"-",IF(ABS(E46/'Consol Pull'!T46-1)>1000%," - ",(E46/'Consol Pull'!T46-1))) -> -1 | I46: ='FIRM Load Pull'!E46 -> 0 | J46: ='Ship Load Pull'!E46 -> 0 | K46: =IF(ISERROR(I46/'FIRM Load Pull'!Q46-1),"-",IF(ABS(I46/'FIRM Load Pull'!Q46-1)>1000%," - ",(I46/'FIRM Load Pull'!Q46-1))) -> - | L46: ='FIRM Load Pull'!E46-'FIRM Load Pull'!F46 -> 0 | M46: ='FIRM Load Pull'!E46-'FIRM Load Pull'!G46 -> 0 | N46: ='Consol Pull'!G46 -> 0 | O46: =I46-N46 -> 0 | P46: =I46-'Tracks Pull'!E46 -> -59.21004 | Q46: =M46-'Tracks Pull'!G46 -> -16.765116 | R46: =IF(ISERROR(#REF!/'RETAIL Load Pull'!N46-1),"-",IF(ABS(#REF!/'RETAIL Load Pull'!N46-1)>1000%," - ",(#REF!/'RETAIL Load Pull'!N46-1))) -> - | U46: ='RETAIL Load Pull'!E46-'RETAIL Load Pull'!F46 -> 0 | V46: ='RETAIL Load Pull'!E46-'RETAIL Load Pull'!G46 -> 0 | W46: =#REF!-N46 -> #REF! | Y46: =#REF!-'Tracks Pull'!M45 -> #REF! | AA46: =V46-'Tracks Pull'!O45 -> 0 | AC46: ='Stream Pull'!F46 -> 0 | AD46: ='Stream Pull'!G46 -> 0 | AE46: ='Stream Pull'!H46 -> 0 | AF46: ='Stream Pull'!M46 -> 0 | AG46: =AC46+AF46 -> 0 | AH46: ='Consol Pull'!F46-'Consol Pull'!G46 -> 0 | AI46: =AG46-AH46 -> 0 | AK46: =I46+AG46 -> 0 | AM46: =AK46-E46 -> 0 | AO46: ='FIRM Load Pull'!#REF! -> #REF! | AP46: =I46+AG46+AO46 -> #REF! | AQ46: =AP46-E46 -> #REF!
A47: Power | B47: Americas | C47: Americas | D47: Americas | E47: ='Consol Pull'!F47 -> 310.56694 | G47: =IF(ISERROR(E47/'Consol Pull'!T47-1),"-",IF(ABS(E47/'Consol Pull'!T47-1)>1000%," - ",(E47/'Consol Pull'!T47-1))) -> 0.29521456 | I47: ='FIRM Load Pull'!E47 -> 16.236899 | J47: ='Ship Load Pull'!E47 -> 19.769533 | K47: =IF(ISERROR(I47/'FIRM Load Pull'!Q47-1),"-",IF(ABS(I47/'FIRM Load Pull'!Q47-1)>1000%," - ",(I47/'FIRM Load Pull'!Q47-1))) -> -0.33400527 | L47: ='FIRM Load Pull'!E47-'FIRM Load Pull'!F47 -> 0.15086584 | M47: ='FIRM Load Pull'!E47-'FIRM Load Pull'!G47 -> 4.4218189 | N47: ='Consol Pull'!G47 -> 207.70299 | O47: =I47-N47 -> -191.46609 | P47: =I47-'Tracks Pull'!E47 -> 5.6612296 | Q47: =M47-'Tracks Pull'!G47 -> 1.427355 | R47: =IF(ISERROR(#REF!/'RETAIL Load Pull'!N47-1),"-",IF(ABS(#REF!/'RETAIL Load Pull'!N47-1)>1000%," - ",(#REF!/'RETAIL Load Pull'!N47-1))) -> - | U47: ='RETAIL Load Pull'!E47-'RETAIL Load Pull'!F47 -> 4.6582671 | V47: ='RETAIL Load Pull'!E47-'RETAIL Load Pull'!G47 -> 27.270373 | W47: =#REF!-N47 -> #REF! | Y47: =#REF!-'Tracks Pull'!M46 -> #REF! | AA47: =V47-'Tracks Pull'!O46 -> 10.505257 | AC47: ='Stream Pull'!F47 -> 34.485317 | AD47: ='Stream Pull'!G47 -> 4.3964096 | AE47: ='Stream Pull'!H47 -> 30.088907 | AF47: ='Stream Pull'!M47 -> 57.297516 | AG47: =AC47+AF47 -> 91.782833 | AH47: ='Consol Pull'!F47-'Consol Pull'!G47 -> 102.86395 | AI47: =AG47-AH47 -> -11.081117 | AK47: =I47+AG47 -> 108.01973 | AM47: =AK47-E47 -> -202.5472 | AO47: ='FIRM Load Pull'!#REF! -> #REF! | AP47: =I47+AG47+AO47 -> #REF! | AQ47: =AP47-E47 -> #REF!
A48: Power | B48: 4A | C48: 4A | D48: US Industry | E48: ='Consol Pull'!F48 -> 50.055672 | G48: =IF(ISERROR(E48/'Consol Pull'!T48-1),"-",IF(ABS(E48/'Consol Pull'!T48-1)>1000%," - ",(E48/'Consol Pull'!T48-1))) -> - | I48: ='FIRM Load Pull'!E48 -> 3.1201139 | J48: ='Ship Load Pull'!E48 -> 1.6130656 | K48: =IF(ISERROR(I48/'FIRM Load Pull'!Q48-1),"-",IF(ABS(I48/'FIRM Load Pull'!Q48-1)>1000%," - ",(I48/'FIRM Load Pull'!Q48-1))) -> -0.43362 | L48: ='FIRM Load Pull'!E48-'FIRM Load Pull'!F48 -> 0 | M48: ='FIRM Load Pull'!E48-'FIRM Load Pull'!G48 -> 1.4226303 | N48: ='Consol Pull'!G48 -> 37.098408 | O48: =I48-N48 -> -33.978294 | P48: =I48-'Tracks Pull'!E48 -> 3.0058421 | Q48: =M48-'Tracks Pull'!G48 -> 1.3902747 | R48: =IF(ISERROR(#REF!/'RETAIL Load Pull'!N48-1),"-",IF(ABS(#REF!/'RETAIL Load Pull'!N48-1)>1000%," - ",(#REF!/'RETAIL Load Pull'!N48-1))) -> - | U48: ='RETAIL Load Pull'!E48-'RETAIL Load Pull'!F48 -> 0 | V48: ='RETAIL Load Pull'!E48-'RETAIL Load Pull'!G48 -> 1.5726303 | W48: =#REF!-N48 -> #REF! | Y48: =#REF!-'Tracks Pull'!M47 -> #REF! | AA48: =V48-'Tracks Pull'!O47 -> -1.4218336 | AC48: ='Stream Pull'!F48 -> 4.8541205 | AD48: ='Stream Pull'!G48 -> 0.54786041 | AE48: ='Stream Pull'!H48 -> 4.3062601 | AF48: ='Stream Pull'!M48 -> 6.18 | AG48: =AC48+AF48 -> 11.034121 | AH48: ='Consol Pull'!F48-'Consol Pull'!G48 -> 12.957264 | AI48: =AG48-AH48 -> -1.9231432 | AK48: =I48+AG48 -> 14.154234 | AM48: =AK48-E48 -> -35.901437 | AO48: ='FIRM Load Pull'!#REF! -> #REF! | AP48: =I48+AG48+AO48 -> #REF! | AQ48: =AP48-E48 -> #REF!
A49: Power | B49: 4O | C49: 4O | D49: US Build/Service Partners | E49: ='Consol Pull'!F49 -> 1.2999331 | G49: =IF(ISERROR(E49/'Consol Pull'!T49-1),"-",IF(ABS(E49/'Consol Pull'!T49-1)>1000%," - ",(E49/'Consol Pull'!T49-1))) -> - | I49: ='FIRM Load Pull'!E49 -> 0.080696495 | J49: ='Ship Load Pull'!E49 -> 0.080696495 | K49: =IF(ISERROR(I49/'FIRM Load Pull'!Q49-1),"-",IF(ABS(I49/'FIRM Load Pull'!Q49-1)>1000%," - ",(I49/'FIRM Load Pull'!Q49-1))) -> -0.95201183 | L49: ='FIRM Load Pull'!E49-'FIRM Load Pull'!F49 -> 0 | M49: ='FIRM Load Pull'!E49-'FIRM Load Pull'!G49 -> -0.00231397 | N49: ='Consol Pull'!G49 -> 0.40085423 | O49: =I49-N49 -> -0.32015774 | P49: =I49-'Tracks Pull'!E49 -> -21.200071 | Q49: =M49-'Tracks Pull'!G49 -> -6.0517389 | R49: =IF(ISERROR(#REF!/'RETAIL Load Pull'!N49-1),"-",IF(ABS(#REF!/'RETAIL Load Pull'!N49-1)>1000%," - ",(#REF!/'RETAIL Load Pull'!N49-1))) -> - | U49: ='RETAIL Load Pull'!E49-'RETAIL Load Pull'!F49 -> 0 | V49: ='RETAIL Load Pull'!E49-'RETAIL Load Pull'!G49 -> -0.00231397 | W49: =#REF!-N49 -> #REF! | Y49: =#REF!-'Tracks Pull'!M48 -> #REF! | AA49: =V49-'Tracks Pull'!O48 -> -0.034669632 | AC49: ='Stream Pull'!F49 -> 0 | AD49: ='Stream Pull'!G49 -> 0 | AE49: ='Stream Pull'!H49 -> 0 | AF49: ='Stream Pull'!M49 -> 0.28 | AG49: =AC49+AF49 -> 0.28 | AH49: ='Consol Pull'!F49-'Consol Pull'!G49 -> 0.89907883 | AI49: =AG49-AH49 -> -0.61907883 | AK49: =I49+AG49 -> 0.3606965 | AM49: =AK49-E49 -> -0.93923657 | AO49: ='FIRM Load Pull'!#REF! -> #REF! | AP49: =I49+AG49+AO49 -> #REF! | AQ49: =AP49-E49 -> #REF!
A50: Power | B50: 4J | C50: 4J | D50: US National | E50: ='Consol Pull'!F50 -> 109.45059 | G50: =IF(ISERROR(E50/'Consol Pull'!T50-1),"-",IF(ABS(E50/'Consol Pull'!T50-1)>1000%," - ",(E50/'Consol Pull'!T50-1))) -> - | I50: ='FIRM Load Pull'!E50 -> 9.0891047 | J50: ='Ship Load Pull'!E50 -> 6.3326558 | K50: =IF(ISERROR(I50/'FIRM Load Pull'!Q50-1),"-",IF(ABS(I50/'FIRM Load Pull'!Q50-1)>1000%," - ",(I50/'FIRM Load Pull'!Q50-1))) -> 0.17640007 | L50: ='FIRM Load Pull'!E50-'FIRM Load Pull'!F50 -> 0.13952082 | M50: ='FIRM Load Pull'!E50-'FIRM Load Pull'!G50 -> 2.2870944 | N50: ='Consol Pull'!G50 -> 74.798863 | O50: =I50-N50 -> -65.709758 | P50: =I50-'Tracks Pull'!E50 -> 1.5663009 | Q50: =M50-'Tracks Pull'!G50 -> 0.15703879 | R50: =IF(ISERROR(#REF!/'RETAIL Load Pull'!N50-1),"-",IF(ABS(#REF!/'RETAIL Load Pull'!N50-1)>1000%," - ",(#REF!/'RETAIL Load Pull'!N50-1))) -> - | U50: ='RETAIL Load Pull'!E50-'RETAIL Load Pull'!F50 -> 0.017903174 | V50: ='RETAIL Load Pull'!E50-'RETAIL Load Pull'!G50 -> 12.037735 | W50: =#REF!-N50 -> #REF! | Y50: =#REF!-'Tracks Pull'!M49 -> #REF! | AA50: =V50-'Tracks Pull'!O49 -> 5.9883103 | AC50: ='Stream Pull'!F50 -> 12.259932 | AD50: ='Stream Pull'!G50 -> 2.2591077 | AE50: ='Stream Pull'!H50 -> 10.000824 | AF50: ='Stream Pull'!M50 -> 19.457516 | AG50: =AC50+AF50 -> 31.717448 | AH50: ='Consol Pull'!F50-'Consol Pull'!G50 -> 34.651731 | AI50: =AG50-AH50 -> -2.9342831 | AK50: =I50+AG50 -> 40.806552 | AM50: =AK50-E50 -> -68.644041 | AO50: ='FIRM Load Pull'!#REF! -> #REF! | AP50: =I50+AG50+AO50 -> #REF! | AQ50: =AP50-E50 -> #REF!
A51: Power | B51: 4L | C51: 4L | D51: FSS | E51: ='Consol Pull'!F51 -> 35.410219 | G51: =IF(ISERROR(E51/'Consol Pull'!T51-1),"-",IF(ABS(E51/'Consol Pull'!T51-1)>1000%," - ",(E51/'Consol Pull'!T51-1))) -> - | I51: ='FIRM Load Pull'!E51 -> 0.9938473 | J51: ='Ship Load Pull'!E51 -> 1.3538473 | K51: =IF(ISERROR(I51/'FIRM Load Pull'!Q51-1),"-",IF(ABS(I51/'FIRM Load Pull'!Q51-1)>1000%," - ",(I51/'FIRM Load Pull'!Q51-1))) -> -3.3090228 | L51: ='FIRM Load Pull'!E51-'FIRM Load Pull'!F51 -> 0 | M51: ='FIRM Load Pull'!E51-'FIRM Load Pull'!G51 -> 0.10284482 | N51: ='Consol Pull'!G51 -> 26.389254 | O51: =I51-N51 -> -25.395407 | P51: =I51-'Tracks Pull'!E51 -> -2.3790041 | Q51: =M51-'Tracks Pull'!G51 -> -0.85216627 | R51: =IF(ISERROR(#REF!/'RETAIL Load Pull'!N51-1),"-",IF(ABS(#REF!/'RETAIL Load Pull'!N51-1)>1000%," - ",(#REF!/'RETAIL Load Pull'!N51-1))) -> - | U51: ='RETAIL Load Pull'!E51-'RETAIL Load Pull'!F51 -> 3.3226677 | V51: ='RETAIL Load Pull'!E51-'RETAIL Load Pull'!G51 -> 3.5155125 | W51: =#REF!-N51 -> #REF! | Y51: =#REF!-'Tracks Pull'!M50 -> #REF! | AA51: =V51-'Tracks Pull'!O50 -> 1.385457 | AC51: ='Stream Pull'!F51 -> 3.7519379 | AD51: ='Stream Pull'!G51 -> 0.17473043 | AE51: ='Stream Pull'!H51 -> 3.5772075 | AF51: ='Stream Pull'!M51 -> 4.02 | AG51: =AC51+AF51 -> 7.7719379 | AH51: ='Consol Pull'!F51-'Consol Pull'!G51 -> 9.0209648 | AI51: =AG51-AH51 -> -1.2490269 | AK51: =I51+AG51 -> 8.7657852 | AM51: =AK51-E51 -> -26.644434 | AO51: ='FIRM Load Pull'!#REF! -> #REF! | AP51: =I51+AG51+AO51 -> #REF! | AQ51: =AP51-E51 -> #REF!
A52: Power | B52: 4P | C52: 4P | D52: Public | E52: ='Consol Pull'!F52 -> 19.125371 | G52: =IF(ISERROR(E52/'Consol Pull'!T52-1),"-",IF(ABS(E52/'Consol Pull'!T52-1)>1000%," - ",(E52/'Consol Pull'!T52-1))) -> - | I52: ='FIRM Load Pull'!E52 -> 1.6162016 | J52: ='Ship Load Pull'!E52 -> 1.6845422 | K52: =IF(ISERROR(I52/'FIRM Load Pull'!Q52-1),"-",IF(ABS(I52/'FIRM Load Pull'!Q52-1)>1000%," - ",(I52/'FIRM Load Pull'!Q52-1))) -> -0.0032148183 | L52: ='FIRM Load Pull'!E52-'FIRM Load Pull'!F52 -> 0 | M52: ='FIRM Load Pull'!E52-'FIRM Load Pull'!G52 -> 0.51694454 | N52: ='Consol Pull'!G52 -> 11.831631 | O52: =I52-N52 -> -10.215429 | P52: =I52-'Tracks Pull'!E52 -> -0.30407475 | Q52: =M52-'Tracks Pull'!G52 -> -0.02677499 | R52: =IF(ISERROR(#REF!/'RETAIL Load Pull'!N52-1),"-",IF(ABS(#REF!/'RETAIL Load Pull'!N52-1)>1000%," - ",(#REF!/'RETAIL Load Pull'!N52-1))) -> - | U52: ='RETAIL Load Pull'!E52-'RETAIL Load Pull'!F52 -> 0 | V52: ='RETAIL Load Pull'!E52-'RETAIL Load Pull'!G52 -> 4.8631257 | W52: =#REF!-N52 -> #REF! | Y52: =#REF!-'Tracks Pull'!#REF! -> #REF! | AA52: =V52-'Tracks Pull'!#REF! -> #REF! | AC52: ='Stream Pull'!F52 -> 2.2558085 | AD52: ='Stream Pull'!G52 -> 0.16254179 | AE52: ='Stream Pull'!H52 -> 2.0932667 | AF52: ='Stream Pull'!M52 -> 4.03 | AG52: =AC52+AF52 -> 6.2858085 | AH52: ='Consol Pull'!F52-'Consol Pull'!G52 -> 7.2937406 | AI52: =AG52-AH52 -> -1.007932 | AK52: =I52+AG52 -> 7.9020101 | AM52: =AK52-E52 -> -11.223361 | AO52: ='FIRM Load Pull'!#REF! -> #REF! | AP52: =I52+AG52+AO52 -> #REF! | AQ52: =AP52-E52 -> #REF!
A53: Power | B53: 4X | C53: 4X | D53: Federal | E53: ='Consol Pull'!F53 -> 9.4721772 | G53: =IF(ISERROR(E53/'Consol Pull'!T53-1),"-",IF(ABS(E53/'Consol Pull'!T53-1)>1000%," - ",(E53/'Consol Pull'!T53-1))) -> - | I53: ='FIRM Load Pull'!E53 -> 0.87073003 | J53: ='Ship Load Pull'!E53 -> 0.87073003 | K53: =IF(ISERROR(I53/'FIRM Load Pull'!Q53-1),"-",IF(ABS(I53/'FIRM Load Pull'!Q53-1)>1000%," - ",(I53/'FIRM Load Pull'!Q53-1))) -> 2.7405262 | L53: ='FIRM Load Pull'!E53-'FIRM Load Pull'!F53 -> 0 | M53: ='FIRM Load Pull'!E53-'FIRM Load Pull'!G53 -> -0.01970042 | N53: ='Consol Pull'!G53 -> 6.7361403 | O53: =I53-N53 -> -5.8654102 | P53: =I53-'Tracks Pull'!E53 -> -0.084588381 | Q53: =M53-'Tracks Pull'!G53 -> -0.26634554 | R53: =IF(ISERROR(#REF!/'RETAIL Load Pull'!N53-1),"-",IF(ABS(#REF!/'RETAIL Load Pull'!N53-1)>1000%," - ",(#REF!/'RETAIL Load Pull'!N53-1))) -> - | U53: ='RETAIL Load Pull'!E53-'RETAIL Load Pull'!F53 -> 0 | V53: ='RETAIL Load Pull'!E53-'RETAIL Load Pull'!G53 -> -0.01970042 | W53: =#REF!-N53 -> #REF! | Y53: =#REF!-'Tracks Pull'!#REF! -> #REF! | AA53: =V53-'Tracks Pull'!#REF! -> #REF! | AC53: ='Stream Pull'!F53 -> 0.52778967 | AD53: ='Stream Pull'!G53 -> 0.13147241 | AE53: ='Stream Pull'!H53 -> 0.39631726 | AF53: ='Stream Pull'!M53 -> 0.77 | AG53: =AC53+AF53 -> 1.2977897 | AH53: ='Consol Pull'!F53-'Consol Pull'!G53 -> 2.7360369 | AI53: =AG53-AH53 -> -1.4382473 | AK53: =I53+AG53 -> 2.1685197 | AM53: =AK53-E53 -> -7.3036575
A54: Power | B54: 4V | C54: 4V | D54: US Top | E54: ='Consol Pull'!F54 -> 21.940748 | G54: =IF(ISERROR(E54/'Consol Pull'!T54-1),"-",IF(ABS(E54/'Consol Pull'!T54-1)>1000%," - ",(E54/'Consol Pull'!T54-1))) -> - | I54: ='FIRM Load Pull'!E54 -> -4.3256449 | J54: ='Ship Load Pull'!E54 -> 3.0708592 | K54: =IF(ISERROR(I54/'FIRM Load Pull'!Q54-1),"-",IF(ABS(I54/'FIRM Load Pull'!Q54-1)>1000%," - ",(I54/'FIRM Load Pull'!Q54-1))) -> 0.41833544 | L54: ='FIRM Load Pull'!E54-'FIRM Load Pull'!F54 -> 0 | M54: ='FIRM Load Pull'!E54-'FIRM Load Pull'!G54 -> -0.27536396 | N54: ='Consol Pull'!G54 -> 3.2031376 | O54: =I54-N54 -> -7.5287826 | P54: =I54-'Tracks Pull'!E54 -> -9.1646391 | Q54: =M54-'Tracks Pull'!G54 -> -1.2776094 | R54: =IF(ISERROR(#REF!/'RETAIL Load Pull'!N54-1),"-",IF(ABS(#REF!/'RETAIL Load Pull'!N54-1)>1000%," - ",(#REF!/'RETAIL Load Pull'!N54-1))) -> - | U54: ='RETAIL Load Pull'!E54-'RETAIL Load Pull'!F54 -> 0 | V54: ='RETAIL Load Pull'!E54-'RETAIL Load Pull'!G54 -> 3.120213 | W54: =#REF!-N54 -> #REF! | Y54: =#REF!-'Tracks Pull'!M53 -> #REF! | AA54: =V54-'Tracks Pull'!O53 -> 2.8735679 | AC54: ='Stream Pull'!F54 -> 0 | AD54: ='Stream Pull'!G54 -> 0 | AE54: ='Stream Pull'!H54 -> 0 | AF54: ='Stream Pull'!M54 -> 12.89 | AG54: =AC54+AF54 -> 12.89 | AH54: ='Consol Pull'!F54-'Consol Pull'!G54 -> 18.737611 | AI54: =AG54-AH54 -> -5.8476106 | AK54: =I54+AG54 -> 8.5643551 | AM54: =AK54-E54 -> -13.376393 | AO54: ='FIRM Load Pull'!#REF! -> #REF! | AP54: =I54+AG54+AO54 -> #REF! | AQ54: =AP54-E54 -> #REF!
A55: Power | B55: Canada | C55: Canada | D55: Canada | E55: ='Consol Pull'!F55 -> 21.338865 | G55: =IF(ISERROR(E55/'Consol Pull'!T55-1),"-",IF(ABS(E55/'Consol Pull'!T55-1)>1000%," - ",(E55/'Consol Pull'!T55-1))) -> -0.011364319 | I55: ='FIRM Load Pull'!E55 -> 0.776701 | J55: ='Ship Load Pull'!E55 -> 1.2146277 | K55: =IF(ISERROR(I55/'FIRM Load Pull'!Q55-1),"-",IF(ABS(I55/'FIRM Load Pull'!Q55-1)>1000%," - ",(I55/'FIRM Load Pull'!Q55-1))) -> -0.688239 | L55: ='FIRM Load Pull'!E55-'FIRM Load Pull'!F55 -> 0 | M55: ='FIRM Load Pull'!E55-'FIRM Load Pull'!G55 -> 0.59667163 | N55: ='Consol Pull'!G55 -> 14.691342 | O55: =I55-N55 -> -13.914641 | P55: =I55-'Tracks Pull'!E55 -> -7.8523849 | Q55: =M55-'Tracks Pull'!G55 -> -2.2145227 | R55: =IF(ISERROR(#REF!/'RETAIL Load Pull'!N55-1),"-",IF(ABS(#REF!/'RETAIL Load Pull'!N55-1)>1000%," - ",(#REF!/'RETAIL Load Pull'!N55-1))) -> - | U55: ='RETAIL Load Pull'!E55-'RETAIL Load Pull'!F55 -> 0 | V55: ='RETAIL Load Pull'!E55-'RETAIL Load Pull'!G55 -> 1.0844082 | W55: =#REF!-N55 -> #REF! | Y55: =#REF!-'Tracks Pull'!M54 -> #REF! | AA55: =V55-'Tracks Pull'!O54 -> 0.082162714 | AC55: ='Stream Pull'!F55 -> 5.6196466 | AD55: ='Stream Pull'!G55 -> 0.16417211 | AE55: ='Stream Pull'!H55 -> 5.4554745 | AF55: ='Stream Pull'!M55 -> 3.79 | AG55: =AC55+AF55 -> 9.4096466 | AH55: ='Consol Pull'!F55-'Consol Pull'!G55 -> 6.6475237 | AI55: =AG55-AH55 -> 2.762123 | AK55: =I55+AG55 -> 10.186348 | AM55: =AK55-E55 -> -11.152518 | AO55: ='FIRM Load Pull'!#REF! -> #REF! | AP55: =I55+AG55+AO55 -> #REF! | AQ55: =AP55-E55 -> #REF!
A56: Power | B56: LA | C56: LA | D56: LA | E56: ='Consol Pull'!F56 -> 42.473356 | G56: =IF(ISERROR(E56/'Consol Pull'!T56-1),"-",IF(ABS(E56/'Consol Pull'!T56-1)>1000%," - ",(E56/'Consol Pull'!T56-1))) -> 0.20216737 | I56: ='FIRM Load Pull'!E56 -> 4.0151494 | J56: ='Ship Load Pull'!E56 -> 3.5485089 | K56: =IF(ISERROR(I56/'FIRM Load Pull'!Q56-1),"-",IF(ABS(I56/'FIRM Load Pull'!Q56-1)>1000%," - ",(I56/'FIRM Load Pull'!Q56-1))) -> -0.53301082 | L56: ='FIRM Load Pull'!E56-'FIRM Load Pull'!F56 -> 0.011345013 | M56: ='FIRM Load Pull'!E56-'FIRM Load Pull'!G56 -> -0.20698838 | N56: ='Consol Pull'!G56 -> 32.553356 | O56: =I56-N56 -> -28.538207 | P56: =I56-'Tracks Pull'!E56 -> -55.334864 | Q56: =M56-'Tracks Pull'!G56 -> -14.541342 | R56: =IF(ISERROR(#REF!/'RETAIL Load Pull'!N56-1),"-",IF(ABS(#REF!/'RETAIL Load Pull'!N56-1)>1000%," - ",(#REF!/'RETAIL Load Pull'!N56-1))) -> - | U56: ='RETAIL Load Pull'!E56-'RETAIL Load Pull'!F56 -> 1.3176962 | V56: ='RETAIL Load Pull'!E56-'RETAIL Load Pull'!G56 -> 1.0987621 | W56: =#REF!-N56 -> #REF! | Y56: =#REF!-'Tracks Pull'!M55 -> #REF! | AA56: =V56-'Tracks Pull'!O55 -> -1.7124323 | AC56: ='Stream Pull'!F56 -> 5.2160818 | AD56: ='Stream Pull'!G56 -> 0.95652476 | AE56: ='Stream Pull'!H56 -> 4.2595571 | AF56: ='Stream Pull'!M56 -> 5.88 | AG56: =AC56+AF56 -> 11.096082 | AH56: ='Consol Pull'!F56-'Consol Pull'!G56 -> 9.92 | AI56: =AG56-AH56 -> 1.1760818 | AK56: =I56+AG56 -> 15.111231 | AM56: =AK56-E56 -> -27.362125 | AO56: ='FIRM Load Pull'!#REF! -> #REF! | AP56: =I56+AG56+AO56 -> #REF! | AQ56: =AP56-E56 -> #REF!
A57: Power | B57: EMEA | C57: EMEA | D57: EMEA | E57: ='Consol Pull'!F57 -> 227.8848 | G57: =IF(ISERROR(E57/'Consol Pull'!T57-1),"-",IF(ABS(E57/'Consol Pull'!T57-1)>1000%," - ",(E57/'Consol Pull'!T57-1))) -> -0.066744044 | I57: ='FIRM Load Pull'!E57 -> 33.317005 | J57: ='Ship Load Pull'!E57 -> 23.89606 | K57: =IF(ISERROR(I57/'FIRM Load Pull'!Q57-1),"-",IF(ABS(I57/'FIRM Load Pull'!Q57-1)>1000%," - ",(I57/'FIRM Load Pull'!Q57-1))) -> -0.019456015 | L57: ='FIRM Load Pull'!E57-'FIRM Load Pull'!F57 -> 1.972338 | M57: ='FIRM Load Pull'!E57-'FIRM Load Pull'!G57 -> 6.2704183 | N57: ='Consol Pull'!G57 -> 164.65587 | O57: =I57-N57 -> -131.33887 | P57: =I57-'Tracks Pull'!E57 -> 9.895689 | Q57: =M57-'Tracks Pull'!G57 -> 0.61364768 | R57: =IF(ISERROR(#REF!/'RETAIL Load Pull'!N57-1),"-",IF(ABS(#REF!/'RETAIL Load Pull'!N57-1)>1000%," - ",(#REF!/'RETAIL Load Pull'!N57-1))) -> - | U57: ='RETAIL Load Pull'!E57-'RETAIL Load Pull'!F57 -> 8.9089842 | V57: ='RETAIL Load Pull'!E57-'RETAIL Load Pull'!G57 -> 24.8245 | W57: =#REF!-N57 -> #REF! | Y57: =#REF!-'Tracks Pull'!M56 -> #REF! | AA57: =V57-'Tracks Pull'!O56 -> 10.490147 | AC57: ='Stream Pull'!F57 -> 20.177501 | AD57: ='Stream Pull'!G57 -> 4.0815085 | AE57: ='Stream Pull'!H57 -> 16.095992 | AF57: ='Stream Pull'!M57 -> 36.924717 | AG57: =AC57+AF57 -> 57.102218 | AH57: ='Consol Pull'!F57-'Consol Pull'!G57 -> 63.228933 | AI57: =AG57-AH57 -> -6.1267152 | AK57: =I57+AG57 -> 90.419222 | AM57: =AK57-E57 -> -137.46558 | AO57: ='FIRM Load Pull'!#REF! -> #REF! | AP57: =I57+AG57+AO57 -> #REF! | AQ57: =AP57-E57 -> #REF!
A58: Power | B58: Dach | C58: Dach | D58: Dach | E58: ='Consol Pull'!F58 -> 69.368105 | G58: =IF(ISERROR(E58/'Consol Pull'!T58-1),"-",IF(ABS(E58/'Consol Pull'!T58-1)>1000%," - ",(E58/'Consol Pull'!T58-1))) -> -0.097886259 | I58: ='FIRM Load Pull'!E58 -> 3.4876261 | J58: ='Ship Load Pull'!E58 -> 4.4614373 | K58: =IF(ISERROR(I58/'FIRM Load Pull'!Q58-1),"-",IF(ABS(I58/'FIRM Load Pull'!Q58-1)>1000%," - ",(I58/'FIRM Load Pull'!Q58-1))) -> -0.18138848 | L58: ='FIRM Load Pull'!E58-'FIRM Load Pull'!F58 -> 0 | M58: ='FIRM Load Pull'!E58-'FIRM Load Pull'!G58 -> -1.5084716 | N58: ='Consol Pull'!G58 -> 52.927924 | O58: =I58-N58 -> -49.440298 | P58: =I58-'Tracks Pull'!E58 -> -2.3545579 | Q58: =M58-'Tracks Pull'!G58 -> -2.9194894 | R58: =IF(ISERROR(#REF!/'RETAIL Load Pull'!N58-1),"-",IF(ABS(#REF!/'RETAIL Load Pull'!N58-1)>1000%," - ",(#REF!/'RETAIL Load Pull'!N58-1))) -> - | U58: ='RETAIL Load Pull'!E58-'RETAIL Load Pull'!F58 -> 0 | V58: ='RETAIL Load Pull'!E58-'RETAIL Load Pull'!G58 -> 2.2187424 | W58: =#REF!-N58 -> #REF! | Y58: =#REF!-'Tracks Pull'!M57 -> #REF! | AA58: =V58-'Tracks Pull'!O57 -> -3.4380282 | AC58: ='Stream Pull'!F58 -> 4.3054187 | AD58: ='Stream Pull'!G58 -> 0.66368268 | AE58: ='Stream Pull'!H58 -> 3.6417361 | AF58: ='Stream Pull'!M58 -> 8.6489346 | AG58: =AC58+AF58 -> 12.954353 | AH58: ='Consol Pull'!F58-'Consol Pull'!G58 -> 16.44018 | AI58: =AG58-AH58 -> -3.485827 | AK58: =I58+AG58 -> 16.441979 | AM58: =AK58-E58 -> -52.926125 | AO58: ='FIRM Load Pull'!#REF! -> #REF! | AP58: =I58+AG58+AO58 -> #REF! | AQ58: =AP58-E58 -> #REF!
A59: Power | B59: France | C59: France | D59: France | E59: ='Consol Pull'!F59 -> 19.501147 | G59: =IF(ISERROR(E59/'Consol Pull'!T59-1),"-",IF(ABS(E59/'Consol Pull'!T59-1)>1000%," - ",(E59/'Consol Pull'!T59-1))) -> -0.06004874 | I59: ='FIRM Load Pull'!E59 -> 2.8845728 | J59: ='Ship Load Pull'!E59 -> 1.6171943 | K59: =IF(ISERROR(I59/'FIRM Load Pull'!Q59-1),"-",IF(ABS(I59/'FIRM Load Pull'!Q59-1)>1000%," - ",(I59/'FIRM Load Pull'!Q59-1))) -> 0.6151736 | L59: ='FIRM Load Pull'!E59-'FIRM Load Pull'!F59 -> 0.1038868 | M59: ='FIRM Load Pull'!E59-'FIRM Load Pull'!G59 -> 0.55104086 | N59: ='Consol Pull'!G59 -> 13.202276 | O59: =I59-N59 -> -10.317703 | P59: =I59-'Tracks Pull'!E59 -> -4.1456029 | Q59: =M59-'Tracks Pull'!G59 -> -1.1469035 | R59: =IF(ISERROR(#REF!/'RETAIL Load Pull'!N59-1),"-",IF(ABS(#REF!/'RETAIL Load Pull'!N59-1)>1000%," - ",(#REF!/'RETAIL Load Pull'!N59-1))) -> - | U59: ='RETAIL Load Pull'!E59-'RETAIL Load Pull'!F59 -> 0.1038868 | V59: ='RETAIL Load Pull'!E59-'RETAIL Load Pull'!G59 -> 0.87895223 | W59: =#REF!-N59 -> #REF! | Y59: =#REF!-'Tracks Pull'!M58 -> #REF! | AA59: =V59-'Tracks Pull'!O58 -> -0.53206564 | AC59: ='Stream Pull'!F59 -> 1.8344219 | AD59: ='Stream Pull'!G59 -> 0.48033698 | AE59: ='Stream Pull'!H59 -> 1.3540849 | AF59: ='Stream Pull'!M59 -> 3.8667311 | AG59: =AC59+AF59 -> 5.701153 | AH59: ='Consol Pull'!F59-'Consol Pull'!G59 -> 6.2988712 | AI59: =AG59-AH59 -> -0.59771821 | AK59: =I59+AG59 -> 8.5857258 | AM59: =AK59-E59 -> -10.915421 | AO59: ='FIRM Load Pull'!#REF! -> #REF! | AP59: =I59+AG59+AO59 -> #REF! | AQ59: =AP59-E59 -> #REF!
A60: Power | B60: UKI | C60: UKI | D60: UKI | E60: ='Consol Pull'!F60 -> 24.845239 | G60: =IF(ISERROR(E60/'Consol Pull'!T60-1),"-",IF(ABS(E60/'Consol Pull'!T60-1)>1000%," - ",(E60/'Consol Pull'!T60-1))) -> -0.17423299 | I60: ='FIRM Load Pull'!E60 -> 0.61233873 | J60: ='Ship Load Pull'!E60 -> 1.0911333 | K60: =IF(ISERROR(I60/'FIRM Load Pull'!Q60-1),"-",IF(ABS(I60/'FIRM Load Pull'!Q60-1)>1000%," - ",(I60/'FIRM Load Pull'!Q60-1))) -> -0.87690454 | L60: ='FIRM Load Pull'!E60-'FIRM Load Pull'!F60 -> 0 | M60: ='FIRM Load Pull'!E60-'FIRM Load Pull'!G60 -> -0.31778237 | N60: ='Consol Pull'!G60 -> 15.886922 | O60: =I60-N60 -> -15.274583 | P60: =I60-'Tracks Pull'!E60 -> -3.8913931 | Q60: =M60-'Tracks Pull'!G60 -> -1.4055342 | R60: =IF(ISERROR(#REF!/'RETAIL Load Pull'!N60-1),"-",IF(ABS(#REF!/'RETAIL Load Pull'!N60-1)>1000%," - ",(#REF!/'RETAIL Load Pull'!N60-1))) -> - | U60: ='RETAIL Load Pull'!E60-'RETAIL Load Pull'!F60 -> 7.3383717 | V60: ='RETAIL Load Pull'!E60-'RETAIL Load Pull'!G60 -> 7.4241771 | W60: =#REF!-N60 -> #REF! | Y60: =#REF!-'Tracks Pull'!M59 -> #REF! | AA60: =V60-'Tracks Pull'!O59 -> 5.7262327 | AC60: ='Stream Pull'!F60 -> 2.1814355 | AD60: ='Stream Pull'!G60 -> 0.23564059 | AE60: ='Stream Pull'!H60 -> 1.9457949 | AF60: ='Stream Pull'!M60 -> 5.3004825 | AG60: =AC60+AF60 -> 7.4819181 | AH60: ='Consol Pull'!F60-'Consol Pull'!G60 -> 8.9583169 | AI60: =AG60-AH60 -> -1.4763989 | AK60: =I60+AG60 -> 8.0942568 | AM60: =AK60-E60 -> -16.750982 | AO60: ='FIRM Load Pull'!#REF! -> #REF! | AP60: =I60+AG60+AO60 -> #REF! | AQ60: =AP60-E60 -> #REF!
A61: Power | B61: Italy | C61: Italy | D61: Italy | E61: ='Consol Pull'!F61 -> 15.367584 | G61: =IF(ISERROR(E61/'Consol Pull'!T61-1),"-",IF(ABS(E61/'Consol Pull'!T61-1)>1000%," - ",(E61/'Consol Pull'!T61-1))) -> -0.002998477 | I61: ='FIRM Load Pull'!E61 -> 2.0193428 | J61: ='Ship Load Pull'!E61 -> 1.8638562 | K61: =IF(ISERROR(I61/'FIRM Load Pull'!Q61-1),"-",IF(ABS(I61/'FIRM Load Pull'!Q61-1)>1000%," - ",(I61/'FIRM Load Pull'!Q61-1))) -> 0.034432142 | L61: ='FIRM Load Pull'!E61-'FIRM Load Pull'!F61 -> 0.31753408 | M61: ='FIRM Load Pull'!E61-'FIRM Load Pull'!G61 -> 0.14119655 | N61: ='Consol Pull'!G61 -> 10.177617 | O61: =I61-N61 -> -8.1582743 | P61: =I61-'Tracks Pull'!E61 -> -1.3724156 | Q61: =M61-'Tracks Pull'!G61 -> -0.67798881 | R61: =IF(ISERROR(#REF!/'RETAIL Load Pull'!N61-1),"-",IF(ABS(#REF!/'RETAIL Load Pull'!N61-1)>1000%," - ",(#REF!/'RETAIL Load Pull'!N61-1))) -> - | U61: ='RETAIL Load Pull'!E61-'RETAIL Load Pull'!F61 -> 1.0454602 | V61: ='RETAIL Load Pull'!E61-'RETAIL Load Pull'!G61 -> 1.1540576 | W61: =#REF!-N61 -> #REF! | Y61: =#REF!-'Tracks Pull'!M60 -> #REF! | AA61: =V61-'Tracks Pull'!O60 -> 0.066305842 | AC61: ='Stream Pull'!F61 -> 1.1996985 | AD61: ='Stream Pull'!G61 -> 0.31152767 | AE61: ='Stream Pull'!H61 -> 0.88817086 | AF61: ='Stream Pull'!M61 -> 3.45549 | AG61: =AC61+AF61 -> 4.6551885 | AH61: ='Consol Pull'!F61-'Consol Pull'!G61 -> 5.1899672 | AI61: =AG61-AH61 -> -0.53477869 | AK61: =I61+AG61 -> 6.6745312 | AM61: =AK61-E61 -> -8.6930529 | AO61: ='FIRM Load Pull'!#REF! -> #REF! | AP61: =I61+AG61+AO61 -> #REF! | AQ61: =AP61-E61 -> #REF!
A62: Power | B62: SPIGI | C62: SPIGI | D62: SPIGI | E62: ='Consol Pull'!F62 -> 11.301933 | G62: =IF(ISERROR(E62/'Consol Pull'!T62-1),"-",IF(ABS(E62/'Consol Pull'!T62-1)>1000%," - ",(E62/'Consol Pull'!T62-1))) -> -0.14747809 | I62: ='FIRM Load Pull'!E62 -> 11.235183 | J62: ='Ship Load Pull'!E62 -> 3.2745554 | K62: =IF(ISERROR(I62/'FIRM Load Pull'!Q62-1),"-",IF(ABS(I62/'FIRM Load Pull'!Q62-1)>1000%," - ",(I62/'FIRM Load Pull'!Q62-1))) -> 2.7994047 | L62: ='FIRM Load Pull'!E62-'FIRM Load Pull'!F62 -> 1.5509171 | M62: ='FIRM Load Pull'!E62-'FIRM Load Pull'!G62 -> 6.917397 | N62: ='Consol Pull'!G62 -> 7.6647585 | O62: =I62-N62 -> 3.5704245 | P62: =I62-'Tracks Pull'!E62 -> 11.235183 | Q62: =M62-'Tracks Pull'!G62 -> 6.917397 | R62: =IF(ISERROR(#REF!/'RETAIL Load Pull'!N62-1),"-",IF(ABS(#REF!/'RETAIL Load Pull'!N62-1)>1000%," - ",(#REF!/'RETAIL Load Pull'!N62-1))) -> - | U62: ='RETAIL Load Pull'!E62-'RETAIL Load Pull'!F62 -> 0.27474013 | V62: ='RETAIL Load Pull'!E62-'RETAIL Load Pull'!G62 -> 11.509899 | W62: =#REF!-N62 -> #REF! | Y62: =#REF!-'Tracks Pull'!M61 -> #REF! | AA62: =V62-'Tracks Pull'!O61 -> 10.690713 | AC62: ='Stream Pull'!F62 -> 2.7142698 | AD62: ='Stream Pull'!G62 -> 0.81112785 | AE62: ='Stream Pull'!H62 -> 1.903142 | AF62: ='Stream Pull'!M62 -> 2.2398666 | AG62: =AC62+AF62 -> 4.9541364 | AH62: ='Consol Pull'!F62-'Consol Pull'!G62 -> 3.6371747 | AI62: =AG62-AH62 -> 1.3169618 | AK62: =I62+AG62 -> 16.189319 | AM62: =AK62-E62 -> 4.8873863 | AO62: ='FIRM Load Pull'!#REF! -> #REF! | AP62: =I62+AG62+AO62 -> #REF! | AQ62: =AP62-E62 -> #REF!
A63: Power | B63: NCEE | C63: NCEE | D63: NCEE | E63: ='Consol Pull'!F63 -> 44.465201 | G63: =IF(ISERROR(E63/'Consol Pull'!T63-1),"-",IF(ABS(E63/'Consol Pull'!T63-1)>1000%," - ",(E63/'Consol Pull'!T63-1))) -> -0.014419072 | I63: ='FIRM Load Pull'!E63 -> 7.5138676 | J63: ='Ship Load Pull'!E63 -> 5.6941119 | K63: =IF(ISERROR(I63/'FIRM Load Pull'!Q63-1),"-",IF(ABS(I63/'FIRM Load Pull'!Q63-1)>1000%," - ",(I63/'FIRM Load Pull'!Q63-1))) -> -0.24690886 | L63: ='FIRM Load Pull'!E63-'FIRM Load Pull'!F63 -> 0 | M63: ='FIRM Load Pull'!E63-'FIRM Load Pull'!G63 -> 1.6282084 | N63: ='Consol Pull'!G63 -> 30.535609 | O63: =I63-N63 -> -23.021741 | P63: =I63-'Tracks Pull'!E63 -> -7.6469801 | Q63: =M63-'Tracks Pull'!G63 -> -2.0334748 | R63: =IF(ISERROR(#REF!/'RETAIL Load Pull'!N63-1),"-",IF(ABS(#REF!/'RETAIL Load Pull'!N63-1)>1000%," - ",(#REF!/'RETAIL Load Pull'!N63-1))) -> - | U63: ='RETAIL Load Pull'!E63-'RETAIL Load Pull'!F63 -> 0.75007257 | V63: ='RETAIL Load Pull'!E63-'RETAIL Load Pull'!G63 -> 3.606034 | W63: =#REF!-N63 -> #REF! | Y63: =#REF!-'Tracks Pull'!M62 -> #REF! | AA63: =V63-'Tracks Pull'!O62 -> 3.606034 | AC63: ='Stream Pull'!F63 -> 0 | AD63: ='Stream Pull'!G63 -> 0 | AE63: ='Stream Pull'!H63 -> 0 | AF63: ='Stream Pull'!M63 -> 0 | AG63: =AC63+AF63 -> 0 | AH63: ='Consol Pull'!F63-'Consol Pull'!G63 -> 13.929592 | AI63: =AG63-AH63 -> -13.929592 | AK63: =I63+AG63 -> 7.5138676 | AM63: =AK63-E63 -> -36.951333 | AO63: ='FIRM Load Pull'!#REF! -> #REF! | AP63: =I63+AG63+AO63 -> #REF! | AQ63: =AP63-E63 -> #REF!
A64: Power | B64: MEA | C64: MEA | D64: MEA | E64: ='Consol Pull'!F64 -> 43.035596 | G64: =IF(ISERROR(E64/'Consol Pull'!T64-1),"-",IF(ABS(E64/'Consol Pull'!T64-1)>1000%," - ",(E64/'Consol Pull'!T64-1))) -> 0.0082342947 | I64: ='FIRM Load Pull'!E64 -> 5.5640735 | J64: ='Ship Load Pull'!E64 -> 5.8937716 | K64: =IF(ISERROR(I64/'FIRM Load Pull'!Q64-1),"-",IF(ABS(I64/'FIRM Load Pull'!Q64-1)>1000%," - ",(I64/'FIRM Load Pull'!Q64-1))) -> -0.3105798 | L64: ='FIRM Load Pull'!E64-'FIRM Load Pull'!F64 -> 0 | M64: ='FIRM Load Pull'!E64-'FIRM Load Pull'!G64 -> -1.1411706 | N64: ='Consol Pull'!G64 -> 34.260765 | O64: =I64-N64 -> -28.696692 | P64: =I64-'Tracks Pull'!E64 -> 5.5640735 | Q64: =M64-'Tracks Pull'!G64 -> -1.1411706 | R64: =IF(ISERROR(#REF!/'RETAIL Load Pull'!N64-1),"-",IF(ABS(#REF!/'RETAIL Load Pull'!N64-1)>1000%," - ",(#REF!/'RETAIL Load Pull'!N64-1))) -> - | U64: ='RETAIL Load Pull'!E64-'RETAIL Load Pull'!F64 -> -0.60354723 | V64: ='RETAIL Load Pull'!E64-'RETAIL Load Pull'!G64 -> -1.9673618 | W64: =#REF!-N64 -> #REF! | Y64: =#REF!-'Tracks Pull'!M63 -> #REF! | AA64: =V64-'Tracks Pull'!O63 -> -5.629045 | AC64: ='Stream Pull'!F64 -> 0 | AD64: ='Stream Pull'!G64 -> 0 | AE64: ='Stream Pull'!H64 -> 0 | AF64: ='Stream Pull'!M64 -> 0 | AG64: =AC64+AF64 -> 0 | AH64: ='Consol Pull'!F64-'Consol Pull'!G64 -> 8.7748303 | AI64: =AG64-AH64 -> -8.7748303 | AK64: =I64+AG64 -> 5.5640735 | AM64: =AK64-E64 -> -37.471522 | AO64: ='FIRM Load Pull'!#REF! -> #REF! | AP64: =I64+AG64+AO64 -> #REF! | AQ64: =AP64-E64 -> #REF!
A65: Power | B65: EMEA Top | C65: EMEA Top | D65: EMEA Top | E65: ='Consol Pull'!F65 -> 0 | I65: ='FIRM Load Pull'!E65 -> 0 | J65: ='Ship Load Pull'!E65 -> 0 | K65: =IF(ISERROR(I65/'FIRM Load Pull'!Q65-1),"-",IF(ABS(I65/'FIRM Load Pull'!Q65-1)>1000%," - ",(I65/'FIRM Load Pull'!Q65-1))) -> - | L65: ='FIRM Load Pull'!E65-'FIRM Load Pull'!F65 -> 0 | M65: ='FIRM Load Pull'!E65-'FIRM Load Pull'!G65 -> 0 | N65: ='Consol Pull'!G65 -> 0 | O65: =I65-N65 -> 0 | P65: =I65-'Tracks Pull'!E65 -> -17.84927 | Q65: =M65-'Tracks Pull'!G65 -> -3.0620486 | AC65: ='Stream Pull'!F65 -> 0 | AD65: ='Stream Pull'!G65 -> 0 | AE65: ='Stream Pull'!H65 -> 0 | AF65: ='Stream Pull'!M65 -> -0.0032178182
A66: Power | B66: Japan | C66: Japan | D66: Japan | E66: ='Consol Pull'!F66 -> 57.554961 | G66: =IF(ISERROR(E66/'Consol Pull'!T66-1),"-",IF(ABS(E66/'Consol Pull'!T66-1)>1000%," - ",(E66/'Consol Pull'!T66-1))) -> 0.1325402 | I66: ='FIRM Load Pull'!E66 -> 16.121618 | J66: ='Ship Load Pull'!E66 -> 9.335567 | K66: =IF(ISERROR(I66/'FIRM Load Pull'!Q66-1),"-",IF(ABS(I66/'FIRM Load Pull'!Q66-1)>1000%," - ",(I66/'FIRM Load Pull'!Q66-1))) -> 0.2523097 | L66: ='FIRM Load Pull'!E66-'FIRM Load Pull'!F66 -> 0.3431665 | M66: ='FIRM Load Pull'!E66-'FIRM Load Pull'!G66 -> 0.12639758 | N66: ='Consol Pull'!G66 -> 34.505811 | O66: =I66-N66 -> -18.384192 | P66: =I66-'Tracks Pull'!E66 -> -22.214581 | Q66: =M66-'Tracks Pull'!G66 -> -5.4262431 | R66: =IF(ISERROR(#REF!/'RETAIL Load Pull'!N66-1),"-",IF(ABS(#REF!/'RETAIL Load Pull'!N66-1)>1000%," - ",(#REF!/'RETAIL Load Pull'!N66-1))) -> - | U66: ='RETAIL Load Pull'!E66-'RETAIL Load Pull'!F66 -> 1.3526654 | V66: ='RETAIL Load Pull'!E66-'RETAIL Load Pull'!G66 -> 1.5596432 | W66: =#REF!-N66 -> #REF! | Y66: =#REF!-'Tracks Pull'!M65 -> #REF! | AA66: =V66-'Tracks Pull'!O65 -> -1.5024054 | AC66: ='Stream Pull'!F66 -> 4.8673881 | AD66: ='Stream Pull'!G66 -> 3.1210472 | AE66: ='Stream Pull'!H66 -> 1.7463409 | AF66: ='Stream Pull'!M66 -> 13.67 | AG66: =AC66+AF66 -> 18.537388 | AH66: ='Consol Pull'!F66-'Consol Pull'!G66 -> 23.04915 | AI66: =AG66-AH66 -> -4.511762 | AK66: =I66+AG66 -> 34.659007 | AM66: =AK66-E66 -> -22.895954 | AO66: ='FIRM Load Pull'!#REF! -> #REF! | AP66: =I66+AG66+AO66 -> #REF! | AQ66: =AP66-E66 -> #REF!
A67: Power | B67: APAC | C67: APAC | D67: APAC | E67: ='Consol Pull'!F67 -> 109.49074 | G67: =IF(ISERROR(E67/'Consol Pull'!T67-1),"-",IF(ABS(E67/'Consol Pull'!T67-1)>1000%," - ",(E67/'Consol Pull'!T67-1))) -> 0.15784321 | I67: ='FIRM Load Pull'!E67 -> 13.891208 | J67: ='Ship Load Pull'!E67 -> 9.4653747 | K67: =IF(ISERROR(I67/'FIRM Load Pull'!Q67-1),"-",IF(ABS(I67/'FIRM Load Pull'!Q67-1)>1000%," - ",(I67/'FIRM Load Pull'!Q67-1))) -> -0.40342531 | L67: ='FIRM Load Pull'!E67-'FIRM Load Pull'!F67 -> 0.060963687 | M67: ='FIRM Load Pull'!E67-'FIRM Load Pull'!G67 -> 0.61693642 | N67: ='Consol Pull'!G67 -> 81.027821 | O67: =I67-N67 -> -67.136613 | P67: =I67-'Tracks Pull'!E67 -> 3.7411398 | Q67: =M67-'Tracks Pull'!G67 -> -0.7224047 | R67: =IF(ISERROR(#REF!/'RETAIL Load Pull'!N67-1),"-",IF(ABS(#REF!/'RETAIL Load Pull'!N67-1)>1000%," - ",(#REF!/'RETAIL Load Pull'!N67-1))) -> - | U67: ='RETAIL Load Pull'!E67-'RETAIL Load Pull'!F67 -> -0.094343133 | V67: ='RETAIL Load Pull'!E67-'RETAIL Load Pull'!G67 -> 0.90366181 | W67: =#REF!-N67 -> #REF! | Y67: =#REF!-'Tracks Pull'!M66 -> #REF! | AA67: =V67-'Tracks Pull'!O66 -> -4.6489789 | AC67: ='Stream Pull'!F67 -> 13.57109 | AD67: ='Stream Pull'!G67 -> 2.5968146 | AE67: ='Stream Pull'!H67 -> 10.974276 | AF67: ='Stream Pull'!M67 -> 14.349492 | AG67: =AC67+AF67 -> 27.920582 | AH67: ='Consol Pull'!F67-'Consol Pull'!G67 -> 28.46292 | AI67: =AG67-AH67 -> -0.54233825 | AK67: =I67+AG67 -> 41.81179 | AM67: =AK67-E67 -> -67.678951 | AO67: ='FIRM Load Pull'!#REF! -> #REF! | AP67: =I67+AG67+AO67 -> #REF! | AQ67: =AP67-E67 -> #REF!
A68: Power | B68: ASE | C68: Asean | D68: Asean | E68: ='Consol Pull'!F68 -> 32.085914 | I68: ='FIRM Load Pull'!E68 -> 5.2196543 | J68: ='Ship Load Pull'!E68 -> 5.0122287 | K68: =IF(ISERROR(I68/'FIRM Load Pull'!Q68-1),"-",IF(ABS(I68/'FIRM Load Pull'!Q68-1)>1000%," - ",(I68/'FIRM Load Pull'!Q68-1))) -> -0.1824491 | L68: ='FIRM Load Pull'!E68-'FIRM Load Pull'!F68 -> 0 | M68: ='FIRM Load Pull'!E68-'FIRM Load Pull'!G68 -> 1.8003186 | N68: ='Consol Pull'!G68 -> 23.609576 | O68: =I68-N68 -> -18.389922 | P68: =I68-'Tracks Pull'!E68 -> 5.2196543 | Q68: =M68-'Tracks Pull'!G68 -> 1.8003186 | AC68: ='Stream Pull'!F68 -> 4.1414202 | AD68: ='Stream Pull'!G68 -> 1.2572724 | AE68: ='Stream Pull'!H68 -> 2.8841479 | AF68: ='Stream Pull'!M68 -> 4.3702448
A69: Power | B69: AZK | C69: Australia/NZ | D69: Australia/NZ | E69: ='Consol Pull'!F69 -> 13.782718 | G69: =IF(ISERROR(E69/'Consol Pull'!T68-1),"-",IF(ABS(E69/'Consol Pull'!T68-1)>1000%," - ",(E69/'Consol Pull'!T68-1))) -> -0.51035153 | I69: ='FIRM Load Pull'!E69 -> 0.43985423 | J69: ='Ship Load Pull'!E69 -> 0.47911556 | K69: =IF(ISERROR(I69/'FIRM Load Pull'!Q69-1),"-",IF(ABS(I69/'FIRM Load Pull'!Q69-1)>1000%," - ",(I69/'FIRM Load Pull'!Q69-1))) -> 0.013901633 | L69: ='FIRM Load Pull'!E69-'FIRM Load Pull'!F69 -> 0 | M69: ='FIRM Load Pull'!E69-'FIRM Load Pull'!G69 -> -0.08622954 | N69: ='Consol Pull'!G69 -> 10.459296 | O69: =I69-N69 -> -10.019441 | P69: =I69-'Tracks Pull'!E69 -> 0.43985423 | Q69: =M69-'Tracks Pull'!G69 -> -0.08622954 | R69: =IF(ISERROR(#REF!/'RETAIL Load Pull'!N68-1),"-",IF(ABS(#REF!/'RETAIL Load Pull'!N68-1)>1000%," - ",(#REF!/'RETAIL Load Pull'!N68-1))) -> - | U69: ='RETAIL Load Pull'!E68-'RETAIL Load Pull'!F68 -> 0 | V69: ='RETAIL Load Pull'!E68-'RETAIL Load Pull'!G68 -> 1.8784563 | W69: =#REF!-N69 -> #REF! | Y69: =#REF!-'Tracks Pull'!M67 -> #REF! | AA69: =V69-'Tracks Pull'!O67 -> 0.53911516 | AC69: ='Stream Pull'!F69 -> 1.3372388 | AD69: ='Stream Pull'!G69 -> 0.14084515 | AE69: ='Stream Pull'!H69 -> 1.1963937 | AF69: ='Stream Pull'!M69 -> 2.5467367 | AG69: =AC69+AF69 -> 3.8839755 | AH69: ='Consol Pull'!F68-'Consol Pull'!G68 -> 8.4763377 | AI69: =AG69-AH69 -> -4.5923622 | AK69: =I69+AG69 -> 4.3238298 | AM69: =AK69-E69 -> -9.4588886 | AO69: ='FIRM Load Pull'!#REF! -> #REF! | AP69: =I69+AG69+AO69 -> #REF! | AQ69: =AP69-E69 -> #REF!
A70: Power | B70: KOR | C70: Korea | D70: Korea | E70: ='Consol Pull'!F70 -> 26.872563 | I70: ='FIRM Load Pull'!E70 -> 6.5712911 | J70: ='Ship Load Pull'!E70 -> 2.7896126 | K70: =IF(ISERROR(I70/'FIRM Load Pull'!Q70-1),"-",IF(ABS(I70/'FIRM Load Pull'!Q70-1)>1000%," - ",(I70/'FIRM Load Pull'!Q70-1))) -> -0.46426617 | L70: ='FIRM Load Pull'!E70-'FIRM Load Pull'!F70 -> 0.060963688 | M70: ='FIRM Load Pull'!E70-'FIRM Load Pull'!G70 -> 1.3637805 | N70: ='Consol Pull'!G70 -> 20.762477 | O70: =I70-N70 -> -14.191185 | P70: =I70-'Tracks Pull'!E70 -> -1.5892757 | Q70: =M70-'Tracks Pull'!G70 -> 0.28113312 | AC70: ='Stream Pull'!F70 -> 1.9339032 | AD70: ='Stream Pull'!G70 -> 0.34409932 | AE70: ='Stream Pull'!H70 -> 1.5898039 | AF70: ='Stream Pull'!M70 -> 1.9729499
A71: Power | B71: ISA | C71: ISA | D71: ISA | E71: ='Consol Pull'!F71 -> 20.059092 | G71: =IF(ISERROR(E71/'Consol Pull'!T71-1),"-",IF(ABS(E71/'Consol Pull'!T71-1)>1000%," - ",(E71/'Consol Pull'!T71-1))) -> 0.67005484 | I71: ='FIRM Load Pull'!E71 -> 0.56562501 | J71: ='Ship Load Pull'!E71 -> -0.13764127 | K71: =IF(ISERROR(I71/'FIRM Load Pull'!Q71-1),"-",IF(ABS(I71/'FIRM Load Pull'!Q71-1)>1000%," - ",(I71/'FIRM Load Pull'!Q71-1))) -> -0.65142246 | L71: ='FIRM Load Pull'!E71-'FIRM Load Pull'!F71 -> 0 | M71: ='FIRM Load Pull'!E71-'FIRM Load Pull'!G71 -> -2.1180794 | N71: ='Consol Pull'!G71 -> 14.934802 | O71: =I71-N71 -> -14.369177 | P71: =I71-'Tracks Pull'!E71 -> -7.6619658 | Q71: =M71-'Tracks Pull'!G71 -> -3.1584702 | R71: =IF(ISERROR(#REF!/'RETAIL Load Pull'!N71-1),"-",IF(ABS(#REF!/'RETAIL Load Pull'!N71-1)>1000%," - ",(#REF!/'RETAIL Load Pull'!N71-1))) -> - | U71: ='RETAIL Load Pull'!E71-'RETAIL Load Pull'!F71 -> 0 | V71: ='RETAIL Load Pull'!E71-'RETAIL Load Pull'!G71 -> -1.423176 | W71: =#REF!-N71 -> #REF! | Y71: =#REF!-'Tracks Pull'!M70 -> #REF! | AA71: =V71-'Tracks Pull'!O70 -> -2.5058233 | AC71: ='Stream Pull'!F71 -> 2.5596313 | AD71: ='Stream Pull'!G71 -> 0.44732227 | AE71: ='Stream Pull'!H71 -> 2.112309 | AF71: ='Stream Pull'!M71 -> 2.8135392 | AG71: =AC71+AF71 -> 5.3731705 | AH71: ='Consol Pull'!F71-'Consol Pull'!G71 -> 5.1242907 | AI71: =AG71-AH71 -> 0.24887974 | AK71: =I71+AG71 -> 5.9387955 | AM71: =AK71-E71 -> -14.120297 | AO71: ='FIRM Load Pull'!#REF! -> #REF! | AP71: =I71+AG71+AO71 -> #REF! | AQ71: =AP71-E71 -> #REF!
A72: Power | B72: China | C72: China | D72: China | E72: ='Consol Pull'!F72 -> 21.464547 | G72: =IF(ISERROR(E72/'Consol Pull'!T72-1),"-",IF(ABS(E72/'Consol Pull'!T72-1)>1000%," - ",(E72/'Consol Pull'!T72-1))) -> 0.0063759569 | I72: ='FIRM Load Pull'!E72 -> 1.0947833 | J72: ='Ship Load Pull'!E72 -> 1.3220591 | K72: =IF(ISERROR(I72/'FIRM Load Pull'!Q72-1),"-",IF(ABS(I72/'FIRM Load Pull'!Q72-1)>1000%," - ",(I72/'FIRM Load Pull'!Q72-1))) -> -0.57533468 | L72: ='FIRM Load Pull'!E72-'FIRM Load Pull'!F72 -> 0 | M72: ='FIRM Load Pull'!E72-'FIRM Load Pull'!G72 -> -0.34285383 | N72: ='Consol Pull'!G72 -> 16.035765 | O72: =I72-N72 -> -14.940982 | P72: =I72-'Tracks Pull'!E72 -> 1.0947833 | Q72: =M72-'Tracks Pull'!G72 -> -0.34285383 | R72: =IF(ISERROR(#REF!/'RETAIL Load Pull'!N72-1),"-",IF(ABS(#REF!/'RETAIL Load Pull'!N72-1)>1000%," - ",(#REF!/'RETAIL Load Pull'!N72-1))) -> - | U72: ='RETAIL Load Pull'!E72-'RETAIL Load Pull'!F72 -> 0 | V72: ='RETAIL Load Pull'!E72-'RETAIL Load Pull'!G72 -> -0.0513125 | W72: =#REF!-N72 -> #REF! | Y72: =#REF!-'Tracks Pull'!M71 -> #REF! | AA72: =V72-'Tracks Pull'!O71 -> -1.0917033 | AC72: ='Stream Pull'!F72 -> 3.5988969 | AD72: ='Stream Pull'!G72 -> 0.40727551 | AE72: ='Stream Pull'!H72 -> 3.1916214 | AF72: ='Stream Pull'!M72 -> 2.6460211 | AG72: =AC72+AF72 -> 6.244918 | AH72: ='Consol Pull'!F72-'Consol Pull'!G72 -> 5.4287823 | AI72: =AG72-AH72 -> 0.81613569 | AK72: =I72+AG72 -> 7.3397013 | AM72: =AK72-E72 -> -14.124846 | AO72: ='FIRM Load Pull'!#REF! -> #REF! | AP72: =I72+AG72+AO72 -> #REF! | AQ72: =AP72-E72 -> #REF!
A73: Power | B73: APAC Top | C73: AP Top | D73: APAC Top | E73: ='Consol Pull'!F73 -> -4.7740941 | F73: =WW!E12 -> 938.76306 | G73: =WW!F12 -> -0.10855255 | H73: =WW!G12 -> 0 | I73: ='FIRM Load Pull'!E73 -> 0 | J73: ='Ship Load Pull'!E73 -> 0 | K73: =IF(ISERROR(I73/'FIRM Load Pull'!Q73-1),"-",IF(ABS(I73/'FIRM Load Pull'!Q73-1)>1000%," - ",(I73/'FIRM Load Pull'!Q73-1))) -> - | L73: ='FIRM Load Pull'!E73-'FIRM Load Pull'!F73 -> 0 | M73: ='FIRM Load Pull'!E73-'FIRM Load Pull'!G73 -> 0 | N73: ='Consol Pull'!G73 -> -4.7740941 | O73: =I73-N73 -> 4.7740941 | P73: =I73-'Tracks Pull'!E73 -> -407.69262 | Q73: =M73-'Tracks Pull'!G73 -> -82.172916 | R73: =WW!#REF! -> #REF! | S73: =WW!#REF! -> #REF! | T73: =WW!#REF! -> #REF! | U73: =WW!#REF! -> #REF! | V73: =WW!#REF! -> #REF! | W73: =WW!#REF! -> #REF! | X73: =WW!#REF! -> #REF! | Y73: =WW!#REF! -> #REF! | ... AB73: =WW!#REF! -> #REF! | AC73: ='Stream Pull'!F73 -> 0 | AD73: ='Stream Pull'!G73 -> 0 | AE73: ='Stream Pull'!H73 -> 0 | AF73: ='Stream Pull'!M73 -> 0 | AG73: =WW!Z12 -> 60.09463 | AH73: =WW!AA12 -> 21.219791 | AI73: =WW!AB12 -> 38.87484 | AJ73: =WW!AC12 -> 0 | AK73: =WW!AD12 -> 294.09434 | AL73: =WW!AE12 -> -0.68672144 | AM73: =WW!AF12 -> -542.76359
E74: ='Consol Pull'!F74 -> 0 | I74: ='FIRM Load Pull'!E74 -> 0 | J74: ='Ship Load Pull'!E74 -> 0 | K74: =IF(ISERROR(I74/'FIRM Load Pull'!Q74-1),"-",IF(ABS(I74/'FIRM Load Pull'!Q74-1)>1000%," - ",(I74/'FIRM Load Pull'!Q74-1))) -> - | L74: ='FIRM Load Pull'!E74-'FIRM Load Pull'!F74 -> 0 | M74: ='FIRM Load Pull'!E74-'FIRM Load Pull'!G74 -> 0 | N74: ='Consol Pull'!G74 -> 0 | O74: =I74-N74 -> 0 | P74: =I74-'Tracks Pull'!E74 -> 0 | Q74: =M74-'Tracks Pull'!G74 -> 0 | AC74: ='Stream Pull'!F74 -> 0 | AD74: ='Stream Pull'!G74 -> 0 | AE74: ='Stream Pull'!H74 -> 0 | AF74: ='Stream Pull'!M74 -> 0
A75: Storage | B75: WW | C75: WW | D75: Storage | E75: ='Consol Pull'!F75 -> 836.85793 | G75: =IF(ISERROR(E75/'Consol Pull'!T75-1),"-",IF(ABS(E75/'Consol Pull'!T75-1)>1000%," - ",(E75/'Consol Pull'!T75-1))) -> -0.10855255 | I75: ='FIRM Load Pull'!E75 -> 233.99971 | J75: ='Ship Load Pull'!E75 -> 159.49734 | K75: =IF(ISERROR(I75/'FIRM Load Pull'!Q75-1),"-",IF(ABS(I75/'FIRM Load Pull'!Q75-1)>1000%," - ",(I75/'FIRM Load Pull'!Q75-1))) -> 0.10525547 | L75: ='FIRM Load Pull'!E75-'FIRM Load Pull'!F75 -> 9.1554589 | M75: ='FIRM Load Pull'!E75-'FIRM Load Pull'!G75 -> 19.927302 | N75: ='Consol Pull'!G75 -> 815.63814 | O75: =I75-N75 -> -581.63843 | P75: =I75-'Tracks Pull'!E75 -> 233.99971 | Q75: =M75-'Tracks Pull'!G75 -> 19.927302 | R75: =#REF!/'RETAIL Load Pull'!N75 -> #REF! | U75: ='RETAIL Load Pull'!E75-'RETAIL Load Pull'!F75 -> 12.107496 | V75: ='RETAIL Load Pull'!E75-'RETAIL Load Pull'!G75 -> 48.63534 | W75: =#REF!-N75 -> #REF! | Y75: =#REF!-'Tracks Pull'!M73 -> #REF! | AA75: =V75-'Tracks Pull'!O73 -> -33.537575 | AC75: ='Stream Pull'!F75 -> 39.879983 | AD75: ='Stream Pull'!G75 -> -0.1200171 | AE75: ='Stream Pull'!H75 -> 0 | AF75: ='Stream Pull'!M75 -> 20.334665 | AG75: =AC75+AF75 -> 60.214648 | AH75: ='Consol Pull'!F75-'Consol Pull'!G75+AC75 -> 61.099774 | AI75: =AG75-AH75 -> -0.88512624 | AK75: =I75+AG75 -> 294.21436 | AM75: =AK75-E75 -> -542.64357 | AO75: ='FIRM Load Pull'!#REF! -> #REF! | AP75: =I75+AG75+AO75 -> #REF! | AQ75: =AP75-E75 -> #REF!
A76: Storage | B76: Sum of Geos | C76: Sum of Geos | D76: Sum of Geos | E76: ='Consol Pull'!F76 -> 794.91778 | G76: =IF(ISERROR(E76/'Consol Pull'!T76-1),"-",IF(ABS(E76/'Consol Pull'!T76-1)>1000%," - ",(E76/'Consol Pull'!T76-1))) -> -0.115082 | I76: ='FIRM Load Pull'!E76 -> 0 | J76: ='Ship Load Pull'!E76 -> 0 | K76: =IF(ISERROR(I76/'FIRM Load Pull'!Q76-1),"-",IF(ABS(I76/'FIRM Load Pull'!Q76-1)>1000%," - ",(I76/'FIRM Load Pull'!Q76-1))) -> - | L76: ='FIRM Load Pull'!E76-'FIRM Load Pull'!F76 -> 0 | M76: ='FIRM Load Pull'!E76-'FIRM Load Pull'!G76 -> 0 | N76: ='Consol Pull'!G76 -> 773.69799 | O76: =I76-N76 -> -773.69799 | P76: =I76-'Tracks Pull'!E76 -> -159.828 | Q76: =M76-'Tracks Pull'!G76 -> -30.011024 | R76: =IF(ISERROR(#REF!/'RETAIL Load Pull'!N76-1),"-",IF(ABS(#REF!/'RETAIL Load Pull'!N76-1)>1000%," - ",(#REF!/'RETAIL Load Pull'!N76-1))) -> - | U76: ='RETAIL Load Pull'!E76-'RETAIL Load Pull'!F76 -> 0 | V76: ='RETAIL Load Pull'!E76-'RETAIL Load Pull'!G76 -> 0 | W76: =#REF!-N76 -> #REF! | Y76: =#REF!-'Tracks Pull'!M74 -> #REF! | AA76: =V76-'Tracks Pull'!O74 -> 0 | AC76: ='Stream Pull'!F76 -> 0 | AD76: ='Stream Pull'!G76 -> 0 | AE76: ='Stream Pull'!H76 -> 0 | AF76: ='Stream Pull'!M76 -> 0 | AG76: =AC76+AF76 -> 0 | AH76: ='Consol Pull'!F76-'Consol Pull'!G76 -> 21.219791 | AI76: =AG76-AH76 -> -21.219791 | AK76: =I76+AG76 -> 0 | AM76: =AK76-E76 -> -794.91778 | AO76: ='FIRM Load Pull'!#REF! -> #REF! | AP76: =I76+AG76+AO76 -> #REF! | AQ76: =AP76-E76 -> #REF!
A77: Storage | B77: WW Top | C77: WW Top | D77: WW Top | E77: ='Consol Pull'!F77 -> 41.940156 | G77: =IF(ISERROR(E77/'Consol Pull'!T77-1),"-",IF(ABS(E77/'Consol Pull'!T77-1)>1000%," - ",(E77/'Consol Pull'!T77-1))) -> -0.13842941 | I77: ='FIRM Load Pull'!E77 -> 0 | J77: ='Ship Load Pull'!E77 -> 0 | K77: =IF(ISERROR(I77/'FIRM Load Pull'!Q77-1),"-",IF(ABS(I77/'FIRM Load Pull'!Q77-1)>1000%," - ",(I77/'FIRM Load Pull'!Q77-1))) -> - | L77: ='FIRM Load Pull'!E77-'FIRM Load Pull'!F77 -> 0 | M77: ='FIRM Load Pull'!E77-'FIRM Load Pull'!G77 -> 0 | N77: ='Consol Pull'!G77 -> 41.940156 | O77: =I77-N77 -> -41.940156 | P77: =I77-'Tracks Pull'!E77 -> -21.951207 | Q77: =M77-'Tracks Pull'!G77 -> -4.1877763 | R77: =IF(ISERROR(#REF!/'RETAIL Load Pull'!N77-1),"-",IF(ABS(#REF!/'RETAIL Load Pull'!N77-1)>1000%," - ",(#REF!/'RETAIL Load Pull'!N77-1))) -> - | U77: ='RETAIL Load Pull'!E77-'RETAIL Load Pull'!F77 -> 0 | V77: ='RETAIL Load Pull'!E77-'RETAIL Load Pull'!G77 -> 0 | W77: =#REF!-N77 -> #REF! | Y77: =#REF!-'Tracks Pull'!M75 -> #REF! | AA77: =V77-'Tracks Pull'!O75 -> 0 | AC77: ='Stream Pull'!F77 -> 40 | AD77: ='Stream Pull'!G77 -> 0 | AE77: ='Stream Pull'!H77 -> 0 | AF77: ='Stream Pull'!M77 -> 0 | AG77: =AC77+AF77 -> 40 | AH77: ='Consol Pull'!F77-'Consol Pull'!G77 -> 0 | AI77: =AG77-AH77 -> 40 | AK77: =I77+AG77 -> 40 | AM77: =AK77-E77 -> -1.9401556 | AO77: ='FIRM Load Pull'!#REF! -> #REF! | AP77: =I77+AG77+AO77 -> #REF! | AQ77: =AP77-E77 -> #REF!
A78: Storage | B78: Americas | C78: Americas | D78: Americas | E78: ='Consol Pull'!F78 -> 357.79325 | G78: =IF(ISERROR(E78/'Consol Pull'!T78-1),"-",IF(ABS(E78/'Consol Pull'!T78-1)>1000%," - ",(E78/'Consol Pull'!T78-1))) -> -0.0053950121 | I78: ='FIRM Load Pull'!E78 -> 97.061502 | J78: ='Ship Load Pull'!E78 -> 68.552021 | K78: =IF(ISERROR(I78/'FIRM Load Pull'!Q78-1),"-",IF(ABS(I78/'FIRM Load Pull'!Q78-1)>1000%," - ",(I78/'FIRM Load Pull'!Q78-1))) -> 0.073660265 | L78: ='FIRM Load Pull'!E78-'FIRM Load Pull'!F78 -> 3.2462507 | M78: ='FIRM Load Pull'!E78-'FIRM Load Pull'!G78 -> 3.2044904 | N78: ='Consol Pull'!G78 -> 350.96596 | O78: =I78-N78 -> -253.90446 | P78: =I78-'Tracks Pull'!E78 -> 97.04406 | Q78: =M78-'Tracks Pull'!G78 -> 3.2033177 | R78: =IF(ISERROR(#REF!/'RETAIL Load Pull'!N78-1),"-",IF(ABS(#REF!/'RETAIL Load Pull'!N78-1)>1000%," - ",(#REF!/'RETAIL Load Pull'!N78-1))) -> - | U78: ='RETAIL Load Pull'!E78-'RETAIL Load Pull'!F78 -> 0.21596277 | V78: ='RETAIL Load Pull'!E78-'RETAIL Load Pull'!G78 -> -1.4226306 | W78: =#REF!-N78 -> #REF! | Y78: =#REF!-'Tracks Pull'!M76 -> #REF! | AA78: =V78-'Tracks Pull'!O76 -> -31.433655 | AC78: ='Stream Pull'!F78 -> -0.12772239 | AD78: ='Stream Pull'!G78 -> -0.12772239 | AE78: ='Stream Pull'!H78 -> 0 | AF78: ='Stream Pull'!M78 -> 6.6008708 | AG78: =AC78+AF78 -> 6.4731484 | AH78: ='Consol Pull'!F78-'Consol Pull'!G78 -> 6.8272831 | AI78: =AG78-AH78 -> -0.3541347 | AK78: =I78+AG78 -> 103.53465 | AM78: =AK78-E78 -> -254.2586 | AO78: ='FIRM Load Pull'!#REF! -> #REF! | AP78: =I78+AG78+AO78 -> #REF! | AQ78: =AP78-E78 -> #REF!
A79: Storage | B79: 4A | C79: 4A | D79: US Industry | E79: ='Consol Pull'!F79 -> 49.711036 | G79: =IF(ISERROR(E79/'Consol Pull'!T79-1),"-",IF(ABS(E79/'Consol Pull'!T79-1)>1000%," - ",(E79/'Consol Pull'!T79-1))) -> - | I79: ='FIRM Load Pull'!E79 -> 30.183916 | J79: ='Ship Load Pull'!E79 -> 13.795128 | K79: =IF(ISERROR(I79/'FIRM Load Pull'!Q79-1),"-",IF(ABS(I79/'FIRM Load Pull'!Q79-1)>1000%," - ",(I79/'FIRM Load Pull'!Q79-1))) -> 1.7286715 | L79: ='FIRM Load Pull'!E79-'FIRM Load Pull'!F79 -> 2.7737487 | M79: ='FIRM Load Pull'!E79-'FIRM Load Pull'!G79 -> 1.6842228 | N79: ='Consol Pull'!G79 -> 49.25796 | O79: =I79-N79 -> -19.074044 | P79: =I79-'Tracks Pull'!E79 -> 4.3947139 | Q79: =M79-'Tracks Pull'!G79 -> -2.9244007 | R79: =IF(ISERROR(#REF!/'RETAIL Load Pull'!N79-1),"-",IF(ABS(#REF!/'RETAIL Load Pull'!N79-1)>1000%," - ",(#REF!/'RETAIL Load Pull'!N79-1))) -> - | U79: ='RETAIL Load Pull'!E79-'RETAIL Load Pull'!F79 -> 0.010079052 | V79: ='RETAIL Load Pull'!E79-'RETAIL Load Pull'!G79 -> 2.0363767 | W79: =#REF!-N79 -> #REF! | Y79: =#REF!-'Tracks Pull'!M77 -> #REF! | AA79: =V79-'Tracks Pull'!O77 -> -2.1513996 | AC79: ='Stream Pull'!F79 -> -0.12922272 | AD79: ='Stream Pull'!G79 -> -0.12922272 | AE79: ='Stream Pull'!H79 -> 0 | AF79: ='Stream Pull'!M79 -> 1.3223082 | AG79: =AC79+AF79 -> 1.1930855 | AH79: ='Consol Pull'!F79-'Consol Pull'!G79 -> 0.45307567 | AI79: =AG79-AH79 -> 0.74000982 | AK79: =I79+AG79 -> 31.377002 | AM79: =AK79-E79 -> -18.334034 | AO79: ='FIRM Load Pull'!#REF! -> #REF! | AP79: =I79+AG79+AO79 -> #REF! | AQ79: =AP79-E79 -> #REF!
A80: Storage | B80: 4O | C80: 4O | D80: US Build/Service Partners | E80: ='Consol Pull'!F80 -> 0.033233866 | G80: =IF(ISERROR(E80/'Consol Pull'!T80-1),"-",IF(ABS(E80/'Consol Pull'!T80-1)>1000%," - ",(E80/'Consol Pull'!T80-1))) -> - | I80: ='FIRM Load Pull'!E80 -> 0.05117715 | J80: ='Ship Load Pull'!E80 -> 0.05117715 | K80: =IF(ISERROR(I80/'FIRM Load Pull'!Q80-1),"-",IF(ABS(I80/'FIRM Load Pull'!Q80-1)>1000%," - ",(I80/'FIRM Load Pull'!Q80-1))) -> -0.99343439 | L80: ='FIRM Load Pull'!E80-'FIRM Load Pull'!F80 -> 0 | M80: ='FIRM Load Pull'!E80-'FIRM Load Pull'!G80 -> -0.00136613 | N80: ='Consol Pull'!G80 -> 0.17700889 | O80: =I80-N80 -> -0.12583174 | P80: =I80-'Tracks Pull'!E80 -> -43.827237 | Q80: =M80-'Tracks Pull'!G80 -> -8.7507579 | R80: =IF(ISERROR(#REF!/'RETAIL Load Pull'!N80-1),"-",IF(ABS(#REF!/'RETAIL Load Pull'!N80-1)>1000%," - ",(#REF!/'RETAIL Load Pull'!N80-1))) -> - | U80: ='RETAIL Load Pull'!E80-'RETAIL Load Pull'!F80 -> 0 | V80: ='RETAIL Load Pull'!E80-'RETAIL Load Pull'!G80 -> -0.00136613 | W80: =#REF!-N80 -> #REF! | Y80: =#REF!-'Tracks Pull'!M78 -> #REF! | AA80: =V80-'Tracks Pull'!O78 -> -0.0025388529 | AC80: ='Stream Pull'!F80 -> 0 | AD80: ='Stream Pull'!G80 -> 0 | AE80: ='Stream Pull'!H80 -> 0 | AF80: ='Stream Pull'!M80 -> 0.035560865 | AG80: =AC80+AF80 -> 0.035560865 | AH80: ='Consol Pull'!F80-'Consol Pull'!G80 -> -0.14377502 | AI80: =AG80-AH80 -> 0.17933589 | AK80: =I80+AG80 -> 0.086738015 | AM80: =AK80-E80 -> 0.053504149 | AO80: ='FIRM Load Pull'!#REF! -> #REF! | AP80: =I80+AG80+AO80 -> #REF! | AQ80: =AP80-E80 -> #REF!
A81: Storage | B81: 4J | C81: 4J | D81: US National | E81: ='Consol Pull'!F81 -> 54.776373 | G81: =IF(ISERROR(E81/'Consol Pull'!T81-1),"-",IF(ABS(E81/'Consol Pull'!T81-1)>1000%," - ",(E81/'Consol Pull'!T81-1))) -> - | I81: ='FIRM Load Pull'!E81 -> 24.647938 | J81: ='Ship Load Pull'!E81 -> 15.209081 | K81: =IF(ISERROR(I81/'FIRM Load Pull'!Q81-1),"-",IF(ABS(I81/'FIRM Load Pull'!Q81-1)>1000%," - ",(I81/'FIRM Load Pull'!Q81-1))) -> 0.43328447 | L81: ='FIRM Load Pull'!E81-'FIRM Load Pull'!F81 -> 0.29380122 | M81: ='FIRM Load Pull'!E81-'FIRM Load Pull'!G81 -> 1.9342456 | N81: ='Consol Pull'!G81 -> 52.942312 | O81: =I81-N81 -> -28.294373 | P81: =I81-'Tracks Pull'!E81 -> 10.118863 | Q81: =M81-'Tracks Pull'!G81 -> -0.77733293 | R81: =IF(ISERROR(#REF!/'RETAIL Load Pull'!N81-1),"-",IF(ABS(#REF!/'RETAIL Load Pull'!N81-1)>1000%," - ",(#REF!/'RETAIL Load Pull'!N81-1))) -> - | U81: ='RETAIL Load Pull'!E81-'RETAIL Load Pull'!F81 -> 0.67520973 | V81: ='RETAIL Load Pull'!E81-'RETAIL Load Pull'!G81 -> 3.576214 | W81: =#REF!-N81 -> #REF! | Y81: =#REF!-'Tracks Pull'!M79 -> #REF! | AA81: =V81-'Tracks Pull'!O79 -> -1.0324095 | AC81: ='Stream Pull'!F81 -> 0 | AD81: ='Stream Pull'!G81 -> 0 | AE81: ='Stream Pull'!H81 -> 0 | AF81: ='Stream Pull'!M81 -> 0.90719007 | AG81: =AC81+AF81 -> 0.90719007 | AH81: ='Consol Pull'!F81-'Consol Pull'!G81 -> 1.8340619 | AI81: =AG81-AH81 -> -0.92687186 | AK81: =I81+AG81 -> 25.555129 | AM81: =AK81-E81 -> -29.221245 | AO81: ='FIRM Load Pull'!#REF! -> #REF! | AP81: =I81+AG81+AO81 -> #REF! | AQ81: =AP81-E81 -> #REF!
A82: Storage | B82: 4L | C82: 4L | D82: FSS | E82: ='Consol Pull'!F82 -> 105.85835 | G82: =IF(ISERROR(E82/'Consol Pull'!T82-1),"-",IF(ABS(E82/'Consol Pull'!T82-1)>1000%," - ",(E82/'Consol Pull'!T82-1))) -> - | I82: ='FIRM Load Pull'!E82 -> 16.214778 | J82: ='Ship Load Pull'!E82 -> 15.915989 | K82: =IF(ISERROR(I82/'FIRM Load Pull'!Q82-1),"-",IF(ABS(I82/'FIRM Load Pull'!Q82-1)>1000%," - ",(I82/'FIRM Load Pull'!Q82-1))) -> -0.2471484 | L82: ='FIRM Load Pull'!E82-'FIRM Load Pull'!F82 -> 0 | M82: ='FIRM Load Pull'!E82-'FIRM Load Pull'!G82 -> -0.20558567 | N82: ='Consol Pull'!G82 -> 103.87062 | O82: =I82-N82 -> -87.655846 | P82: =I82-'Tracks Pull'!E82 -> 8.4878017 | Q82: =M82-'Tracks Pull'!G82 -> -1.5139104 | R82: =IF(ISERROR(#REF!/'RETAIL Load Pull'!N82-1),"-",IF(ABS(#REF!/'RETAIL Load Pull'!N82-1)>1000%," - ",(#REF!/'RETAIL Load Pull'!N82-1))) -> - | U82: ='RETAIL Load Pull'!E82-'RETAIL Load Pull'!F82 -> 0 | V82: ='RETAIL Load Pull'!E82-'RETAIL Load Pull'!G82 -> -8.3467885 | W82: =#REF!-N82 -> #REF! | Y82: =#REF!-'Tracks Pull'!M80 -> #REF! | AA82: =V82-'Tracks Pull'!O80 -> -17.09618 | AC82: ='Stream Pull'!F82 -> 0 | AD82: ='Stream Pull'!G82 -> 0 | AE82: ='Stream Pull'!H82 -> 0 | AF82: ='Stream Pull'!M82 -> 1.6085695 | AG82: =AC82+AF82 -> 1.6085695 | AH82: ='Consol Pull'!F82-'Consol Pull'!G82 -> 1.987722 | AI82: =AG82-AH82 -> -0.37915253 | AK82: =I82+AG82 -> 17.823348 | AM82: =AK82-E82 -> -88.034999 | AO82: ='FIRM Load Pull'!#REF! -> #REF! | AP82: =I82+AG82+AO82 -> #REF! | AQ82: =AP82-E82 -> #REF!
A83: Storage | B83: 4P | C83: 4P | D83: Public | E83: ='Consol Pull'!F83 -> 31.836055 | G83: =IF(ISERROR(E83/'Consol Pull'!T83-1),"-",IF(ABS(E83/'Consol Pull'!T83-1)>1000%," - ",(E83/'Consol Pull'!T83-1))) -> - | I83: ='FIRM Load Pull'!E83 -> 1.9831018 | J83: ='Ship Load Pull'!E83 -> 1.7086666 | K83: =IF(ISERROR(I83/'FIRM Load Pull'!Q83-1),"-",IF(ABS(I83/'FIRM Load Pull'!Q83-1)>1000%," - ",(I83/'FIRM Load Pull'!Q83-1))) -> -0.19422825 | L83: ='FIRM Load Pull'!E83-'FIRM Load Pull'!F83 -> 0.00414703 | M83: ='FIRM Load Pull'!E83-'FIRM Load Pull'!G83 -> -0.84564167 | N83: ='Consol Pull'!G83 -> 31.646446 | O83: =I83-N83 -> -29.663344 | P83: =I83-'Tracks Pull'!E83 -> 1.283217 | Q83: =M83-'Tracks Pull'!G83 -> -0.98783732 | R83: =IF(ISERROR(#REF!/'RETAIL Load Pull'!N83-1),"-",IF(ABS(#REF!/'RETAIL Load Pull'!N83-1)>1000%," - ",(#REF!/'RETAIL Load Pull'!N83-1))) -> - | U83: ='RETAIL Load Pull'!E83-'RETAIL Load Pull'!F83 -> -0.36458125 | V83: ='RETAIL Load Pull'!E83-'RETAIL Load Pull'!G83 -> -1.4395091 | W83: =#REF!-N83 -> #REF! | Y83: =#REF!-'Tracks Pull'!M81 -> #REF! | AA83: =V83-'Tracks Pull'!O81 -> -4.1510876 | AC83: ='Stream Pull'!F83 -> 0 | AD83: ='Stream Pull'!G83 -> 0 | AE83: ='Stream Pull'!H83 -> 0 | AF83: ='Stream Pull'!M83 -> 0.39531898 | AG83: =AC83+AF83 -> 0.39531898 | AH83: ='Consol Pull'!F83-'Consol Pull'!G83 -> 0.18960899 | AI83: =AG83-AH83 -> 0.20570999 | AK83: =I83+AG83 -> 2.3784208 | AM83: =AK83-E83 -> -29.457634 | AO83: ='FIRM Load Pull'!#REF! -> #REF! | AP83: =I83+AG83+AO83 -> #REF! | AQ83: =AP83-E83 -> #REF!
A84: Storage | B84: 4X | C84: 4X | D84: Federal | E84: ='Consol Pull'!F84 -> 14.869021 | I84: ='FIRM Load Pull'!E84 -> 9.421804 | J84: ='Ship Load Pull'!E84 -> 8.176437 | K84: =IF(ISERROR(I84/'FIRM Load Pull'!Q84-1),"-",IF(ABS(I84/'FIRM Load Pull'!Q84-1)>1000%," - ",(I84/'FIRM Load Pull'!Q84-1))) -> 1.2669718 | L84: ='FIRM Load Pull'!E84-'FIRM Load Pull'!F84 -> 0 | M84: ='FIRM Load Pull'!E84-'FIRM Load Pull'!G84 -> 1.8351771 | N84: ='Consol Pull'!G84 -> 14.869021 | O84: =I84-N84 -> -5.4472166 | P84: =I84-'Tracks Pull'!E84 -> -11.467787 | Q84: =M84-'Tracks Pull'!G84 -> -2.1407081 | R84: =IF(ISERROR(#REF!/'RETAIL Load Pull'!N84-1),"-",IF(ABS(#REF!/'RETAIL Load Pull'!N84-1)>1000%," - ",(#REF!/'RETAIL Load Pull'!N84-1))) -> - | U84: ='RETAIL Load Pull'!E84-'RETAIL Load Pull'!F84 -> 0 | V84: ='RETAIL Load Pull'!E84-'RETAIL Load Pull'!G84 -> 1.8327906 | W84: =#REF!-N84 -> #REF! | Y84: =#REF!-'Tracks Pull'!M82 -> #REF! | AA84: =V84-'Tracks Pull'!O82 -> 0.52446586 | AC84: ='Stream Pull'!F84 -> 0 | AD84: ='Stream Pull'!G84 -> 0 | AE84: ='Stream Pull'!H84 -> 0 | AF84: ='Stream Pull'!M84 -> 0.11960767 | AG84: =AC84+AF84 -> 0.11960767 | AH84: ='Consol Pull'!F84-'Consol Pull'!G84 -> 0 | AI84: =AG84-AH84 -> 0.11960767 | AK84: =I84+AG84 -> 9.5414117 | AM84: =AK84-E84 -> -5.327609
A85: Storage | B85: 4V | C85: 4V | D85: US Top | E85: ='Consol Pull'!F85 -> 2.0096295 | G85: =IF(ISERROR(E85/'Consol Pull'!T85-1),"-",IF(ABS(E85/'Consol Pull'!T85-1)>1000%," - ",(E85/'Consol Pull'!T85-1))) -> - | I85: ='FIRM Load Pull'!E85 -> -2.9409853 | J85: ='Ship Load Pull'!E85 -> 2.264797 | K85: =IF(ISERROR(I85/'FIRM Load Pull'!Q85-1),"-",IF(ABS(I85/'FIRM Load Pull'!Q85-1)>1000%," - ",(I85/'FIRM Load Pull'!Q85-1))) -> -0.16197027 | L85: ='FIRM Load Pull'!E85-'FIRM Load Pull'!F85 -> 0 | M85: ='FIRM Load Pull'!E85-'FIRM Load Pull'!G85 -> -1.0697253 | N85: ='Consol Pull'!G85 -> 1.7379147 | O85: =I85-N85 -> -4.6789001 | P85: =I85-'Tracks Pull'!E85 -> -27.28719 | Q85: =M85-'Tracks Pull'!G85 -> -5.3958009 | R85: =IF(ISERROR(#REF!/'RETAIL Load Pull'!N85-1),"-",IF(ABS(#REF!/'RETAIL Load Pull'!N85-1)>1000%," - ",(#REF!/'RETAIL Load Pull'!N85-1))) -> - | U85: ='RETAIL Load Pull'!E85-'RETAIL Load Pull'!F85 -> 0 | V85: ='RETAIL Load Pull'!E85-'RETAIL Load Pull'!G85 -> 1.6517064 | W85: =#REF!-N85 -> #REF! | Y85: =#REF!-'Tracks Pull'!M83 -> #REF! | AA85: =V85-'Tracks Pull'!O83 -> 1.5095107 | AC85: ='Stream Pull'!F85 -> 0 | AD85: ='Stream Pull'!G85 -> 0 | AE85: ='Stream Pull'!H85 -> 0 | AF85: ='Stream Pull'!M85 -> 0 | AG85: =AC85+AF85 -> 0 | AH85: ='Consol Pull'!F85-'Consol Pull'!G85 -> 0.27171475 | AI85: =AG85-AH85 -> -0.27171475 | AK85: =I85+AG85 -> -2.9409853 | AM85: =AK85-E85 -> -4.9506148 | AO85: ='FIRM Load Pull'!#REF! -> #REF! | AP85: =I85+AG85+AO85 -> #REF! | AQ85: =AP85-E85 -> #REF!
A86: Storage | B86: Canada | C86: Canada | D86: Canada | E86: ='Consol Pull'!F86 -> 46.862514 | G86: =IF(ISERROR(E86/'Consol Pull'!T86-1),"-",IF(ABS(E86/'Consol Pull'!T86-1)>1000%," - ",(E86/'Consol Pull'!T86-1))) -> 1.5610247 | I86: ='FIRM Load Pull'!E86 -> 1.8506284 | J86: ='Ship Load Pull'!E86 -> 1.9229538 | K86: =IF(ISERROR(I86/'FIRM Load Pull'!Q86-1),"-",IF(ABS(I86/'FIRM Load Pull'!Q86-1)>1000%," - ",(I86/'FIRM Load Pull'!Q86-1))) -> -0.27964747 | L86: ='FIRM Load Pull'!E86-'FIRM Load Pull'!F86 -> 0.05753946 | M86: ='FIRM Load Pull'!E86-'FIRM Load Pull'!G86 -> 0.07609453 | N86: ='Consol Pull'!G86 -> 46.652918 | O86: =I86-N86 -> -44.80229 | P86: =I86-'Tracks Pull'!E86 -> -166.24499 | Q86: =M86-'Tracks Pull'!G86 -> -39.913068 | R86: =IF(ISERROR(#REF!/'RETAIL Load Pull'!N86-1),"-",IF(ABS(#REF!/'RETAIL Load Pull'!N86-1)>1000%," - ",(#REF!/'RETAIL Load Pull'!N86-1))) -> - | U86: ='RETAIL Load Pull'!E86-'RETAIL Load Pull'!F86 -> -0.22175909 | V86: ='RETAIL Load Pull'!E86-'RETAIL Load Pull'!G86 -> 0.18200883 | W86: =#REF!-N86 -> #REF! | Y86: =#REF!-'Tracks Pull'!M84 -> #REF! | AA86: =V86-'Tracks Pull'!O84 -> -3.7938764 | AC86: ='Stream Pull'!F86 -> 0 | AD86: ='Stream Pull'!G86 -> 0 | AE86: ='Stream Pull'!H86 -> 0 | AF86: ='Stream Pull'!M86 -> 0.29029323 | AG86: =AC86+AF86 -> 0.29029323 | AH86: ='Consol Pull'!F86-'Consol Pull'!G86 -> 0.2095954 | AI86: =AG86-AH86 -> 0.080697826 | AK86: =I86+AG86 -> 2.1409216 | AM86: =AK86-E86 -> -44.721592 | AO86: ='FIRM Load Pull'!#REF! -> #REF! | AP86: =I86+AG86+AO86 -> #REF! | AQ86: =AP86-E86 -> #REF!
A87: Storage | B87: LA | C87: LA | D87: LA | E87: ='Consol Pull'!F87 -> 51.837039 | G87: =IF(ISERROR(E87/'Consol Pull'!T87-1),"-",IF(ABS(E87/'Consol Pull'!T87-1)>1000%," - ",(E87/'Consol Pull'!T87-1))) -> -0.082272022 | I87: ='FIRM Load Pull'!E87 -> 15.649143 | J87: ='Ship Load Pull'!E87 -> 9.5077912 | K87: =IF(ISERROR(I87/'FIRM Load Pull'!Q87-1),"-",IF(ABS(I87/'FIRM Load Pull'!Q87-1)>1000%," - ",(I87/'FIRM Load Pull'!Q87-1))) -> -0.42327317 | L87: ='FIRM Load Pull'!E87-'FIRM Load Pull'!F87 -> 0.11701433 | M87: ='FIRM Load Pull'!E87-'FIRM Load Pull'!G87 -> -0.20293074 | N87: ='Consol Pull'!G87 -> 49.81176 | O87: =I87-N87 -> -34.162616 | P87: =I87-'Tracks Pull'!E87 -> -28.443272 | Q87: =M87-'Tracks Pull'!G87 -> -10.712161 | R87: =IF(ISERROR(#REF!/'RETAIL Load Pull'!N87-1),"-",IF(ABS(#REF!/'RETAIL Load Pull'!N87-1)>1000%," - ",(#REF!/'RETAIL Load Pull'!N87-1))) -> - | U87: ='RETAIL Load Pull'!E87-'RETAIL Load Pull'!F87 -> 0.11701433 | V87: ='RETAIL Load Pull'!E87-'RETAIL Load Pull'!G87 -> -0.91406342 | W87: =#REF!-N87 -> #REF! | Y87: =#REF!-'Tracks Pull'!M85 -> #REF! | AA87: =V87-'Tracks Pull'!O85 -> -5.240139 | AC87: ='Stream Pull'!F87 -> 0.00150033 | AD87: ='Stream Pull'!G87 -> 0.00150033 | AE87: ='Stream Pull'!H87 -> 0 | AF87: ='Stream Pull'!M87 -> 1.9220223 | AG87: =AC87+AF87 -> 1.9235226 | AH87: ='Consol Pull'!F87-'Consol Pull'!G87 -> 2.0252794 | AI87: =AG87-AH87 -> -0.10175675 | AK87: =I87+AG87 -> 17.572666 | AM87: =AK87-E87 -> -34.264373 | AO87: ='FIRM Load Pull'!#REF! -> #REF! | AP87: =I87+AG87+AO87 -> #REF! | AQ87: =AP87-E87 -> #REF!
A88: Storage | B88: EMEA | C88: EMEA | D88: EMEA | E88: ='Consol Pull'!F88 -> 296.30689 | G88: =IF(ISERROR(E88/'Consol Pull'!T88-1),"-",IF(ABS(E88/'Consol Pull'!T88-1)>1000%," - ",(E88/'Consol Pull'!T88-1))) -> -0.21692054 | I88: ='FIRM Load Pull'!E88 -> 88.554956 | J88: ='Ship Load Pull'!E88 -> 65.737111 | K88: =IF(ISERROR(I88/'FIRM Load Pull'!Q88-1),"-",IF(ABS(I88/'FIRM Load Pull'!Q88-1)>1000%," - ",(I88/'FIRM Load Pull'!Q88-1))) -> 0.093600409 | L88: ='FIRM Load Pull'!E88-'FIRM Load Pull'!F88 -> 5.2968358 | M88: ='FIRM Load Pull'!E88-'FIRM Load Pull'!G88 -> 5.653411 | N88: ='Consol Pull'!G88 -> 290.40707 | O88: =I88-N88 -> -201.85212 | P88: =I88-'Tracks Pull'!E88 -> 74.576087 | Q88: =M88-'Tracks Pull'!G88 -> 2.3478135 | R88: =IF(ISERROR(#REF!/'RETAIL Load Pull'!N88-1),"-",IF(ABS(#REF!/'RETAIL Load Pull'!N88-1)>1000%," - ",(#REF!/'RETAIL Load Pull'!N88-1))) -> - | U88: ='RETAIL Load Pull'!E88-'RETAIL Load Pull'!F88 -> 13.696938 | V88: ='RETAIL Load Pull'!E88-'RETAIL Load Pull'!G88 -> 47.513111 | W88: =#REF!-N88 -> #REF! | Y88: =#REF!-'Tracks Pull'!M86 -> #REF! | AA88: =V88-'Tracks Pull'!O86 -> 7.5239486 | AC88: ='Stream Pull'!F88 -> -0.00012742 | AD88: ='Stream Pull'!G88 -> -0.00012742 | AE88: ='Stream Pull'!H88 -> 0 | AF88: ='Stream Pull'!M88 -> 5.8042714 | AG88: =AC88+AF88 -> 5.804144 | AH88: ='Consol Pull'!F88-'Consol Pull'!G88 -> 5.8998209 | AI88: =AG88-AH88 -> -0.095676892 | AK88: =I88+AG88 -> 94.3591 | AM88: =AK88-E88 -> -201.94779 | AO88: ='FIRM Load Pull'!#REF! -> #REF! | AP88: =I88+AG88+AO88 -> #REF! | AQ88: =AP88-E88 -> #REF!
A89: Storage | B89: Dach | C89: Dach | D89: Dach | E89: ='Consol Pull'!F89 -> 76.60987 | G89: =IF(ISERROR(E89/'Consol Pull'!T89-1),"-",IF(ABS(E89/'Consol Pull'!T89-1)>1000%," - ",(E89/'Consol Pull'!T89-1))) -> -0.21917521 | I89: ='FIRM Load Pull'!E89 -> 20.156544 | J89: ='Ship Load Pull'!E89 -> 14.262814 | K89: =IF(ISERROR(I89/'FIRM Load Pull'!Q89-1),"-",IF(ABS(I89/'FIRM Load Pull'!Q89-1)>1000%," - ",(I89/'FIRM Load Pull'!Q89-1))) -> 0.46953821 | L89: ='FIRM Load Pull'!E89-'FIRM Load Pull'!F89 -> 0.22000885 | M89: ='FIRM Load Pull'!E89-'FIRM Load Pull'!G89 -> -1.7489191 | N89: ='Consol Pull'!G89 -> 75.944123 | O89: =I89-N89 -> -55.787579 | P89: =I89-'Tracks Pull'!E89 -> -0.12038064 | Q89: =M89-'Tracks Pull'!G89 -> -6.5558426 | R89: =IF(ISERROR(#REF!/'RETAIL Load Pull'!N89-1),"-",IF(ABS(#REF!/'RETAIL Load Pull'!N89-1)>1000%," - ",(#REF!/'RETAIL Load Pull'!N89-1))) -> - | U89: ='RETAIL Load Pull'!E89-'RETAIL Load Pull'!F89 -> 0.37262345 | V89: ='RETAIL Load Pull'!E89-'RETAIL Load Pull'!G89 -> 3.6567051 | W89: =#REF!-N89 -> #REF! | Y89: =#REF!-'Tracks Pull'!M87 -> #REF! | AA89: =V89-'Tracks Pull'!O87 -> -6.8525247 | AC89: ='Stream Pull'!F89 -> -0.00483513 | AD89: ='Stream Pull'!G89 -> -0.00483513 | AE89: ='Stream Pull'!H89 -> 0 | AF89: ='Stream Pull'!M89 -> 0.59657326 | AG89: =AC89+AF89 -> 0.59173813 | AH89: ='Consol Pull'!F89-'Consol Pull'!G89 -> 0.66574778 | AI89: =AG89-AH89 -> -0.074009644 | AK89: =I89+AG89 -> 20.748282 | AM89: =AK89-E89 -> -55.861589 | AO89: ='FIRM Load Pull'!#REF! -> #REF! | AP89: =I89+AG89+AO89 -> #REF! | AQ89: =AP89-E89 -> #REF!
A90: Storage | B90: France | C90: France | D90: France | E90: ='Consol Pull'!F90 -> 24.831877 | G90: =IF(ISERROR(E90/'Consol Pull'!T90-1),"-",IF(ABS(E90/'Consol Pull'!T90-1)>1000%," - ",(E90/'Consol Pull'!T90-1))) -> -0.17509166 | I90: ='FIRM Load Pull'!E90 -> 10.849738 | J90: ='Ship Load Pull'!E90 -> 10.162157 | K90: =IF(ISERROR(I90/'FIRM Load Pull'!Q90-1),"-",IF(ABS(I90/'FIRM Load Pull'!Q90-1)>1000%," - ",(I90/'FIRM Load Pull'!Q90-1))) -> 2.2291187 | L90: ='FIRM Load Pull'!E90-'FIRM Load Pull'!F90 -> 0.0428372 | M90: ='FIRM Load Pull'!E90-'FIRM Load Pull'!G90 -> 0.17912723 | N90: ='Consol Pull'!G90 -> 24.382693 | O90: =I90-N90 -> -13.532955 | P90: =I90-'Tracks Pull'!E90 -> -1.1439515 | Q90: =M90-'Tracks Pull'!G90 -> -2.6774503 | R90: =IF(ISERROR(#REF!/'RETAIL Load Pull'!N90-1),"-",IF(ABS(#REF!/'RETAIL Load Pull'!N90-1)>1000%," - ",(#REF!/'RETAIL Load Pull'!N90-1))) -> - | U90: ='RETAIL Load Pull'!E90-'RETAIL Load Pull'!F90 -> 1.3283836 | V90: ='RETAIL Load Pull'!E90-'RETAIL Load Pull'!G90 -> 7.3408383 | W90: =#REF!-N90 -> #REF! | Y90: =#REF!-'Tracks Pull'!M88 -> #REF! | AA90: =V90-'Tracks Pull'!O88 -> 4.0352409 | AC90: ='Stream Pull'!F90 -> 0 | AD90: ='Stream Pull'!G90 -> 0 | AE90: ='Stream Pull'!H90 -> 0 | AF90: ='Stream Pull'!M90 -> 0.44409983 | AG90: =AC90+AF90 -> 0.44409983 | AH90: ='Consol Pull'!F90-'Consol Pull'!G90 -> 0.44918326 | AI90: =AG90-AH90 -> -0.0050834247 | AK90: =I90+AG90 -> 11.293838 | AM90: =AK90-E90 -> -13.538039 | AO90: ='FIRM Load Pull'!#REF! -> #REF! | AP90: =I90+AG90+AO90 -> #REF! | AQ90: =AP90-E90 -> #REF!
A91: Storage | B91: UKI | C91: UKI | D91: UKI | E91: ='Consol Pull'!F91 -> 35.864668 | G91: =IF(ISERROR(E91/'Consol Pull'!T91-1),"-",IF(ABS(E91/'Consol Pull'!T91-1)>1000%," - ",(E91/'Consol Pull'!T91-1))) -> -0.4279136 | I91: ='FIRM Load Pull'!E91 -> 6.4623853 | J91: ='Ship Load Pull'!E91 -> 6.7017599 | K91: =IF(ISERROR(I91/'FIRM Load Pull'!Q91-1),"-",IF(ABS(I91/'FIRM Load Pull'!Q91-1)>1000%," - ",(I91/'FIRM Load Pull'!Q91-1))) -> 0.1179156 | L91: ='FIRM Load Pull'!E91-'FIRM Load Pull'!F91 -> 0 | M91: ='FIRM Load Pull'!E91-'FIRM Load Pull'!G91 -> 0.17310207 | N91: ='Consol Pull'!G91 -> 35.227159 | O91: =I91-N91 -> -28.764774 | P91: =I91-'Tracks Pull'!E91 -> -7.815698 | Q91: =M91-'Tracks Pull'!G91 -> -3.2275571 | R91: =IF(ISERROR(#REF!/'RETAIL Load Pull'!N91-1),"-",IF(ABS(#REF!/'RETAIL Load Pull'!N91-1)>1000%," - ",(#REF!/'RETAIL Load Pull'!N91-1))) -> - | U91: ='RETAIL Load Pull'!E91-'RETAIL Load Pull'!F91 -> 0.32849799 | V91: ='RETAIL Load Pull'!E91-'RETAIL Load Pull'!G91 -> 7.4973853 | W91: =#REF!-N91 -> #REF! | Y91: =#REF!-'Tracks Pull'!M89 -> #REF! | AA91: =V91-'Tracks Pull'!O89 -> 2.6904618 | AC91: ='Stream Pull'!F91 -> 0 | AD91: ='Stream Pull'!G91 -> 0 | AE91: ='Stream Pull'!H91 -> 0 | AF91: ='Stream Pull'!M91 -> 0.6373772 | AG91: =AC91+AF91 -> 0.6373772 | AH91: ='Consol Pull'!F91-'Consol Pull'!G91 -> 0.63750874 | AI91: =AG91-AH91 -> -0.00013153584 | AK91: =I91+AG91 -> 7.0997625 | AM91: =AK91-E91 -> -28.764905 | AO91: ='FIRM Load Pull'!#REF! -> #REF! | AP91: =I91+AG91+AO91 -> #REF! | AQ91: =AP91-E91 -> #REF!
